Workbook

Sheet Inputs
A1: INPUTS | B1: Отрасль | C1: Подотрасль/ Дивизион | D1: Источник | E1: Дата обновления | F1: Наименование | G1: Ед. измерения | H1: Link | I1: Комментарий к заполнению (формула) | J1: 2001 | K1: 2002 | L1: 2003 | M1: 2004 | N1: 2005 | O1: 2006 | P1: 2007 | Q1: 2008 | R1: 2009 | S1: 2010 | T1: 2011 | U1: 2012 | V1: 2013 | W1: 2014 | X1: 2015 | Y1: 2016 | Z1: 2017 | AA1: 2018 | AB1: 2019 | AC1: 2020 | AD1: 2021 | AE1: 2022 | AF1: 2023 | AG1: 2024 | AH1: 2025 | AI1: 2026 | AJ1: 2027 | AK1: 2028 | AL1: 2029 | AM1: 2030 | AN1: 2031 | AO1: 2032 | AP1: 2033 | AQ1: 2034 | AR1: 2035 | AS1: 2036 | AT1: 2037 | AU1: 2038 | AV1: 2039 | AW1: 2040 | AX1: 2041 | AY1: 2042 | AZ1: 2043 | BA1: 2044 | BB1: 2045 | BC1: 2046 | BD1: 2047 | BE1: 2048 | BF1: 2049 | BG1: 2050
A2: Общие | D2: ЦМИ | F2: Рост реального ВВП | G2: % | H2: Наименование листа, номер строки [например: Scenarios, line 352] | I2: Базовый 11.09.2026 | J2: 0.051 | K2: 0.047 | L2: 0.072956141 | M2: 0.07175933 | N2: 0.063764415 | O2: 0.081534248 | P2: 0.085350329 | Q2: 0.052477517 | R2: -0.078208582 | S2: 0.045037137 | T2: 0.042643516 | U2: 0.036559016 | V2: 0.017853545 | W2: 0.0073860077 | X2: -0.025383168 | Y2: 0.0028878412 | Z2: 0.016468837 | AA2: 0.028063408 | AB2: 0.020329827 | AC2: -0.026536545 | AD2: 0.059 | AE2: -0.014359355 | AF2: 0.0407 | AG2: 0.0492 | AH2: 0.01 | AI2: 0.0063 | AJ2: 0.0139 | AK2: 0.0163 | AL2: 0.0182 | AM2: 0.0182 | AN2: =AM2 -> 0.0182 | AO2: =AN2 -> 0.0182 | AP2: =AO2 -> 0.0182 | AQ2: =AP2 -> 0.0182 | AR2: =AQ2 -> 0.0182 | AS2: =AR2 -> 0.0182 | AT2: =AS2 -> 0.0182 | AU2: =AT2 -> 0.0182 | ... BG2: =BF2 -> 0.0182
A3: Общие | D3: ЦМИ | F3: Инфляция - Рост индекса потребительских цен (RUB, eop CPI) | G3: % | I3: С 2021 года прогноз CIB | J3: 0.1858 | K3: 0.1506 | L3: 0.1199 | M3: 0.1173 | N3: 0.1092 | O3: 0.09 | P3: 0.1187 | Q3: 0.1328 | R3: 0.088 | S3: 0.0878 | T3: 0.061 | U3: 0.066 | V3: 0.065 | W3: 0.1135 | X3: 0.1291 | Y3: 0.0539 | Z3: 0.0251 | AA3: 0.0426 | AB3: 0.0304 | AC3: 0.0491 | AD3: 0.083930153 | AE3: 0.11922836 | AF3: 0.0742 | AG3: 0.0952 | AH3: 0.0559 | AI3: 0.067380961 | AJ3: 0.047439689 | AK3: 0.040050205 | AL3: 0.039847139 | AM3: 0.03995079 | AN3: 0.04 | AO3: =AN3 -> 0.04 | AP3: =AO3 -> 0.04 | AQ3: =AP3 -> 0.04 | AR3: =AQ3 -> 0.04 | AS3: =AR3 -> 0.04 | AT3: =AS3 -> 0.04 | AU3: =AT3 -> 0.04 | AV3: =AU3 -> 0.04 | ... BG3: =BF3 -> 0.04
A4: Общие | D4: CIB Research | F4: Инфляция - Рост индекса потребительских цен в США, в долларах США (USD, eop CPI) | G4: % | I4: EoY PCE, source: FX/IR team | J4: 0.0172429 | K4: 0.0172766 | L4: 0.0141467 | M4: 0.021474 | N4: 0.0219964 | O4: 0.0222292 | P4: 0.0233468 | Q4: 0.0135128 | R4: 0.0161556 | S4: 0.0090211 | T4: 0.0205826 | U4: 0.0171363 | V4: 0.016331 | W4: 0.0075649327 | X4: 0.0063871458 | Y4: 0.020507924 | Z4: 0.021299357 | AA4: 0.020023707 | AB4: 0.023195291 | AC4: 0.013049536 | AD4: 0.071765966 | AE4: 0.064115004 | AF4: 0.03323156 | AG4: 0.028723677 | AH4: 0.026899449 | AI4: 0.027326387 | AJ4: 0.026069089 | AK4: 0.022921913 | AL4: 0.01939121 | AM4: 0.02235396 | AN4: 0.02 | AO4: 0.02 | AP4: 0.02 | AQ4: 0.02 | AR4: 0.02 | AS4: 0.02 | AT4: 0.02 | AU4: 0.02 | AV4: 0.02 | AW4: 0.02 | AX4: 0.02 | AY4: 0.02 | AZ4: 0.02 | BA4: 0.02 | BB4: 0.02 | BC4: =BB4 -> 0.02 | BD4: =BC4 -> 0.02 | BE4: =BD4 -> 0.02 | BF4: =BE4 -> 0.02 | BG4: =BF4 -> 0.02
A5: Общие | D5: ЦМИ | F5: Инфляция - Рост индекса цен производителей (RUB, eop PPI) | G5: % | I5: С 2021 года прогноз CIB | J5: 0.0833 | K5: 0.1765 | L5: 0.1254 | M5: 0.2883 | N5: 0.1335 | O5: 0.1037 | P5: 0.2507 | Q5: -0.07 | R5: 0.1385 | S5: 0.1666 | T5: 0.1201 | U5: 0.051 | V5: 0.0346 | W5: 0.0628 | X5: 0.1214 | Y5: 0.0745 | Z5: 0.0837 | AA5: 0.1171 | AB5: -0.0426 | AC5: 0.0356 | AD5: 0.2852 | AE5: -0.033181437 | AF5: 0.1916 | AG5: 0.0791 | AH5: -0.0328 | AI5: 0.12373075 | AJ5: 0.048265541 | AK5: 0.087119187 | AL5: 0.053103144 | AM5: 0.056887074 | AN5: 0.04 | AO5: =AN5 -> 0.04 | AP5: =AO5 -> 0.04 | AQ5: =AP5 -> 0.04 | AR5: =AQ5 -> 0.04 | AS5: =AR5 -> 0.04 | AT5: =AS5 -> 0.04 | AU5: =AT5 -> 0.04 | AV5: =AU5 -> 0.04 | ... BG5: =BF5 -> 0.04
A6: Общие | D6: ЦМИ | F6: Инфляция - Дефлятор ВВП (RUB, GDP Deflator) | G6: % | I6: =0.8CPI+0.2PPI; С 2021 года прогноз CIB | J6: 0.16489519 | K6: 0.15613926 | L6: 0.13780061 | M6: 0.20282077 | N6: 0.19306095 | O6: 0.15170047 | P6: 0.13804421 | Q6: 0.17959714 | R6: 0.019937228 | S6: 0.14187039 | T6: 0.15914448 | U6: 0.074 | V6: 0.05 | W6: 0.089 | X6: 0.079 | Y6: 0.035158922 | Z6: 0.044 | AA6: 0.099989476 | AB6: 0.030841738 | AC6: 0.0089826982 | AD6: 0.182 | AE6: 0.182 | AF6: 0.067 | AG6: 0.107 | AH6: 0.049 | AI6: 0.076830584 | AJ6: 0.033790794 | AK6: 0.052796743 | AL6: 0.063195192 | AM6: 0.048456871 | AN6: =0.8*AN3+0.2*AN5 -> 0.04 | AO6: =0.8*AO3+0.2*AO5 -> 0.04 | AP6: =0.8*AP3+0.2*AP5 -> 0.04 | AQ6: =0.8*AQ3+0.2*AQ5 -> 0.04 | AR6: =0.8*AR3+0.2*AR5 -> 0.04 | AS6: =0.8*AS3+0.2*AS5 -> 0.04 | AT6: =0.8*AT3+0.2*AT5 -> 0.04 | AU6: =0.8*AU3+0.2*AU5 -> 0.04 | ... BG6: =0.8*BG3+0.2*BG5 -> 0.04
A7: Общие | D7: Расчет | F7: Курс рубля к доллару США в конце года (eop USD/RUB) | G7: $/руб | I7: 2015-17 модель ЦМИ c ценой на нефть CIB Research, после - CIB Research, с 2019 года прогноз CIB; =предыдущий год*1.02 | J7: 30.14 | K7: 31.78 | L7: 29.45 | M7: 27.75 | N7: 28.78 | O7: 26.33 | P7: 24.55 | Q7: 29.38 | R7: 30.24 | S7: 30.48 | T7: 32.2 | U7: 30.37 | V7: 32.73 | W7: 56.2584 | X7: 72.8827 | Y7: 60.6569 | Z7: 57.6002 | AA7: 69.4706 | AB7: 61.9057 | AC7: 73.8757 | AD7: 74.2926 | AE7: 70.3375 | AF7: 89.69 | AG7: 101.68 | AH7: 78.23 | AI7: 88.047138 | AJ7: 93.201775 | AK7: 97.205694 | AL7: 101.36373 | AM7: 105.70549 | AN7: =AN14 -> 105.95911 | AO7: =AO14 -> 108.07829 | AP7: =AP14 -> 110.23985 | AQ7: =AQ14 -> 112.44465 | AR7: =AR14 -> 114.69354 | AS7: =AS14 -> 116.98741 | AT7: =AT14 -> 119.32716 | AU7: =AU14 -> 121.71371 | ... BG7: =BG14 -> 154.36241
A8: Общие | D8: Расчет | F8: Курс рубля к EUR в конце года (eop EUR/RUB) | G8: EUR/руб | I8: =EUR/USD*курс доллара | J8: 26.49 | K8: 33.11 | L8: 36.82 | M8: 37.81 | N8: 34.19 | O8: 34.7 | P8: 35.93 | Q8: 41.44 | R8: 43.39 | S8: 40.33 | T8: 41.67 | U8: 40.23 | V8: 44.97 | W8: 68.34 | X8: 79.56 | Y8: 63.8111 | Z8: 68.8668 | AA8: 79.4605 | AB8: 69.3406 | AC8: 90.6824 | AD8: 84.0695 | AE8: 75.6553 | AF8: 99.2 | AG8: 106.1028 | AH8: 92.097683 | AI8: =AI7*AI36 -> 102.13468 | AJ8: =AJ7*AJ36 -> 107.18204 | AK8: =AK7*AK36 -> 111.78655 | AL8: =AL7*AL36 -> 116.56829 | AM8: =AM7*AM36 -> 121.56131 | AN8: =AN7*AN36 -> 121.83983 | AO8: =AO7*AO36 -> 124.27662 | AP8: =AP7*AP36 -> 126.76215 | ... BG8: =BG7*BG36 -> 177.49762
A9: Общие | D9: ЦМИ | F9: Рост реальных расп. денежных доходов населения | G9: % | I9: С 2021 года прогноз CIB | J9: 0.087 | K9: 0.111 | L9: 0.15 | M9: 0.104 | N9: 0.124 | O9: 0.135 | P9: 0.121 | Q9: 0.024 | R9: 0.03 | S9: 0.059 | T9: 0.005 | U9: 0.058 | V9: 0.048 | W9: -0.012 | X9: -0.024 | Y9: -0.045 | Z9: -0.005 | AA9: 0.00675 | AB9: 0.01125 | AC9: -0.01975 | AD9: 0.032167843 | AE9: 0.045 | AF9: 0.060855091 | AG9: 0.082218231 | AH9: 0.074745567 | AI9: 0.019344246 | AJ9: 0.051262825 | AK9: 0.022596442 | AL9: 0.021191425 | AM9: 0.021023688 | AN9: =AM9 -> 0.021023688 | AO9: =AN9 -> 0.021023688 | AP9: =AO9 -> 0.021023688 | AQ9: =AP9 -> 0.021023688 | AR9: =AQ9 -> 0.021023688 | AS9: =AR9 -> 0.021023688 | AT9: =AS9 -> 0.021023688 | AU9: =AT9 -> 0.021023688 | ... BG9: =BF9 -> 0.021023688
A10: Общие | D10: ЦМИ | F10: Ставка Libor 3m | G10: % | I10: ЦМИ, 2022 и далее = 2021 | J10: 0.0188125 | K10: 0.0138 | L10: 0.0115188 | M10: 0.0256438 | N10: 0.0453625 | O10: 0.0536 | P10: 0.047025 | Q10: 0.01425 | R10: 0.0025063 | S10: 0.0030281 | T10: 0.00581 | U10: 0.0043006071 | V10: 0.0026720119 | W10: 0.002556 | X10: 0.006127 | Y10: 0.0099789 | Z10: 0.0169428 | AA10: 0.0280763 | AB10: 0.0190838 | AC10: 0.0024 | AD10: 0.0021 | AE10: 0.0477 | AF10: 0.0559301 | AG10: 0.0395 | AH10: 0.0295 | AI10: 0.0255 | AJ10: =AI10 -> 0.0255 | AK10: =AJ10 -> 0.0255 | AL10: =AK10 -> 0.0255 | AM10: =AL10 -> 0.0255 | AN10: =AM10 -> 0.0255 | AO10: =AN10 -> 0.0255 | AP10: =AO10 -> 0.0255 | AQ10: =AP10 -> 0.0255 | ... BG10: =BF10 -> 0.0255
A11: Общие | D11: ЦМИ | F11: Ставка Mosprime 3m | G11: % | I11: EoY | N11: 0.0622 | O11: 0.058 | P11: 0.0671 | Q11: 0.218 | R11: 0.0705 | S11: 0.0406 | T11: 0.0722 | U11: 0.070919919 | V11: 0.070100407 | W11: 0.10529433 | X11: 0.1179 | Y11: 0.1049 | Z11: 0.0788 | AA11: 0.0858 | AB11: 0.0645 | AC11: 0.0492 | AD11: 0.095 | AE11: 0.0841 | AF11: 0.0955 | AG11: 0.083 | AH11: 0.07 | AI11: 0.0655 | AJ11: =AI11+(AJ$39-AI$39) -> 0.048 | AK11: =AJ11+(AK$39-AJ$39) -> 0.023 | AL11: =AK11+(AL$39-AK$39) -> 0.018 | AM11: =AL11+(AM$39-AL$39) -> 0.018 | AN11: =AM11+(AN$39-AM$39) -> 0.018 | AO11: =AN11+(AO$39-AN$39) -> 0.018 | AP11: =AO11+(AP$39-AO$39) -> 0.018 | AQ11: =AP11+(AQ$39-AP$39) -> 0.018 | ... BG11: =BF11+(BG$39-BF$39) -> 0.018
A12: Общие | D12: Законодательство | F12: Ставка НДС | G12: % | I12: С 2019 года прогноз CIB | U12: 0.18 | V12: 0.18 | W12: 0.18 | X12: 0.18 | Y12: 0.18 | Z12: 0.18 | AA12: 0.18 | AB12: 0.2 | AC12: 0.2 | AD12: 0.2 | AE12: 0.2 | AF12: 0.2 | AG12: 0.2 | AH12: =AG12 -> 0.2 | AI12: 0.22 | AJ12: =AI12 -> 0.22 | AK12: =AJ12 -> 0.22 | AL12: =AK12 -> 0.22 | AM12: =AL12 -> 0.22 | AN12: =AM12 -> 0.22 | AO12: =AN12 -> 0.22 | AP12: =AO12 -> 0.22 | AQ12: =AP12 -> 0.22 | ... BG12: =BF12 -> 0.22
A13: Общие | D13: Законодательство | F13: Ставка НДФЛ | G13: % | I13: Базовая ставка при доходе до 200 тыс. руб./мес, далее прогрессивная шкала | U13: 0.13 | V13: 0.13 | W13: 0.13 | X13: 0.13 | Y13: 0.13 | Z13: 0.13 | AA13: 0.13 | AB13: 0.13 | AC13: 0.13 | AD13: 0.13 | AE13: 0.13 | AF13: 0.13 | AG13: 0.13 | AH13: =AG13 -> 0.13 | AI13: =AH13 -> 0.13 | AJ13: =AI13 -> 0.13 | AK13: =AJ13 -> 0.13 | AL13: =AK13 -> 0.13 | AM13: =AL13 -> 0.13 | AN13: =AM13 -> 0.13 | AO13: =AN13 -> 0.13 | ... BG13: =BF13 -> 0.13
A14: Общие | D14: ЦМИ | F14: Средний за период курс рубля к доллару США (av USD/RUB) | G14: $/руб | I14: С 2021 года прогноз CIB | J14: 29.17 | K14: 31.35 | L14: 30.68 | M14: 28.81 | N14: 28.7 | O14: 27.18 | P14: 25.57 | Q14: 24.81 | R14: 31.68 | S14: 30.36 | T14: 29.35 | U14: 31.07 | V14: 31.82 | W14: 38.378333 | X14: 60.938333 | Y14: 67.055 | Z14: 58.343333 | AA14: 62.668333 | AB14: 64.737642 | AC14: 72.104908 | AD14: 73.65435 | AE14: 68.485225 | AF14: 85.1725 | AG14: 92.552167 | AH14: 83.654167 | AI14: 80.61478 | AJ14: 91.367236 | AK14: 95.531033 | AL14: 99.616342 | AM14: 103.88148 | AN14: =AM14*(1+AN3-AN4) -> 105.95911 | AO14: =AN14*(1+AO3-AO4) -> 108.07829 | AP14: =AO14*(1+AP3-AP4) -> 110.23985 | AQ14: =AP14*(1+AQ3-AQ4) -> 112.44465 | AR14: =AQ14*(1+AR3-AR4) -> 114.69354 | AS14: =AR14*(1+AS3-AS4) -> 116.98741 | AT14: =AS14*(1+AT3-AT4) -> 119.32716 | AU14: =AT14*(1+AU3-AU4) -> 121.71371 | ... BG14: =BF14*(1+BG3-BG4) -> 154.36241
A15: Общие | D15: ЦМИ | F15: Средний за период курс рубля к EUR (av EUR/RUB) | G15: EUR/руб | I15: формула | J15: 26.13 | K15: 29.65 | L15: 34.69 | M15: 35.81 | N15: 34.17 | O15: 34.11 | P15: 35.01 | Q15: 36.41 | R15: 44.13 | S15: 40.27 | T15: 40.87 | U15: 39.93752 | V15: 42.382855 | W15: 51.019749 | X15: 67.762375 | Y15: 74.253684 | Z15: 65.855176 | AA15: 74.052364 | AB15: 72.4995 | AC15: 82.274762 | AD15: 87.189518 | AE15: 72.022339 | AF15: 92.151471 | AG15: 100.28011 | AH15: =AH14*AH35 -> 94.584736 | AI15: =AI14*AI35 -> 93.749206 | AJ15: =AJ14*AJ35 -> 105.42943 | AK15: =AK14*AK35 -> 109.8249 | AL15: =AL14*AL35 -> 114.57118 | AM15: =AM14*AM35 -> 119.45081 | AN15: =AN14*AN35 -> 121.83983 | AO15: =AO14*AO35 -> 124.27662 | ... BG15: =BG14*BG35 -> 177.49762
A16: Общие | D16: Законодательство | F16: Налог на имущество, инвентаризационная стоимость (НК Часть 2 Статья 380, максимальная ставка) | G16: % | I16: С 2019 года = 2018 | U16: 0.022 | V16: 0.022 | W16: 0.022 | X16: 0.022 | Y16: 0.022 | Z16: 0.022 | AA16: 0.022 | AB16: 0.022 | AC16: 0.022 | AD16: 0.022 | AE16: 0.022 | AF16: 0.022 | AG16: 0.022 | AH16: =AG16 -> 0.022 | AI16: =AH16 -> 0.022 | AJ16: =AI16 -> 0.022 | AK16: =AJ16 -> 0.022 | AL16: =AK16 -> 0.022 | AM16: =AL16 -> 0.022 | AN16: =AM16 -> 0.022 | AO16: =AN16 -> 0.022 | ... BG16: =BF16 -> 0.022
A17: Общие | D17: Законодательство | F17: Налог на имущество, кадастровая стоимость Москва (Закон г. Москвы от 05.11.2003 N 64, ред. от 25.11.2015, "О налоге на имущество организаций") | G17: % | I17: С 2019 года = 2018 | W17: 0.009 | X17: 0.012 | Y17: 0.013 | Z17: 0.014 | AA17: 0.015 | AB17: 0.016 | AC17: 0.017 | AD17: 0.018 | AE17: 0.019 | AF17: 0.02 | AG17: 0.02 | AH17: =AG17 -> 0.02 | AI17: =AH17 -> 0.02 | AJ17: =AI17 -> 0.02 | AK17: =AJ17 -> 0.02 | AL17: =AK17 -> 0.02 | AM17: =AL17 -> 0.02 | AN17: =AM17 -> 0.02 | AO17: =AN17 -> 0.02 | ... BG17: =BF17 -> 0.02
A18: Общие | D18: Законодательство | F18: Налог на имущество, кадастровая стоимость кроме Москвы (НК Часть 2 Статья 380, максимальная ставка) | G18: % | I18: С 2019 года = 2018 | W18: 0.01 | X18: 0.015 | Y18: 0.02 | Z18: 0.02 | AA18: 0.02 | AB18: 0.02 | AC18: 0.02 | AD18: 0.02 | AE18: 0.02 | AF18: 0.02 | AG18: 0.02 | AH18: =AG18 -> 0.02 | AI18: =AH18 -> 0.02 | AJ18: =AI18 -> 0.02 | AK18: =AJ18 -> 0.02 | AL18: =AK18 -> 0.02 | AM18: =AL18 -> 0.02 | AN18: =AM18 -> 0.02 | AO18: =AN18 -> 0.02 | ... BG18: =BF18 -> 0.02
A19: Общие | D19: ЦМИ | F19: Инфляция з.платы (Рост номинальных заработных плат) | G19: % | I19: С 2021 года прогноз CIB; =CPI+рост реальных доходов | J19: 0.457 | K19: 0.346 | L19: 0.261 | M19: 0.226 | N19: 0.269 | O19: 0.243 | P19: 0.278 | Q19: 0.272 | R19: 0.078 | S19: 0.124 | T19: 0.115 | U19: 0.139 | V19: 0.119 | W19: 0.091 | X19: 0.042392097 | Y19: 0.0802013 | Z19: 0.065530006 | AA19: 0.11009795 | AB19: 0.091798583 | AC19: 0.07603513 | AD19: 0.10656959 | AE19: 0.1564009 | AF19: 0.12639276 | AG19: 0.19323935 | AH19: 0.14083749 | AI19: 0.12048028 | AJ19: 0.087616212 | AK19: 0.067391121 | AL19: 0.0661684 | AM19: 0.065929549 | AN19: =(1+AN9)*(1+AN3)-1 -> 0.061864635 | AO19: =(1+AO9)*(1+AO3)-1 -> 0.061864635 | AP19: =(1+AP9)*(1+AP3)-1 -> 0.061864635 | AQ19: =(1+AQ9)*(1+AQ3)-1 -> 0.061864635 | AR19: =(1+AR9)*(1+AR3)-1 -> 0.061864635 | AS19: =(1+AS9)*(1+AS3)-1 -> 0.061864635 | AT19: =(1+AT9)*(1+AT3)-1 -> 0.061864635 | AU19: =(1+AU9)*(1+AU3)-1 -> 0.061864635 | ... BG19: =(1+BG9)*(1+BG3)-1 -> 0.061864635
A20: Общие | D20: ЦМИ | F20: Ставка Euribor 3m | G20: % | I20: EoY, ЦМИ, 2022 и далее = 2021 | J20: 0.03294 | K20: 0.02865 | L20: 0.02124 | M20: 0.02155 | N20: 0.02488 | O20: 0.03725 | P20: 0.04684 | Q20: 0.02892 | R20: 0.007 | S20: 0.01006 | T20: 0.01356 | U20: 0.0049081058 | V20: 0.0015218502 | W20: 0.00078 | X20: -0.00131 | Y20: -0.00319 | Z20: -0.00329 | AA20: -0.00309 | AB20: -0.00383 | AC20: -0.00545 | AD20: -0.00572 | AE20: 0.02132 | AF20: 0.03909 | AG20: 0.02678 | AH20: 0.02026 | AI20: 0.0285 | AJ20: 0.0281 | AK20: 0.023 | AL20: 0.0228 | AM20: 0.0228 | AN20: =AM20 -> 0.0228 | AO20: =AN20 -> 0.0228 | AP20: =AO20 -> 0.0228 | AQ20: =AP20 -> 0.0228 | AR20: =AQ20 -> 0.0228 | AS20: =AR20 -> 0.0228 | AT20: =AS20 -> 0.0228 | AU20: =AT20 -> 0.0228 | ... BG20: =BF20 -> 0.0228
A21: Общие | D21: ЦМИ | F21: Процентный своп IRS 1Y Mosprime | G21: % | I21: EoY | O21: 0.0578 | P21: 0.0568 | Q21: 0.1575 | R21: 0.0732 | S21: 0.05335 | T21: 0.0721 | U21: 0.073222594 | V21: 0.069354529 | W21: 0.10586616 | X21: 0.116 | Y21: 0.10465 | Z21: 0.078 | AA21: 0.0957 | AB21: 0.0646 | AC21: 0.0504 | AD21: 0.1022 | AE21: 0.088 | AF21: 0.1516 | AG21: 0.2192 | AH21: 0.1515 | AI21: 0.13642095 | AJ21: 0.11417202 | AK21: 0.094298272 | AL21: 0.092975259 | AM21: 0.092975259 | AN21: =AM21+(AN$39-AM$39) -> 0.092975259 | AO21: =AN21+(AO$39-AN$39) -> 0.092975259 | AP21: =AO21+(AP$39-AO$39) -> 0.092975259 | AQ21: =AP21+(AQ$39-AP$39) -> 0.092975259 | AR21: =AQ21+(AR$39-AQ$39) -> 0.092975259 | AS21: =AR21+(AS$39-AR$39) -> 0.092975259 | AT21: =AS21+(AT$39-AS$39) -> 0.092975259 | AU21: =AT21+(AU$39-AT$39) -> 0.092975259 | ... BG21: =BF21+(BG$39-BF$39) -> 0.092975259
A22: Общие | D22: ЦМИ | F22: Процентный своп IRS 3Y Mosprime | G22: % | I22: EoY | O22: 0.0615 | P22: 0.0667 | Q22: 0.16 | R22: 0.076 | S22: 0.0675 | T22: 0.0742 | U22: 0.075070977 | V22: 0.069934962 | W22: 0.09891364 | X22: 0.1079 | Y22: 0.0953 | Z22: 0.0759 | AA22: 0.0968 | AB22: 0.0634 | AC22: 0.0554 | AD22: 0.0935 | AE22: 0.097 | AF22: 0.1293 | AG22: 0.1901 | AH22: 0.14 | AI22: 0.13311142 | AJ22: 0.10648377 | AK22: 0.095726654 | AL22: 0.095253555 | AM22: 0.095253891 | AN22: =AM22+(AN$39-AM$39) -> 0.095253891 | AO22: =AN22+(AO$39-AN$39) -> 0.095253891 | AP22: =AO22+(AP$39-AO$39) -> 0.095253891 | AQ22: =AP22+(AQ$39-AP$39) -> 0.095253891 | AR22: =AQ22+(AR$39-AQ$39) -> 0.095253891 | AS22: =AR22+(AS$39-AR$39) -> 0.095253891 | AT22: =AS22+(AT$39-AS$39) -> 0.095253891 | AU22: =AT22+(AU$39-AT$39) -> 0.095253891 | ... BG22: =BF22+(BG$39-BF$39) -> 0.095253891
A23: Общие | D23: ЦМИ | F23: Процентный своп IRS 5Y Mosprime | G23: % | I23: EoY | O23: 0.064 | P23: 0.0718 | Q23: 0.165 | R23: 0.0785 | S23: 0.0735 | T23: 0.0754 | U23: 0.076751556 | V23: 0.071434632 | W23: 0.096330785 | X23: 0.1062 | Y23: 0.0918 | Z23: 0.0755 | AA23: 0.0956 | AB23: 0.0646 | AC23: 0.0588 | AD23: 0.0894 | AE23: 0.102 | AF23: 0.124 | AG23: 0.1808 | AH23: 0.1395 | AI23: 0.13307039 | AJ23: 0.10666102 | AK23: 0.096383824 | AL23: 0.096079831 | AM23: 0.096080046 | AN23: =AM23+(AN$39-AM$39) -> 0.096080046 | AO23: =AN23+(AO$39-AN$39) -> 0.096080046 | AP23: =AO23+(AP$39-AO$39) -> 0.096080046 | AQ23: =AP23+(AQ$39-AP$39) -> 0.096080046 | AR23: =AQ23+(AR$39-AQ$39) -> 0.096080046 | AS23: =AR23+(AS$39-AR$39) -> 0.096080046 | AT23: =AS23+(AT$39-AS$39) -> 0.096080046 | AU23: =AT23+(AU$39-AT$39) -> 0.096080046 | ... BG23: =BF23+(BG$39-BF$39) -> 0.096080046
A24: Общие | D24: ЦМИ | F24: Процентный своп IRS 7Y Mosprime | G24: % | I24: EoY | O24: 0.0646 | P24: 0.0737 | Q24: 0.165 | R24: 0.0815 | S24: 0.07651 | T24: 0.0771 | U24: 0.078596912 | V24: 0.073566594 | W24: 0.095379851 | X24: 0.1054 | Y24: 0.0896 | Z24: 0.0753 | AA24: 0.0945 | AB24: 0.0682 | AC24: 0.0613 | AD24: 0.0879 | AE24: 0.1048 | AF24: 0.12216 | AG24: =AG23+(AG25-AG23)*2/5 -> 0.17244 | AH24: =AH23+(AH25-AH23)*2/5 -> 0.1405 | AI24: =AI23+(AI25-AI23)*2/5 -> 0.14260223 | AJ24: =AJ23+(AJ25-AJ23)*2/5 -> 0.11559661 | AK24: =AK23+(AK25-AK23)*2/5 -> 0.097408956 | AL24: =AL23+(AL25-AL23)*2/5 -> 0.097156651 | AM24: =AM23+(AM25-AM23)*2/5 -> 0.097156938 | AN24: =AN23+(AN25-AN23)*2/5 -> 0.097156938 | ... BG24: =BG23+(BG25-BG23)*2/5 -> 0.097156938
A25: Общие | D25: ЦМИ | F25: Процентный своп IRS 10Y Mosprime | G25: % | I25: EoY | O25: 0.0651 | P25: 0.0766 | Q25: 0.165 | R25: 0.082 | S25: 0.07951 | T25: 0.0789 | U25: 0.081269617 | V25: 0.076304414 | W25: 0.095675602 | X25: 0.1039 | Y25: 0.0873 | Z25: 0.0753 | AA25: 0.0932 | AB25: 0.0684 | AC25: 0.0646 | AD25: 0.0877 | AE25: 0.109 | AF25: 0.1194 | AG25: 0.1599 | AH25: 0.142 | AI25: 0.1569 | AJ25: 0.129 | AK25: 0.098946654 | AL25: 0.098771881 | AM25: 0.098772277 | AN25: =AM25+(AN$39-AM$39) -> 0.098772277 | AO25: =AN25+(AO$39-AN$39) -> 0.098772277 | AP25: =AO25+(AP$39-AO$39) -> 0.098772277 | AQ25: =AP25+(AQ$39-AP$39) -> 0.098772277 | AR25: =AQ25+(AR$39-AQ$39) -> 0.098772277 | AS25: =AR25+(AS$39-AR$39) -> 0.098772277 | AT25: =AS25+(AT$39-AS$39) -> 0.098772277 | AU25: =AT25+(AU$39-AT$39) -> 0.098772277 | ... BG25: =BF25+(BG$39-BF$39) -> 0.098772277
A26: Общие | D26: Расчет | F26: Средний за период курс рубля к CHF (av CHF/RUB) | G26: CHF/руб | I26: формула | J26: 17.318563 | K26: 20.225352 | L26: 22.797648 | M26: 23.200051 | N26: 22.726587 | O26: 21.674498 | P26: 21.310417 | Q26: 22.92536 | R26: 29.245194 | S26: 29.492689 | T26: 33.218057 | U26: 33.114757 | V26: 34.428351 | W26: 42.014608 | X26: 63.877109 | Y26: 67.848924 | Z26: 59.296313 | AA26: 64.271353 | AB26: 65.038546 | AC26: 77.342137 | AD26: 80.517746 | AE26: 74.698218 | AF26: 93.350656 | AG26: 105.25576 | AH26: 100.28323 | AI26: =AI14/AI41 -> 97.05608 | AJ26: =AJ14/AJ41 -> 110.00149 | AK26: =AK14/AK41 -> 115.01449 | AL26: =AL14/AL41 -> 119.93299 | AM26: =AM14/AM41 -> 125.06799 | AN26: =AN14/AN41 -> 127.56935 | AO26: =AO14/AO41 -> 130.12074 | AP26: =AP14/AP41 -> 132.72316 | ... BG26: =BG14/BG41 -> 185.84446
A27: Общие | D27: Расчет | F27: Курс рубля к CHF в конце года (eop CHF/RUB) | G27: CHF/руб | I27: формула | J27: 17.86 | K27: 22.778 | L27: 23.5995 | M27: 24.4827 | N27: 21.9563 | O27: 21.597 | P27: 21.7879 | Q27: 27.8329 | R27: 29.137 | S27: 32.4084 | T27: 34.2366 | U27: 33.2888 | V27: 36.696 | W27: 56.9763 | X27: 73.611527 | Y27: 59.4151 | Z27: 58.9743 | AA27: 70.5787 | AB27: 63.6039 | AC27: 83.5131 | AD27: 80.9376 | AE27: 76.1805 | AF27: 106.7591 | AG27: 112.9774 | AH27: 99.1969 | AI27: =AI7/AI40 -> 110.94649 | AJ27: =AJ7/AJ40 -> 112.21018 | AK27: =AK7/AK40 -> 117.03069 | AL27: =AL7/AL40 -> 122.03675 | AM27: =AM7/AM40 -> 127.26401 | AN27: =AN7/AN40 -> 127.56935 | AO27: =AO7/AO40 -> 130.12074 | AP27: =AP7/AP40 -> 132.72316 | ... BG27: =BG7/BG40 -> 185.84446
A28: Общие | D28: CIB Research | F28: Инфляция - Рост индекса цен производителей в США, в долларах США (USD, eop PPI) | G28: % | I28: =CPI | J28: -0.016 | K28: 0.012 | L28: 0.04 | M28: 0.042 | N28: 0.054 | O28: 0.011 | P28: 0.062 | Q28: -0.009 | R28: 0.043 | S28: 0.038 | T28: 0.047 | U28: 0.021 | V28: 0.004 | W28: 0.008 | X28: -0.051 | Y28: -0.019 | Z28: 0.032 | AA28: 0.013 | AB28: 0.017 | AC28: -0.008 | AD28: 0.122 | AE28: 0.064115004 | AF28: 0.03323156 | AG28: =AG4 -> 0.028723677 | AH28: =AH4 -> 0.026899449 | AI28: =AI4 -> 0.027326387 | AJ28: =AJ4 -> 0.026069089 | AK28: =AK4 -> 0.022921913 | AL28: =AL4 -> 0.01939121 | AM28: =AM4 -> 0.02235396 | AN28: =AN4 -> 0.02 | ... BG28: =BG4 -> 0.02
A29: Общие | D29: CIB Research | F29: Инфляция - Рост индекса потребительских цен в Еврозоне (EUR, eop CPI) | G29: % | I29: EoY HICP, source: FX/IR team | J29: 0.021 | K29: 0.023 | L29: 0.02 | M29: 0.023 | N29: 0.023 | O29: 0.019 | P29: 0.031 | Q29: 0.016 | R29: 0.009 | S29: 0.022 | T29: 0.028 | U29: 0.022212505 | V29: 0.0084695012 | W29: -0.002 | X29: 0.0044947037 | Y29: 0.011242984 | Z29: 0.01357189 | AA29: 0.015592772 | AB29: 0.013479362 | AC29: -0.0026189844 | AD29: 0.050069593 | AE29: 0.092074037 | AF29: 0.029353964 | AG29: 0.024563883 | AH29: 0.019664407 | AI29: 0.029057119 | AJ29: 0.019429195 | AK29: 0.023805054 | AL29: 0.018896804 | AM29: 0.021378704 | AN29: 0.02 | AO29: =AN29 -> 0.02 | AP29: =AO29 -> 0.02 | AQ29: =AP29 -> 0.02 | AR29: =AQ29 -> 0.02 | AS29: =AR29 -> 0.02 | AT29: =AS29 -> 0.02 | AU29: =AT29 -> 0.02 | AV29: =AU29 -> 0.02 | ... BG29: =BF29 -> 0.02
A30: Общие | D30: CIB Research | F30: Инфляция - Рост индекса цен производителей в Еврозоне (EUR, eop PPI) | G30: % | I30: =CPI | J30: -0.005 | K30: 0.015 | L30: 0.01 | M30: 0.037 | N30: 0.045 | O30: 0.038 | P30: 0.044 | Q30: 0.015 | R30: -0.03 | S30: 0.05 | T30: 0.044 | U30: 0.024 | V30: -0.001 | W30: -0.013 | X30: -0.019 | Y30: -0.011 | Z30: 0.022 | AA30: 0.031 | AB30: -0.007 | AC30: -0.011 | AD30: 0.237 | AE30: 0.092074037 | AF30: 0.029353964 | AG30: =AG29 -> 0.024563883 | AH30: =AH29 -> 0.019664407 | AI30: =AI29 -> 0.029057119 | AJ30: =AJ29 -> 0.019429195 | AK30: =AK29 -> 0.023805054 | AL30: =AL29 -> 0.018896804 | AM30: =AM29 -> 0.021378704 | AN30: =AN29 -> 0.02 | ... BG30: =BG29 -> 0.02
A31: Общие | D31: Законодательство | F31: Ставка страхового взноса в ФОМС | G31: % | I31: Не меняется | U31: 0.051 | V31: 0.051 | W31: 0.051 | X31: 0.051 | Y31: 0.051 | Z31: 0.051 | AA31: 0.051 | AB31: 0.051 | AC31: 0.051 | AD31: 0.051 | AE31: 0.051 | AF31: 0.051 | AG31: =AF31 -> 0.051 | AH31: =AG31 -> 0.051 | AI31: =AH31 -> 0.051 | AJ31: =AI31 -> 0.051 | AK31: =AJ31 -> 0.051 | AL31: =AK31 -> 0.051 | AM31: =AL31 -> 0.051 | AN31: =AM31 -> 0.051 | ... BG31: =BF31 -> 0.051
A32: Общие | D32: Законодательство | F32: Ставка страхового взноса в ФСС | G32: % | I32: Не меняется | U32: 0.029 | V32: 0.029 | W32: 0.029 | X32: 0.029 | Y32: 0.029 | Z32: 0.029 | AA32: 0.029 | AB32: 0.029 | AC32: 0.029 | AD32: 0.029 | AE32: 0.029 | AF32: 0.029 | AG32: =AF32 -> 0.029 | AH32: =AG32 -> 0.029 | AI32: =AH32 -> 0.029 | AJ32: =AI32 -> 0.029 | AK32: =AJ32 -> 0.029 | AL32: =AK32 -> 0.029 | AM32: =AL32 -> 0.029 | AN32: =AM32 -> 0.029 | ... BG32: =BF32 -> 0.029
A33: Общие | D33: Законодательство | F33: Ставка страхового взноса в ПФР | G33: % | I33: Не меняется | U33: 0.22 | V33: 0.22 | W33: 0.22 | X33: 0.22 | Y33: 0.22 | Z33: 0.22 | AA33: 0.22 | AB33: 0.22 | AC33: 0.22 | AD33: 0.22 | AE33: 0.22 | AF33: 0.22 | AG33: =AF33 -> 0.22 | AH33: =AG33 -> 0.22 | AI33: =AH33 -> 0.22 | AJ33: =AI33 -> 0.22 | AK33: =AJ33 -> 0.22 | AL33: =AK33 -> 0.22 | AM33: =AL33 -> 0.22 | AN33: =AM33 -> 0.22 | ... BG33: =BF33 -> 0.22
A34: Общие | D34: Законодательство | F34: Ставка налога на прибыль организаций | G34: % | I34: Не меняется | U34: 0.2 | V34: 0.2 | W34: 0.2 | X34: 0.2 | Y34: 0.2 | Z34: 0.2 | AA34: 0.2 | AB34: 0.2 | AC34: 0.2 | AD34: 0.2 | AE34: 0.2 | AF34: 0.2 | AG34: =AF34 -> 0.2 | AH34: 0.25 | AI34: =AH34 -> 0.25 | AJ34: =AI34 -> 0.25 | AK34: =AJ34 -> 0.25 | AL34: =AK34 -> 0.25 | AM34: =AL34 -> 0.25 | AN34: =AM34 -> 0.25 | AO34: =AN34 -> 0.25 | AP34: =AO34 -> 0.25 | ... BG34: =BF34 -> 0.25
A35: Общие | D35: ЦМИ | F35: Средний за период курс EUR к доллару США (av EUR/USD) | G35: EUR/$ | I35: 2017-21 ЦМИ | J35: 0.8956 | K35: 0.9456 | L35: 1.1312 | M35: 1.2439 | N35: 1.2441 | O35: 1.2556 | P35: 1.3705 | Q35: 1.4708 | R35: 1.3948 | S35: 1.3257 | T35: 1.392 | W35: 1.32 | X35: 1.1098449 | Y35: 1.1075317 | Z35: 1.1301778 | AA35: 1.1806945 | AB35: 1.1073 | AC35: 1.1411541 | AD35: 1.183766 | AE35: 1.0518288 | AF35: 1.0820174 | AG35: 1.0830867 | AH35: 1.1306638 | AI35: 1.1629283 | AJ35: 1.1539085 | AK35: 1.1496253 | AL35: 1.1501243 | AM35: 1.1498759 | AN35: =AM35 -> 1.1498759 | AO35: =AN35 -> 1.1498759 | AP35: =AO35 -> 1.1498759 | AQ35: =AP35 -> 1.1498759 | AR35: =AQ35 -> 1.1498759 | AS35: =AR35 -> 1.1498759 | AT35: =AS35 -> 1.1498759 | AU35: =AT35 -> 1.1498759 | ... BG35: =BF35 -> 1.1498759
A36: Общие | D36: Расчет | F36: Курс EUR к доллару США в конце года (eop EUR/USD) | G36: EUR/$ | J36: 0.8813 | K36: 1.0487 | L36: 1.263 | M36: 1.3621 | N36: 1.1797 | O36: 1.317 | P36: 1.4721 | Q36: 1.3917 | R36: 1.4406 | S36: 1.3362 | T36: 1.2939 | U36: 1.3194 | V36: 1.3791 | W36: 1.2141 | X36: 1.08655 | Y36: 1.0516 | Z36: 1.1994 | AA36: 1.1456 | AB36: 1.1214 | AC36: 1.2217 | AD36: 1.137 | AE36: 1.0702 | AF36: 1.1036 | AG36: 1.0434697 | AH36: 1.1772681 | AI36: 1.16 | AJ36: 1.15 | AK36: 1.15 | AL36: 1.15 | AM36: 1.15 | AN36: =AN35 -> 1.1498759 | AO36: =AO35 -> 1.1498759 | AP36: =AP35 -> 1.1498759 | AQ36: =AQ35 -> 1.1498759 | AR36: =AR35 -> 1.1498759 | AS36: =AS35 -> 1.1498759 | AT36: =AT35 -> 1.1498759 | AU36: =AU35 -> 1.1498759 | ... BG36: =BG35 -> 1.1498759
A37: Общие | D37: ЦМИ | F37: ECB policy rate (Main Refinancing Operations rate) | G37: % | I37: EoY, ЦМИ, 2022 и далее = 2021 | J37: 0.0325 | K37: 0.0275 | L37: 0.02 | M37: 0.02 | N37: 0.0225 | O37: 0.035 | P37: 0.04 | Q37: 0.025 | R37: 0.01 | S37: 0.01 | T37: 0.01 | U37: 0.0075 | V37: 0.0025 | W37: 0.0005 | X37: 0.0005 | Y37: 0 | Z37: 0 | AA37: 0 | AB37: 0 | AC37: 0 | AD37: 0 | AE37: 0.025 | AF37: 0.045 | AG37: 0.0315 | AH37: 0.0215 | AI37: 0.0265 | AJ37: 0.024 | AK37: 0.0215 | AL37: 0.0215 | AM37: 0.0215 | AN37: =AM37 -> 0.0215 | AO37: =AN37 -> 0.0215 | AP37: =AO37 -> 0.0215 | AQ37: =AP37 -> 0.0215 | AR37: =AQ37 -> 0.0215 | AS37: =AR37 -> 0.0215 | AT37: =AS37 -> 0.0215 | AU37: =AT37 -> 0.0215 | ... BG37: =BF37 -> 0.0215
A38: Общие | D38: Расчет | F38: Курс EUR к CHF в конце года (eop EUR/CHF) | G38: EUR/CHF | I38: формула | J38: 1.4777 | K38: 1.4514 | L38: 1.56045 | M38: 1.546 | N38: 1.55615 | O38: 1.6091 | P38: 1.6536 | Q38: 1.49358 | R38: 1.48365 | S38: 1.25161 | T38: 1.21689 | U38: 1.2072 | V38: 1.2276 | W38: 1.2024 | X38: 1.0887316 | Y38: 1.074 | Z38: 1.17 | AA38: 1.127 | AB38: 1.0854 | AC38: 1.0809642 | AD38: 1.0373444 | AE38: 0.9893 | AF38: 0.9287 | AG38: 0.9392 | AH38: 0.9311 | AI38: =AI36*AI40 -> 0.920576 | AJ38: =AJ36*AJ40 -> 0.95519 | AK38: =AK36*AK40 -> 0.95519 | AL38: =AL36*AL40 -> 0.95519 | AM38: =AM36*AM40 -> 0.95519 | AN38: =AN36*AN40 -> 0.95508695 | AO38: =AO36*AO40 -> 0.95508695 | AP38: =AP36*AP40 -> 0.95508695 | ... BG38: =BG36*BG40 -> 0.95508695
A39: Общие | D39: ЦМИ | F39: Ключевая ставка на конец года (eop) | G39: % | I39: С 2021 года = инфляция + 2% | T39: 0.0525 | W39: 0.17 | X39: 0.11 | Y39: 0.1 | Z39: 0.0775 | AA39: 0.0775 | AB39: 0.0625 | AC39: 0.0425 | AD39: 0.085 | AE39: 0.075 | AF39: 0.16 | AG39: 0.21 | AH39: 0.16 | AI39: 0.1375 | AJ39: 0.12 | AK39: 0.095 | AL39: 0.09 | AM39: 0.09 | AN39: =AM39 -> 0.09 | AO39: =AN39 -> 0.09 | AP39: =AO39 -> 0.09 | AQ39: =AP39 -> 0.09 | AR39: =AQ39 -> 0.09 | AS39: =AR39 -> 0.09 | AT39: =AS39 -> 0.09 | AU39: =AT39 -> 0.09 | ... BG39: =BF39 -> 0.09
A40: Общие | D40: Расчет | F40: USD/CHF eop | G40: USD/CHF | J40: 1.6603 | K40: 1.3836 | L40: 1.2391 | M40: 1.1404 | N40: 1.3134 | O40: 1.2201 | P40: 1.1335 | Q40: 1.0687 | R40: 1.0352 | S40: 0.9352 | T40: 0.9381 | X40: 1.01 | Y40: 1.016 | Z40: 0.974 | AA40: 0.983 | AB40: 0.9676 | AC40: 0.8852 | AD40: 0.9129 | AE40: 0.9244 | AF40: 0.8415 | AG40: 0.9072 | AH40: =AI41 -> 0.8306 | AI40: 0.7936 | AJ40: =AK41 -> 0.8306 | AK40: =AL41 -> 0.8306 | AL40: =AM41 -> 0.8306 | AM40: =AM41 -> 0.8306 | AN40: =AO41 -> 0.8306 | AO40: =AP41 -> 0.8306 | AP40: =AQ41 -> 0.8306 | AQ40: =AR41 -> 0.8306 | AR40: =AS41 -> 0.8306 | AS40: =AT41 -> 0.8306 | AT40: =AU41 -> 0.8306 | AU40: =AV41 -> 0.8306 | ... BA40: =BB41 -> 0.8306 | BB40: =BB41 -> 0.8306 | BC40: =BC41 -> 0.8306 | BD40: =BD41 -> 0.8306 | BE40: =BE41 -> 0.8306 | BF40: =BF41 -> 0.8306 | BG40: =BG41 -> 0.8306
A41: Общие | D41: ЦМИ | F41: USD/CHF average | G41: USD/CHF | I41: формула | J41: 1.6871387 | K41: 1.5552533 | L41: 1.3443716 | M41: 1.2421034 | N41: 1.2463265 | O41: 1.2528881 | P41: 1.2000165 | Q41: 1.0823534 | R41: 1.0849889 | S41: 1.0423498 | T41: 0.88658192 | Y41: 0.98173705 | Z41: 0.985 | AA41: 0.985 | AB41: 0.993825 | AC41: 0.93885 | AD41: 0.91415 | AE41: 0.9548 | AF41: 0.8983 | AG41: 0.8805 | AH41: 0.8306 | AI41: =AH41 -> 0.8306 | AJ41: =AI41 -> 0.8306 | AK41: =AJ41 -> 0.8306 | AL41: =AK41 -> 0.8306 | AM41: =AL41 -> 0.8306 | AN41: =AM41 -> 0.8306 | AO41: =AN41 -> 0.8306 | AP41: =AO41 -> 0.8306 | ... BG41: =BF41 -> 0.8306
A42: Общие | D42: ЦМИ | F42: Ключевая ставка средняя за период (av) | G42: % | I42: формула | W42: 0.084375 | X42: 0.12625 | Y42: 0.105 | Z42: 0.0903125 | AA42: 0.074375 | AB42: 0.073125 | AC42: 0.05 | AD42: 0.0578125 | AE42: 0.1075 | AF42: 0.10375 | AG42: =AVERAGE('Inputs Q LTM'!CX42:DA42) -> 0.17375 | AH42: =AVERAGE('Inputs Q LTM'!DB42:DE42) -> 0.19125 | AI42: =AVERAGE('Inputs Q LTM'!DF42:DI42) -> 0.1453125 | AJ42: =AVERAGE('Inputs Q LTM'!DJ42:DM42) -> 0.1290625 | AK42: =AK39 -> 0.095 | AL42: =AL39 -> 0.09 | AM42: =AM39 -> 0.09 | AN42: =AN39 -> 0.09 | AO42: =AO39 -> 0.09 | AP42: =AP39 -> 0.09 | AQ42: =AQ39 -> 0.09 | AR42: =AR39 -> 0.09 | ... BG42: =BG39 -> 0.09
A43: Общие | D43: ЦМИ | F43: Курс юаня к доллару (средний за период) | G43: USD/CNY | J43: 8.27705 | K43: 8.27695 | L43: 8.277025 | M43: 8.2768 | N43: 8.193025 | O43: 7.972825 | P43: 7.606025 | Q43: 6.950925 | R43: 6.8315 | S43: 6.76895 | T43: 6.464025 | U43: 6.30805 | V43: 6.148975 | W43: 6.1616 | X43: 6.284675 | Y43: 6.6475 | Z43: 6.757225 | AA43: 6.616875 | AB43: 6.905625 | AC43: 6.898575 | AD43: 6.5 | AE43: 6.7306025 | AF43: 7.0729953 | AG43: 7.1885833 | AH43: 7.1863333 | AI43: 6.8015695 | AJ43: 6.6212138 | AK43: 6.5100455 | AL43: 6.49 | AM43: 6.49 | AN43: =AM43 -> 6.49 | AO43: =AN43 -> 6.49 | AP43: =AO43 -> 6.49 | AQ43: =AP43 -> 6.49 | AR43: =AQ43 -> 6.49 | AS43: =AR43 -> 6.49 | AT43: =AS43 -> 6.49 | AU43: =AT43 -> 6.49 | ... BG43: =BF43 -> 6.49
A44: Общие | D44: ЦМИ | F44: Курс юаня к доллару (на конец периода) | G44: USD/CNY | J44: 8.2765 | K44: 8.277 | L44: 8.2767 | M44: 8.2765 | N44: 8.0702 | O44: 7.8045 | P44: 7.3037 | Q44: 6.8277 | R44: 6.8271 | S44: 6.607 | T44: 6.295 | U44: 6.2306 | V44: 6.0543 | W44: 6.2055 | X44: 6.4937 | Y44: 6.945 | Z44: 6.5068 | AA44: 6.8785 | AB44: 6.9632 | AC44: 6.530795 | AD44: 6.376883 | AE44: 6.9716952 | AF44: 7.123 | AG44: 7.298 | AH44: 7.01 | AI44: 6.7 | AJ44: 6.53 | AK44: 6.49 | AL44: 6.49 | AM44: 6.49 | AN44: =AN43 -> 6.49 | AO44: =AO43 -> 6.49 | AP44: =AP43 -> 6.49 | AQ44: =AQ43 -> 6.49 | AR44: =AR43 -> 6.49 | AS44: =AS43 -> 6.49 | AT44: =AT43 -> 6.49 | AU44: =AU43 -> 6.49 | ... BG44: =BG43 -> 6.49
A45: Общие | D45: ЦМИ | F45: Курс рубля к юаню, руб. (средний за период) | G45: CNY/руб | J45: 3.527325 | K45: 3.791175 | L45: 3.7073 | M45: 3.47975 | N45: 3.45395 | O45: 3.408225 | P45: 3.3615 | Q45: 3.58125 | R45: 4.649125 | S45: 4.486975 | T45: 4.550725 | U45: 4.922125 | V45: 5.181825 | W45: 6.26285 | X45: 9.738075 | Y45: 10.094625 | Z45: 8.636 | AA45: 9.485225 | AB45: 9.373575 | AC45: 10.491275 | AD45: 11.331438 | AE45: 10.2916 | AF45: 11.9846 | AG45: 12.752377 | AH45: 11.635639 | AI45: =AI14/AI43 -> 11.852379 | AJ45: =AJ14/AJ43 -> 13.799167 | AK45: =AK14/AK43 -> 14.674403 | AL45: =AL14/AL43 -> 15.349205 | AM45: =AM14/AM43 -> 16.006391 | AN45: =AN14/AN43 -> 16.326519 | AO45: =AO14/AO43 -> 16.653049 | AP45: =AP14/AP43 -> 16.98611 | ... BG45: =BG14/BG43 -> 23.784655
A46: Общие | D46: ЦМИ | F46: Курс рубля к юаню, руб. (на конец периода) | G46: CNY/руб | J46: 3.6857 | K46: 3.8607 | L46: 3.5331 | M46: 3.3492 | N46: 3.5614 | O46: 3.3731 | P46: 3.3682 | Q46: 4.3064 | R46: 4.3994 | S46: 4.6219 | T46: 5.1024 | U46: 4.9036 | V46: 5.433 | W46: 9.354 | X46: 11.372 | Y46: 8.7827 | Z46: 8.85 | AA46: 10.0892 | AB46: 8.9053 | AC46: 11.3119 | AD46: 11.6503 | AE46: 10.08901 | AF46: 12.5762 | AG46: 13.4272 | AH46: 11.159772 | AI46: =AI7/AI44 -> 13.141364 | AJ46: =AJ7/AJ44 -> 14.27286 | AK46: =AK7/AK44 -> 14.977765 | AL46: =AL7/AL44 -> 15.618448 | AM46: =AM7/AM44 -> 16.287441 | AN46: =AN7/AN44 -> 16.326519 | AO46: =AO7/AO44 -> 16.653049 | AP46: =AP7/AP44 -> 16.98611 | ... BG46: =BG7/BG44 -> 23.784655
A47: Общие | D47: ЦМИ | F47: Курс рупии к доллару (средний за период) | G47: USD/INR | W47: 61.02 | X47: 64.1 | Y47: 67.17 | Z47: 65.11 | AA47: 68.4 | AB47: 70.4 | AC47: 74.1 | AD47: 73.907985 | AE47: 78.421647 | AF47: 82.583103 | AG47: 83.659612 | AH47: 87.141827 | AI47: 94.233195 | AJ47: 94.934035 | AK47: 96.345207 | AL47: 98.106359 | AM47: 99.838398 | AN47: =AM47*(1+2%) -> 101.83517 | AO47: =AN47*(1+2%) -> 103.87187 | AP47: =AO47*(1+2%) -> 105.94931 | AQ47: =AP47*(1+2%) -> 108.06829 | AR47: =AQ47*(1+2%) -> 110.22966 | AS47: =AR47*(1+2%) -> 112.43425 | AT47: =AS47*(1+2%) -> 114.68294 | AU47: =AT47*(1+2%) -> 116.9766 | ... BG47: =BF47*(1+2%) -> 148.35461
A48: Общие | D48: ЦМИ | F48: Курс рупии к доллару (на конец периода) | G48: USD/INR | W48: 63.035 | X48: 66.208 | Y48: 67.955 | Z48: 63.84 | AA48: 69.57 | AB48: 71.355 | AC48: 73.322118 | AD48: 74.410019 | AE48: 82.868453 | AF48: 83.25 | AG48: 85.5765 | AH48: 89.92 | AI48: 94.795649 | AJ48: 95.233087 | AK48: 97.159474 | AL48: 98.690773 | AM48: 100.72016 | AN48: =AN47 -> 101.83517 | AO48: =AO47 -> 103.87187 | AP48: =AP47 -> 105.94931 | AQ48: =AQ47 -> 108.06829 | AR48: =AR47 -> 110.22966 | AS48: =AS47 -> 112.43425 | AT48: =AT47 -> 114.68294 | AU48: =AU47 -> 116.9766 | ... BG48: =BG47 -> 148.35461
A49: Общие | D49: ЦМИ | F49: Ставка Roisfix 3M | G49: % | W49: 0.2105 | X49: 0.1098 | Y49: 0.1005 | Z49: 0.0754 | AA49: 0.0777 | AB49: 0.0612 | AC49: 0.0422 | AD49: 0.0869 | AE49: 0.0762 | AF49: 0.1604 | AG49: 0.213 | AH49: 0.1585 | AI49: 0.13676374 | AJ49: 0.11965761 | AK49: 0.0955 | AL49: 0.0905 | AM49: 0.0905 | AN49: =AM49+(AN$39-AM$39) -> 0.0905 | AO49: =AN49+(AO$39-AN$39) -> 0.0905 | AP49: =AO49+(AP$39-AO$39) -> 0.0905 | AQ49: =AP49+(AQ$39-AP$39) -> 0.0905 | AR49: =AQ49+(AR$39-AQ$39) -> 0.0905 | AS49: =AR49+(AS$39-AR$39) -> 0.0905 | AT49: =AS49+(AT$39-AS$39) -> 0.0905 | AU49: =AT49+(AU$39-AT$39) -> 0.0905 | ... BG49: =BF49+(BG$39-BF$39) -> 0.0905
A50: Общие | D50: ЦМИ | F50: Курс рубля к рупии, руб. (средний за период) | G50: INR/руб | J50: 3.527325 | K50: 3.791175 | L50: 3.7073 | M50: 3.47975 | N50: 3.45395 | O50: 3.408225 | P50: 3.3615 | Q50: 3.58125 | R50: 4.649125 | S50: 4.486975 | T50: 4.550725 | U50: 4.922125 | V50: 5.181825 | W50: 6.26285 | AC50: 0.97310308 | AD50: 0.99673776 | AE50: 0.87766993 | AF50: 1.0309732 | AG50: 1.1060709 | AH50: 0.96052923 | AI50: 0.8550249 | AJ50: 0.96240781 | AK50: 0.9915134 | AL50: 1.0153573 | AM50: 1.0404584 | AN50: =AN14/AN47 -> 1.0404962 | AO50: =AO14/AO47 -> 1.0404962 | AP50: =AP14/AP47 -> 1.0404962 | AQ50: =AQ14/AQ47 -> 1.0404962 | AR50: =AR14/AR47 -> 1.0404962 | AS50: =AS14/AS47 -> 1.0404962 | AT50: =AT14/AT47 -> 1.0404962 | AU50: =AU14/AU47 -> 1.0404962 | ... BG50: =BG14/BG47 -> 1.0404962
A51: Общие | D51: ЦМИ | F51: Курс рубля к рупии, руб. (на конец периода) | G51: INR/руб | J51: 3.6857 | K51: 3.8607 | L51: 3.5331 | M51: 3.3492 | N51: 3.5614 | O51: 3.3731 | P51: 3.3682 | Q51: 4.3064 | R51: 4.3994 | S51: 4.6219 | T51: 5.1024 | U51: 4.9036 | V51: 5.433 | W51: 9.354 | AC51: 1.00755 | AD51: 0.998422 | AE51: 0.848785 | AF51: 1.0773574 | AG51: 1.18797 | AH51: 0.86999555 | AI51: 0.92880991 | AJ51: 0.97867011 | AK51: 1.0004757 | AL51: 1.0270841 | AM51: 1.0494969 | AN51: =AN7/AN48 -> 1.0404962 | AO51: =AO7/AO48 -> 1.0404962 | AP51: =AP7/AP48 -> 1.0404962 | AQ51: =AQ7/AQ48 -> 1.0404962 | AR51: =AR7/AR48 -> 1.0404962 | AS51: =AS7/AS48 -> 1.0404962 | AT51: =AT7/AT48 -> 1.0404962 | AU51: =AU7/AU48 -> 1.0404962 | ... BG51: =BG7/BG48 -> 1.0404962
A52: Общие | D52: ЦМИ | F52: SOFR | G52: % | AA52: 0.03 | AB52: 0.0155 | AC52: 0.0007 | AD52: 0.0005 | AE52: 0.043 | AF52: 0.0538 | AG52: 0.0449 | AH52: 0.0387 | AI52: 0.037 | AJ52: 0.0347 | AK52: 0.0334 | AL52: 0.03125 | AM52: 0.03125 | AN52: =AM52 -> 0.03125 | AO52: =AN52 -> 0.03125 | AP52: =AO52 -> 0.03125 | AQ52: =AP52 -> 0.03125 | AR52: =AQ52 -> 0.03125 | AS52: =AR52 -> 0.03125 | AT52: =AS52 -> 0.03125 | AU52: =AT52 -> 0.03125 | ... BG52: =BF52 -> 0.03125
A53: Общие | D53: ЦМИ | F53: ОФЗ 10Y | G53: % | AB53: 0.0641 | AC53: 0.0627 | AD53: 0.0844 | AE53: 0.1031 | AF53: 0.1186 | AG53: 0.1522 | AH53: 0.1444 | AI53: 0.1569 | AJ53: 0.129 | AK53: 0.111 | AL53: 0.109 | AM53: 0.109 | AN53: =AM53 -> 0.109 | AO53: =AN53 -> 0.109 | AP53: =AO53 -> 0.109 | AQ53: =AP53 -> 0.109 | AR53: =AQ53 -> 0.109 | AS53: =AR53 -> 0.109 | AT53: =AS53 -> 0.109 | AU53: =AT53 -> 0.109 | ... BG53: =BF53 -> 0.109
A54: Общие | D54: ЦМИ | F54: Инфляция - Рост индекса потребительских цен в Китае (CHN, eop CPI) | G54: % | W54: 0.01409697 | X54: 0.016161562 | Y54: 0.019880706 | Z54: 0.018518498 | AA54: 0.019138747 | AB54: 0.044131508 | AC54: 0.0026978704 | AD54: 0.014419056 | AE54: 0.018 | AF54: -0.003 | AG54: 0.00074883604 | AH54: 0.0078279526 | AI54: 0.0093427396 | AJ54: 0.013705743 | AK54: 0.014664101 | AL54: 0.01469173 | AM54: 0.014523738 | AN54: 0.02 | AO54: 0.02 | AP54: 0.02 | AQ54: 0.02 | AR54: 0.02 | AS54: 0.02 | AT54: 0.02 | AU54: 0.02 | AV54: 0.02 | AW54: 0.02 | AX54: 0.02 | AY54: 0.02 | AZ54: 0.02 | BA54: 0.02 | BB54: 0.02 | BC54: =BB54 -> 0.02 | BD54: =BC54 -> 0.02 | BE54: =BD54 -> 0.02 | BF54: =BE54 -> 0.02 | BG54: =BF54 -> 0.02
A55: Общие | D55: ЦМИ | F55: Инфляция - Рост индекса цен производителей без ТЭК | G55: % | AE55: -0.0097125826 | AF55: 0.12913871 | AG55: 0.08538144 | AH55: 0.015989758 | AI55: 0.065513513 | AJ55: 0.062810341 | AK55: 0.050407744 | AL55: 0.043678925 | AM55: 0.044339347 | AN55: 0.04 | AO55: =AN55 -> 0.04 | AP55: =AO55 -> 0.04 | AQ55: =AP55 -> 0.04 | AR55: =AQ55 -> 0.04 | AS55: =AR55 -> 0.04 | AT55: =AS55 -> 0.04 | AU55: =AT55 -> 0.04 | AV55: =AU55 -> 0.04 | ... BG55: =BF55 -> 0.04
A58: Отраслевые | B58: Уголь | D58: Аналитический Хаб | F58: Hard Coking Coal (FOB Australia) | G58: $/т | U58: 192 | V58: 149 | W58: 117 | X58: 90 | Y58: 143.2 | Z58: 187 | AA58: 207 | AB58: 177 | AC58: 125 | AD58: 225 | AE58: 365 | AF58: 295.91827 | AG58: 240.89668 | AH58: 187.62795 | AI58: 230 | AJ58: 205 | AK58: 209.69899 | AL58: 213.76531 | AM58: 218.54381 | AN58: 222.91469 | AO58: 227.37298 | AP58: 231.92044 | AQ58: 236.55885 | AR58: 241.29003 | AS58: 246.11583 | AT58: 251.03814 | AU58: 256.05891 | AV58: 261.18008 | AW58: 266.40369 | AX58: 271.73176 | AY58: 277.16639 | AZ58: 282.70972 | BA58: 288.36392 | BB58: 294.13119 | BC58: 300.01382 | BD58: 306.0141 | BE58: 312.13438 | BF58: 318.37706 | BG58: 324.74461
A59: Отраслевые | B59: Уголь | D59: Аналитический Хаб | F59: Антрацит | G59: $/т | U59: 169 | V59: 132 | W59: 108 | X59: 100 | Y59: 92 | Z59: 116 | AA59: 133.77083 | AB59: 140.02083 | AC59: 114.625 | AD59: 129.80501 | AE59: 176.34877 | AF59: 123.6981 | AG59: 107.45815 | AH59: 97.265639 | AI59: 109.40326 | AJ59: 109.71792 | AK59: 113.36147 | AL59: 116.35183 | AM59: 118.20004 | AN59: 120.02487 | AO59: 121.88369 | AP59: 123.77714 | AQ59: 125.70586 | AR59: 127.67051 | AS59: 129.67177 | AT59: 131.71031 | AU59: 133.78683 | AV59: 135.90205 | AW59: 138.05668 | AX59: 140.25146 | AY59: 142.48715 | AZ59: 144.7645 | BA59: 147.08429 | BB59: 149.44732 | BC59: 151.8544 | BD59: 154.30634 | BE59: 156.80399 | BF59: 159.3482 | BG59: 161.93984
A60: Отраслевые | B60: Уголь | D60: Аналитический Хаб | F60: Энергетический уголь (CIF ARA) | G60: $/т | U60: 93 | V60: 82 | W60: 76 | X60: 56.7 | Y60: 59.41 | Z60: 84.29 | AA60: 91.98 | AB60: 61 | AC60: 50 | AD60: 120.05 | AE60: 290.03916 | AF60: 124.35969 | AG60: 111.70828 | AH60: 99.46433 | AI60: 110 | AJ60: 103 | AK60: 101.63478 | AL60: 103.40852 | AM60: 105.48895 | AN60: 107.38775 | AO60: 109.32073 | AP60: 111.2885 | AQ60: 113.2917 | AR60: 115.33095 | AS60: 117.40691 | AT60: 119.52023 | AU60: 121.67159 | AV60: 123.86168 | AW60: 126.09119 | AX60: 128.36083 | AY60: 130.67133 | AZ60: 133.02341 | BA60: 135.41784 | BB60: 137.85536 | BC60: 140.33675 | BD60: 142.86281 | BE60: 145.43434 | BF60: 148.05216 | BG60: 150.7171
A61: Отраслевые | B61: Уголь | D61: Аналитический Хаб | F61: Thermal Coal (FOB Newcastle) | G61: $/т | U61: 95 | V61: 84 | W61: 71 | X61: 57.73 | Y61: 65.42 | Z61: 87.53 | AA61: 105.78 | AB61: 78 | AC61: 61 | AD61: 132.98159 | AE61: 344.61073 | AF61: 173.52951 | AG61: 136.0315 | AH61: 108.36739 | AI61: 128 | AJ61: 120 | AK61: 118.78755 | AL61: 120.63029 | AM61: 122.78755 | AN61: 124.99772 | AO61: 127.24768 | AP61: 129.53814 | AQ61: 131.86983 | AR61: 134.24348 | AS61: 136.65986 | AT61: 139.11974 | AU61: 141.6239 | AV61: 144.17313 | AW61: 146.76824 | AX61: 149.41007 | AY61: 152.09945 | AZ61: 154.83724 | BA61: 157.62431 | BB61: 160.46155 | BC61: 163.34986 | BD61: 166.29016 | BE61: 169.28338 | BF61: 172.33048 | BG61: 175.43243
A63: Отраслевые | B63: Металлы | C63: Цветная металлургия | D63: Аналитический Хаб | F63: Алюминий (London Metals Exchange, без премии) | G63: $/т | U63: 2052 | V63: 1888 | W63: 1895 | X63: 1681 | Y63: 1611 | Z63: 2111 | AA63: 2114 | AB63: 1794 | AC63: 1706 | AD63: 2477 | AE63: 2701 | AF63: 2253.8796 | AG63: 2420.2282 | AH63: 2633.0714 | AI63: 3340 | AJ63: 3000 | AK63: 2890 | AL63: 2985 | AM63: 3051.7266 | AN63: 3112.7611 | AO63: 3175.0163 | AP63: 3238.5166 | AQ63: 3303.287 | AR63: 3369.3527 | AS63: 3436.7398 | AT63: 3505.4746 | AU63: 3575.5841 | AV63: 3647.0957 | AW63: 3720.0377 | AX63: 3794.4384 | AY63: 3870.3272 | AZ63: 3947.7337 | BA63: 4026.6884 | BB63: 4107.2222 | BC63: 4189.3666 | BD63: 4273.1539 | BE63: 4358.617 | BF63: 4445.7894 | BG63: 4534.7051
A64: Отраслевые | B64: Металлы | C64: Черная металлургия | D64: Аналитический Хаб | F64: Арматура (Rebar, EXW Russia) | G64: $/т | U64: 634 | V64: 543 | W64: 489 | X64: 332.18516 | Y64: 363.50508 | Z64: 451.97062 | AA64: 501.82639 | AB64: 493.82921 | AC64: 423.67839 | AD64: 718.47756 | AE64: 644.36337 | AF64: 551.22299 | AG64: 563.2095 | AH64: 514.79469 | AI64: 523.2944 | AJ64: 543.44997 | AK64: 556.23478 | AL64: 591.21535 | AM64: 604.03416 | AN64: 615.75233 | AO64: 627.69833 | AP64: 639.87662 | AQ64: 652.2917 | AR64: 664.9482 | AS64: 677.85083 | AT64: 691.00437 | AU64: 704.41372 | AV64: 718.08387 | AW64: 732.01989 | AX64: 746.22697 | AY64: 760.71039 | AZ64: 775.47554 | BA64: 790.52791 | BB64: 805.8731 | BC64: 821.51682 | BD64: 837.46488 | BE64: 853.72323 | BF64: 870.2979 | BG64: 887.19507
A65: Отраслевые | B65: Металлы | C65: Черная металлургия | D65: Аналитический Хаб | F65: Арматура (Rebar, FOB Black Sea) | G65: $/т | U65: 619 | V65: 586 | W65: 527 | X65: 361.41667 | Y65: 372.83333 | Z65: 465.5 | AA65: 530.41667 | AB65: 448.85833 | AC65: 445.03333 | AD65: 705.3 | AE65: 642.29167 | AF65: 541.10417 | AG65: 535.58333 | AH65: 512.9 | AI65: 522.80294 | AJ65: 550.9457 | AK65: 556.23478 | AL65: 591.21535 | AM65: 604.03416 | AN65: 615.75233 | AO65: 627.69833 | AP65: 639.87662 | AQ65: 652.2917 | AR65: 664.9482 | AS65: 677.85083 | AT65: 691.00437 | AU65: 704.41372 | AV65: 718.08387 | AW65: 732.01989 | AX65: 746.22697 | AY65: 760.71039 | AZ65: 775.47554 | BA65: 790.52791 | BB65: 805.8731 | BC65: 821.51682 | BD65: 837.46488 | BE65: 853.72323 | BF65: 870.2979 | BG65: 887.19507
A66: Отраслевые | B66: Металлы | C66: Трубы | D66: Аналитический Хаб | F66: Бесшовные трубы (EXW Russia) | G66: $/т | I66: Нет исторических данных с 2018 года | U66: 1288.8095 | V66: 1218.3526 | W66: 1040.3368 | X66: 1078 | Y66: 970 | Z66: 1152 | AA66: 1294 | AB66: 1300 | AC66: 1166 | AD66: 1149 | AE66: 1241 | AF66: 1249.4733 | AG66: 1252.1167 | AH66: 1237.3284 | AI66: 1268.6015 | AJ66: 1309.2294 | AK66: 1337.1909 | AL66: 1375.8245 | AM66: 1404.0636 | AN66: 1429.8486 | AO66: 1456.1079 | AP66: 1482.8503 | AQ66: 1510.0847 | AR66: 1537.8202 | AS66: 1566.066 | AT66: 1594.8315 | AU66: 1624.1264 | AV66: 1653.9603 | AW66: 1684.3432 | AX66: 1715.2852 | AY66: 1746.7967 | AZ66: 1778.8881 | BA66: 1811.5701 | BB66: 1844.8537 | BC66: 1878.7498 | BD66: 1913.2699 | BE66: 1948.4253 | BF66: 1984.228 | BG66: 2020.6896
A67: Отраслевые | B67: Металлы | C67: Черная металлургия | D67: Аналитический Хаб | F67: Горячебрикетированное железо (HBI, EXW Russia) | G67: $/т | I67: Нет исторических данных с 2018 года | U67: 395 | V67: 369 | W67: 370 | X67: 262 | Y67: 216.90683 | Z67: 219.89667 | AA67: 272.25248 | AB67: 242.31184 | AC67: 217.08954 | AD67: 399.71317 | AE67: 326 | AF67: 240 | AG67: 243.39663 | AH67: 237.06217 | AI67: 262.11028 | AJ67: 286.53388 | AK67: 293.55459 | AL67: 311.71549 | AM67: 318.61611 | AN67: 324.78794 | AO67: 331.0796 | AP67: 337.49342 | AQ67: 344.03177 | AR67: 350.69708 | AS67: 357.49183 | AT67: 364.41852 | AU67: 371.47972 | AV67: 378.67806 | AW67: 386.01621 | AX67: 393.49688 | AY67: 401.12285 | AZ67: 408.89694 | BA67: 416.82205 | BB67: 424.9011 | BC67: 433.13711 | BD67: 441.53311 | BE67: 450.09224 | BF67: 458.81765 | BG67: 467.7126
A68: Отраслевые | B68: Металлы | C68: Черная металлургия | D68: Аналитический Хаб | F68: Горячебрикетированное железо (HBI, FOB Black Sea) | G68: $/т | I68: Нет исторических данных с 2018 года | U68: 371 | V68: 350 | W68: 363 | X68: 257 | Y68: 236 | Z68: 240 | AA68: 297 | AB68: 262 | AC68: 256 | AD68: 400 | AE68: 363 | AF68: 280 | AG68: 276.125 | AH68: 270.28333 | AI68: 305 | AJ68: 299.08094 | AK68: 306.01932 | AL68: 325.45297 | AM68: 335.57454 | AN68: 342.08463 | AO68: 348.7213 | AP68: 355.48701 | AQ68: 362.38428 | AR68: 369.41567 | AS68: 376.58379 | AT68: 383.89132 | AU68: 391.34096 | AV68: 398.93548 | AW68: 406.67772 | AX68: 414.57054 | AY68: 422.61688 | AZ68: 430.81975 | BA68: 439.18217 | BB68: 447.70728 | BC68: 456.39823 | BD68: 465.25827 | BE68: 474.29068 | BF68: 483.49883 | BG68: 492.88615
A69: Отраслевые | B69: Металлы | C69: Черная металлургия | D69: Аналитический Хаб | F69: Горячекатанный прокат (HRC, EXW Russia) | G69: $/т | U69: 561 | V69: 509 | W69: 477 | X69: 0 | Y69: 424 | Z69: 534 | AA69: 549.21676 | AB69: 524.52619 | AC69: 473.98652 | AD69: 854.39993 | AE69: 755.29507 | AF69: 603.6808 | AG69: 595.4453 | AH69: 579.81106 | AI69: 588.78535 | AJ69: 627.00517 | AK69: 633.45663 | AL69: 647.33056 | AM69: 661.38837 | AN69: 674.20018 | AO69: 687.2607 | AP69: 700.57477 | AQ69: 714.14732 | AR69: 727.98338 | AS69: 742.08808 | AT69: 756.46663 | AU69: 771.12437 | AV69: 786.06674 | AW69: 801.29926 | AX69: 816.82759 | AY69: 832.65748 | AZ69: 848.7948 | BA69: 865.24553 | BB69: 882.01578 | BC69: 899.11175 | BD69: 916.53979 | BE69: 934.30637 | BF69: 952.41806 | BG69: 970.8816
A70: Отраслевые | B70: Металлы | C70: Черная металлургия | D70: Аналитический Хаб | F70: Горячекатанный прокат (HRC, FOB Black Sea) | G70: $/т | U70: 581 | V70: 543 | W70: 522 | X70: 349.83333 | Y70: 388.83333 | Z70: 503.75 | AA70: 555.16667 | AB70: 460.64583 | AC70: 469.89583 | AD70: 860.28333 | AE70: 705.8125 | AF70: 587.34167 | AG70: 524.575 | AH70: 459.58333 | AI70: 497.77949 | AJ70: 537.06067 | AK70: 541.45043 | AL70: 553.54025 | AM70: 565.50147 | AN70: 576.43493 | AO70: 587.58028 | AP70: 598.94164 | AQ70: 610.5232 | AR70: 622.32924 | AS70: 634.36413 | AT70: 646.6323 | AU70: 659.13828 | AV70: 671.88671 | AW70: 684.88229 | AX70: 698.12982 | AY70: 711.6342 | AZ70: 725.40042 | BA70: 739.43357 | BB70: 753.73884 | BC70: 768.3215 | BD70: 783.18697 | BE70: 798.34072 | BF70: 813.78837 | BG70: 829.53563
A71: Отраслевые | B71: Металлы | C71: Черная металлургия | D71: Аналитический Хаб | F71: Горячеоцинкованный прокат (HDG, EXW Russia) | G71: $/т | U71: 957 | V71: 815 | W71: 716 | X71: 562 | Y71: 647 | Z71: 700 | AA71: 769 | AB71: 731.41324 | AC71: 657.03943 | AD71: 1205.3842 | AE71: 1022.2896 | AF71: 833.58902 | AG71: 920.6993 | AH71: 940.1082 | AI71: 918.31282 | AJ71: 964.6936 | AK71: 978.4985 | AL71: 998.72867 | AM71: 1020.2489 | AN71: 1039.879 | AO71: 1059.8874 | AP71: 1080.2814 | AQ71: 1101.0684 | AR71: 1122.256 | AS71: 1143.8518 | AT71: 1165.8639 | AU71: 1188.3002 | AV71: 1211.1689 | AW71: 1234.4784 | AX71: 1258.2371 | AY71: 1282.4538 | AZ71: 1307.1372 | BA71: 1332.2965 | BB71: 1357.9407 | BC71: 1384.0792 | BD71: 1410.7216 | BE71: 1437.8777 | BF71: 1465.5572 | BG71: 1493.7704
A72: Отраслевые | B72: Металлы | C72: Черная металлургия | D72: Аналитический Хаб | F72: Горячеоцинкованный прокат (HDG, FOB Black Sea) | G72: $/т | U72: 737.64408 | V72: 692.30197 | W72: 649.52198 | X72: 613 | Y72: 657 | Z72: 735 | AA72: 760.125 | AB72: 868.97771 | AC72: 723.10198 | AD72: 1245.1923 | AE72: 1038.8929 | AF72: 836.48107 | AG72: 1050.7969 | AH72: 1147.5993 | AI72: 1083.1547 | AJ72: 1120.0551 | AK72: 1137.3462 | AL72: 1160.5918 | AM72: 1185.6542 | AN72: 1208.4836 | AO72: 1231.7531 | AP72: 1255.4713 | AQ72: 1279.6469 | AR72: 1304.2886 | AS72: 1329.4054 | AT72: 1355.0067 | AU72: 1381.1016 | AV72: 1407.6997 | AW72: 1434.8108 | AX72: 1462.4447 | AY72: 1490.6116 | AZ72: 1519.3217 | BA72: 1548.5855 | BB72: 1578.4138 | BC72: 1608.8173 | BD72: 1639.8073 | BE72: 1671.3951 | BF72: 1703.5922 | BG72: 1736.4104
A73: Отраслевые | B73: Металлы | C73: Черная металлургия | D73: Аналитический Хаб | F73: Железная руда (Iron Ore 62%, CFR China) | G73: $/т | U73: 129 | V73: 136 | W73: 97 | X73: 55 | Y73: 58 | Z73: 71 | AA73: 68.93 | AB73: 93 | AC73: 108 | AD73: 159 | AE73: 121 | AF73: 119.63419 | AG73: 110.01542 | AH73: 101.86989 | AI73: 105 | AJ73: 100 | AK73: 98 | AL73: 99.710305 | AM73: 101.71633 | AN73: 103.54723 | AO73: 105.41108 | AP73: 107.30848 | AQ73: 109.24003 | AR73: 111.20635 | AS73: 113.20806 | AT73: 115.24581 | AU73: 117.32023 | AV73: 119.432 | AW73: 121.58177 | AX73: 123.77025 | AY73: 125.99811 | AZ73: 128.26608 | BA73: 130.57487 | BB73: 132.92521 | BC73: 135.31787 | BD73: 137.75359 | BE73: 140.23315 | BF73: 142.75735 | BG73: 145.32698
A74: Отраслевые | B74: Металлы | C74: Черная металлургия | D74: Аналитический Хаб | F74: Заготовка квадратная (Billet, EXW Russia) | G74: $/т | U74: 574.97962 | V74: 467.93015 | W74: 445.59877 | X74: 300.76849 | Y74: 274.67175 | Z74: 452.47062 | AA74: 460.30973 | AB74: 413 | AC74: 367 | AD74: 623 | AE74: 583.86337 | AF74: 523.06049 | AG74: 516.47616 | AH74: 466.89167 | AI74: 475.57926 | AJ74: 501.80511 | AK74: 505.15981 | AL74: 537.82816 | AM74: 549.18149 | AN74: 559.55569 | AO74: 570.12619 | AP74: 580.89672 | AQ74: 591.87108 | AR74: 603.05312 | AS74: 614.44678 | AT74: 626.05608 | AU74: 637.88509 | AV74: 649.938 | AW74: 662.21903 | AX74: 674.73253 | AY74: 687.48289 | AZ74: 700.4746 | BA74: 713.71225 | BB74: 727.2005 | BC74: 740.94409 | BD74: 754.94788 | BE74: 769.21679 | BF74: 783.75585 | BG74: 798.5702
A75: Отраслевые | B75: Металлы | C75: Черная металлургия | D75: Аналитический Хаб | F75: Заготовка квадратная (Billet, FOB Black Sea) | G75: $/т | U75: 560 | V75: 511 | W75: 483 | X75: 330 | Y75: 284 | Z75: 466 | AA75: 488.9 | AB75: 408.49583 | AC75: 398.1775 | AD75: 607.3 | AE75: 581.79167 | AF75: 512.94167 | AG75: 488.85 | AH75: 436.89167 | AI75: 469.57926 | AJ75: 495.65652 | AK75: 498.87733 | AL75: 531.42994 | AM75: 542.6474 | AN75: 552.89745 | AO75: 563.34144 | AP75: 573.98307 | AQ75: 584.82606 | AR75: 595.87425 | AS75: 607.13151 | AT75: 618.60182 | AU75: 630.2892 | AV75: 642.19778 | AW75: 654.33176 | AX75: 666.69539 | AY75: 679.29305 | AZ75: 692.12916 | BA75: 705.20824 | BB75: 718.53491 | BC75: 732.11386 | BD75: 745.94987 | BE75: 760.04782 | BF75: 774.41267 | BG75: 789.04949
A76: Отраслевые | B76: Металлы | C76: Черная металлургия | D76: Аналитический Хаб | F76: Заготовка плоская (Slab, EXW Russia) | G76: $/т | I76: Нет исторических данных с 2018 года | U76: 529.97962 | V76: 439.93015 | W76: 451.59877 | X76: 477.07302 | Y76: 451.9448 | Z76: 586.35766 | AA76: 677.09416 | AB76: 471 | AC76: 421 | AD76: 779 | AE76: 575.0625 | AF76: 525.25 | AG76: 498.23333 | AH76: 425.825 | AI76: 476.82098 | AJ76: 478.44156 | AK76: 476.4013 | AL76: 487.24994 | AM76: 497.74892 | AN76: 507.34099 | AO76: 517.11458 | AP76: 527.07314 | AQ76: 537.22016 | AR76: 547.55924 | AS76: 558.09399 | AT76: 568.82814 | AU76: 579.76547 | AV76: 590.90982 | AW76: 602.26513 | AX76: 613.83539 | AY76: 625.62468 | AZ76: 637.63715 | BA76: 649.87704 | BB76: 662.34865 | BC76: 675.05639 | BD76: 688.00473 | BE76: 701.19824 | BF76: 714.64156 | BG76: 728.33943
A77: Отраслевые | B77: Металлы | C77: Черная металлургия | D77: Аналитический Хаб | F77: Заготовка плоская, (Slab, FOB Black Sea) | G77: $/т | U77: 515 | V77: 483 | W77: 489 | X77: 295.75 | Y77: 330 | Z77: 440.5 | AA77: 507.16667 | AB77: 421.59167 | AC77: 418.22083 | AD77: 749.31667 | AE77: 545.0625 | AF77: 495.25 | AG77: 468.23333 | AH77: 405.825 | AI77: 461.82098 | AJ77: 483.44156 | AK77: 486.4013 | AL77: 497.24994 | AM77: 507.74892 | AN77: 517.34099 | AO77: 527.11458 | AP77: 537.07314 | AQ77: 547.22016 | AR77: 557.55924 | AS77: 568.09399 | AT77: 578.82814 | AU77: 589.76547 | AV77: 600.90982 | AW77: 612.26513 | AX77: 623.83539 | AY77: 635.62468 | AZ77: 647.63715 | BA77: 659.87704 | BB77: 672.34865 | BC77: 685.05639 | BD77: 698.00473 | BE77: 711.19824 | BF77: 724.64156 | BG77: 738.33943
A78: Отраслевые | B78: Металлы | C78: Цветная металлургия | D78: Аналитический Хаб | F78: Золото (London Metals Exchange) | G78: $/унция | U78: 1669 | V78: 1412 | W78: 1266 | X78: 1160 | Y78: 1249 | Z78: 1258.75 | AA78: 1269.21 | AB78: 1393 | AC78: 1772 | AD78: 1799 | AE78: 1802 | AF78: 1943.2097 | AG78: 2389.3466 | AH78: 3445.1054 | AI78: 4470 | AJ78: 4200 | AK78: 3900 | AL78: 3680 | AM78: 3300 | AN78: 3352.8 | AO78: 3406.4448 | AP78: 3460.9479 | AQ78: 3516.3231 | AR78: 3572.5843 | AS78: 3629.7456 | AT78: 3687.8215 | AU78: 3746.8267 | AV78: 3806.7759 | AW78: 3867.6843 | AX78: 3929.5673 | AY78: 3992.4403 | AZ78: 4056.3194 | BA78: 4121.2205 | BB78: 4187.16 | BC78: 4254.1546 | BD78: 4322.2211 | BE78: 4391.3766 | BF78: 4461.6386 | BG78: 4533.0248
A79: Отраслевые | B79: Металлы | C79: Цветная металлургия | D79: Аналитический Хаб | F79: Медь (London Metals Exchange) | G79: $/т | U79: 7953 | V79: 7349 | W79: 6827 | X79: 5493 | Y79: 4871 | Z79: 6173 | AA79: 6544 | AB79: 6005 | AC79: 6186 | AD79: 9320 | AE79: 8805 | AF79: 8485.4496 | AG79: 9147.8793 | AH79: 9953.7722 | AI79: 13650 | AJ79: 12300 | AK79: 11000 | AL79: 11159.977 | AM79: 11347.08 | AN79: 11551.327 | AO79: 11759.251 | AP79: 11970.918 | AQ79: 12186.394 | AR79: 12405.749 | AS79: 12629.053 | AT79: 12856.376 | AU79: 13087.79 | AV79: 13323.371 | AW79: 13563.191 | AX79: 13807.329 | AY79: 14055.861 | AZ79: 14308.866 | BA79: 14566.426 | BB79: 14828.621 | BC79: 15095.537 | BD79: 15367.256 | BE79: 15643.867 | BF79: 15925.456 | BG79: 16212.115
A80: Отраслевые | B80: Металлы | C80: Черная металлургия | D80: Аналитический Хаб | F80: Металлолом (Scrap, EXW Russia ) | G80: $/т | U80: 318 | V80: 296 | W80: 273 | X80: 179.99403 | Y80: 176.84501 | Z80: 250.79558 | AA80: 279.41005 | AB80: 254.41598 | AC80: 236.89908 | AD80: 373.06437 | AE80: 356.38484 | AF80: 322.28456 | AG80: 304.82723 | AH80: 262.55354 | AI80: 270 | AJ80: 286.0263 | AK80: 292.75515 | AL80: 311.16598 | AM80: 317.91272 | AN80: 324.08017 | AO80: 330.36754 | AP80: 336.77717 | AQ80: 343.31142 | AR80: 349.97274 | AS80: 356.76359 | AT80: 363.68651 | AU80: 370.74406 | AV80: 377.93888 | AW80: 385.27363 | AX80: 392.75104 | AY80: 400.37389 | AZ80: 408.14502 | BA80: 416.06732 | BB80: 424.14374 | BC80: 432.37727 | BD80: 440.77099 | BE80: 449.32801 | BF80: 458.05153 | BG80: 466.94477
A81: Отраслевые | B81: Металлы | C81: Черная металлургия | D81: Аналитический Хаб | F81: Металлолом (Scrap, FOB Black sea) | G81: $/т | X81: 210.33333 | Y81: 204.33333 | Z81: 268.91667 | AA81: 301.5 | AB81: 256.30833 | AC81: 259.15417 | AD81: 420.56667 | AE81: 387.04583 | AF81: 330.525 | AG81: 316.125 | AH81: 286.95 | AI81: 315 | AJ81: 306.08094 | AK81: 309.01932 | AL81: 328.45297 | AM81: 335.57454 | AN81: 342.08463 | AO81: 348.7213 | AP81: 355.48701 | AQ81: 362.38428 | AR81: 369.41567 | AS81: 376.58379 | AT81: 383.89132 | AU81: 391.34096 | AV81: 398.93548 | AW81: 406.67772 | AX81: 414.57054 | AY81: 422.61688 | AZ81: 430.81975 | BA81: 439.18217 | BB81: 447.70728 | BC81: 456.39823 | BD81: 465.25827 | BE81: 474.29068 | BF81: 483.49883 | BG81: 492.88615
A82: Отраслевые | B82: Металлы | C82: Цветная металлургия | D82: Аналитический Хаб | F82: Никель (London Metals Exchange) | G82: $/т | U82: 17519 | V82: 15089 | W82: 16960 | X82: 11877 | Y82: 9645 | Z82: 10471 | AA82: 13186 | AB82: 13944 | AC82: 13803 | AD82: 18474 | AE82: 25623 | AF82: 21486.839 | AG82: 16814.606 | AH82: 15161.707 | AI82: 17500 | AJ82: 17500 | AK82: 17800 | AL82: 18145.164 | AM82: 18550.78 | AN82: 18884.694 | AO82: 19224.618 | AP82: 19570.661 | AQ82: 19922.933 | AR82: 20281.546 | AS82: 20646.614 | AT82: 21018.253 | AU82: 21396.582 | AV82: 21781.72 | AW82: 22173.791 | AX82: 22572.919 | AY82: 22979.232 | AZ82: 23392.858 | BA82: 23813.929 | BB82: 24242.58 | BC82: 24678.947 | BD82: 25123.168 | BE82: 25575.385 | BF82: 26035.742 | BG82: 26504.385
A83: Отраслевые | B83: Металлы | C83: Черная металлургия | D83: Аналитический Хаб | F83: Окатыш (Pellet, EXW Russia) | G83: $/т | I83: Нет исторических данных с 2018 года | U83: 113 | V83: 102 | W83: 73 | X83: 51.84683 | Y83: 48.906834 | Z83: 75.438338 | AA83: 81.127479 | AB83: 105.31184 | AC83: 87.089538 | AD83: 177.71317 | AE83: 107.25181 | AF83: 83.849122 | AG83: 100.02772 | AH83: 95.109797 | AI83: 98.008145 | AJ83: 106.68092 | AK83: 110.99138 | AL83: 113.38015 | AM83: 115.82698 | AN83: 118.05719 | AO83: 120.33045 | AP83: 122.64758 | AQ83: 125.00944 | AR83: 127.41689 | AS83: 129.87081 | AT83: 132.3721 | AU83: 134.92169 | AV83: 137.52049 | AW83: 140.16947 | AX83: 142.8696 | AY83: 145.62186 | AZ83: 148.42727 | BA83: 151.28686 | BB83: 154.20166 | BC83: 157.17276 | BD83: 160.20123 | BE83: 163.2882 | BF83: 166.43479 | BG83: 169.64216
A84: Отраслевые | B84: Металлы | C84: Черная металлургия | D84: Аналитический Хаб | F84: Окатыш (Pellet, FOB Black Sea) | G84: $/т | I84: Нет исторических данных с 2018 года | U84: 112 | V84: 107 | W84: 101 | X84: 66.916667 | Y84: 68 | Z84: 95.541667 | AA84: 105.875 | AB84: 125 | AC84: 126 | AD84: 178 | AE84: 152 | AF84: 117.4519 | AG84: 116.40809 | AH84: 107.75332 | AI84: 111.90539 | AJ84: 114.6598 | AK84: 116.26113 | AL84: 122.17204 | AM84: 126.45484 | AN84: 128.98393 | AO84: 131.56361 | AP84: 134.19488 | AQ84: 136.87878 | AR84: 139.61636 | AS84: 142.40868 | AT84: 145.25686 | AU84: 148.16199 | AV84: 151.12523 | AW84: 154.14774 | AX84: 157.23069 | AY84: 160.37531 | AZ84: 163.58281 | BA84: 166.85447 | BB84: 170.19156 | BC84: 173.59539 | BD84: 177.0673 | BE84: 180.60864 | BF84: 184.22082 | BG84: 187.90523
A85: Отраслевые | B85: Металлы | C85: Цветная металлургия | D85: Аналитический Хаб | F85: Свинец (London Metals Exchange) | G85: $/т | U85: 2074 | V85: 2155 | W85: 2112 | X85: 1794 | Y85: 1875 | Z85: 2250 | AA85: 2248 | AB85: 1999 | AC85: 1826 | AD85: 2202 | AE85: 2147 | AF85: 2136.7301 | AG85: 2070.2917 | AH85: 1962.5087 | AI85: 1985 | AJ85: 2050 | AK85: 2100 | AL85: 2140.7215 | AM85: 2188.5751 | AN85: 2227.9695 | AO85: 2268.0729 | AP85: 2308.8983 | AQ85: 2350.4584 | AR85: 2392.7667 | AS85: 2435.8365 | AT85: 2479.6815 | AU85: 2524.3158 | AV85: 2569.7535 | AW85: 2616.0091 | AX85: 2663.0972 | AY85: 2711.033 | AZ85: 2759.8316 | BA85: 2809.5085 | BB85: 2860.0797 | BC85: 2911.5611 | BD85: 2963.9692 | BE85: 3017.3207 | BF85: 3071.6324 | BG85: 3126.9218
A86: Отраслевые | B86: Металлы | C86: Цветная металлургия | D86: Аналитический Хаб | F86: Серебро (London Metals Exchange) | G86: $/унция | U86: 31.2 | V86: 23.9 | W86: 19.1 | X86: 15.7 | Y86: 17.1167 | Z86: 17.0742 | AA86: 15.71 | AB86: 16 | AC86: 21 | AD86: 25 | AE86: 22 | AF86: 23.391773 | AG86: 28.275966 | AH86: 40.185118 | AI86: 67 | AJ86: 63 | AK86: 54 | AL86: 48.759802 | AM86: 40.26 | AN86: 40.90416 | AO86: 41.558627 | AP86: 42.223565 | AQ86: 42.899142 | AR86: 43.585528 | AS86: 44.282896 | AT86: 44.991423 | AU86: 45.711285 | AV86: 46.442666 | AW86: 47.185749 | AX86: 47.940721 | AY86: 48.707772 | AZ86: 49.487097 | BA86: 50.27889 | BB86: 51.083352 | BC86: 51.900686 | BD86: 52.731097 | BE86: 53.574794 | BF86: 54.431991 | BG86: 55.302903
A87: Отраслевые | B87: Металлы | C87: Трубы | D87: Аналитический Хаб | F87: Трубы большого диаметра (LDP, EXW Russia) | G87: $/т | I87: Нет исторических данных с 2018 года | U87: 1777.5639 | V87: 1777.5639 | W87: 1813.1152 | X87: 1272 | Y87: 1179 | Z87: 1373 | AA87: 1083 | AB87: 979 | AC87: 840 | AD87: 923 | AE87: 996 | AF87: 999.54621 | AG87: 1006.9563 | AH87: 981.62208 | AI87: 1024.2368 | AJ87: 1062.2179 | AK87: 1081.8213 | AL87: 1112.2548 | AM87: 1135.1981 | AN87: 1156.3716 | AO87: 1177.8292 | AP87: 1199.6858 | AQ87: 1221.949 | AR87: 1244.6263 | AS87: 1267.7254 | AT87: 1291.2542 | AU87: 1315.2207 | AV87: 1339.633 | AW87: 1364.4996 | AX87: 1389.8288 | AY87: 1415.6292 | AZ87: 1441.9097 | BA87: 1468.6792 | BB87: 1495.9469 | BC87: 1523.722 | BD87: 1552.014 | BE87: 1580.8326 | BF87: 1610.1875 | BG87: 1640.0887
A88: Отраслевые | B88: Металлы | C88: Цветная металлургия | D88: Аналитический Хаб | F88: Ферросилико-марганец (Европа) | G88: $/т | X88: 0 | Y88: 845 | Z88: 1217 | AA88: 1179.3309 | AB88: 1070 | AC88: 1015 | AD88: 1704.2318 | AE88: 1615.6637 | AF88: 1164.0939 | AG88: 1202.4252 | AH88: 1312.5823 | AI88: 1346.6571 | AJ88: 1380.0079 | AK88: 1410.0587 | AL88: 1436.0343 | AM88: 1466.5303 | AN88: 1494.3943 | AO88: 1522.7878 | AP88: 1551.7208 | AQ88: 1581.2035 | AR88: 1611.2464 | AS88: 1641.8601 | AT88: 1673.0554 | AU88: 1704.8434 | AV88: 1737.2355 | AW88: 1770.2429 | AX88: 1803.8776 | AY88: 1838.1512 | AZ88: 1873.0761 | BA88: 1908.6646 | BB88: 1944.9292 | BC88: 1981.8828 | BD88: 2019.5386 | BE88: 2057.9098 | BF88: 2097.0101 | BG88: 2136.8533
A89: Отраслевые | B89: Металлы | C89: Цветная металлургия | D89: Аналитический Хаб | F89: Ферросилиций (Европа) | G89: $/т | X89: 0 | Y89: 1028 | Z89: 1461 | AA89: 1386.4786 | AB89: 1127 | AC89: 1079 | AD89: 1983.3542 | AE89: 1850.9836 | AF89: 1454.3802 | AG89: 1301.3415 | AH89: 1124.7959 | AI89: 1196.6571 | AJ89: 1303.3579 | AK89: 1410.0587 | AL89: 1507.836 | AM89: 1539.8568 | AN89: 1569.1141 | AO89: 1598.9272 | AP89: 1629.3069 | AQ89: 1660.2637 | AR89: 1691.8087 | AS89: 1723.9531 | AT89: 1756.7082 | AU89: 1790.0856 | AV89: 1824.0972 | AW89: 1858.7551 | AX89: 1894.0714 | AY89: 1930.0588 | AZ89: 1966.7299 | BA89: 2004.0978 | BB89: 2042.1756 | BC89: 2080.977 | BD89: 2120.5155 | BE89: 2160.8053 | BF89: 2201.8606 | BG89: 2243.696
A90: Отраслевые | B90: Металлы | C90: Цветная металлургия | D90: Аналитический Хаб | F90: Феррохром (High carbon/Europe) | G90: cents/lb | I90: Нет исторических данных с 2018 года | U90: 107.9 | V90: 99.6 | W90: 108.1 | X90: 96.8 | Y90: 103 | Z90: 120 | AA90: 125 | AB90: 88 | AC90: 81 | AD90: 124.6875 | AE90: 190 | AF90: 226.99174 | AG90: 139.03673 | AH90: 105.09796 | AI90: 118.48543 | AJ90: 119.48543 | AK90: 121.48543 | AL90: 123.36443 | AM90: 125.57044 | AN90: 127.95627 | AO90: 130.38744 | AP90: 132.8648 | AQ90: 135.38924 | AR90: 137.96163 | AS90: 140.5829 | AT90: 143.25398 | AU90: 145.9758 | AV90: 148.74934 | AW90: 151.57558 | AX90: 154.45552 | AY90: 157.39017 | AZ90: 160.38058 | BA90: 163.42782 | BB90: 166.53294 | BC90: 169.69707 | BD90: 172.92131 | BE90: 176.20682 | BF90: 179.55475 | BG90: 182.96629
A91: Отраслевые | B91: Металлы | C91: Черная металлургия | D91: Аналитический Хаб | F91: Холоднокатанный прокат (CRC, EXW Russia) | G91: $/т | U91: 679 | V91: 596 | W91: 538 | X91: 459 | Y91: 479 | Z91: 600 | AA91: 623.39734 | AB91: 658.83947 | AC91: 595.70839 | AD91: 1040.4122 | AE91: 854.76994 | AF91: 710.94205 | AG91: 774.21423 | AH91: 789.68275 | AI91: 763.98232 | AJ91: 806.54101 | AK91: 816.902 | AL91: 834.1553 | AM91: 852.18057 | AN91: 868.61744 | AO91: 885.37189 | AP91: 902.45007 | AQ91: 919.85825 | AR91: 937.60282 | AS91: 955.69028 | AT91: 974.12728 | AU91: 992.92057 | AV91: 1012.0771 | AW91: 1031.6038 | AX91: 1051.5079 | AY91: 1071.7967 | AZ91: 1092.4777 | BA91: 1113.5584 | BB91: 1135.0466 | BC91: 1156.9501 | BD91: 1179.2771 | BE91: 1202.0357 | BF91: 1225.2342 | BG91: 1248.8813
A92: Отраслевые | B92: Металлы | C92: Черная металлургия | D92: Аналитический Хаб | F92: Холоднокатанный прокат (CRC, FOB Black Sea) | G92: $/т | U92: 679 | V92: 622 | W92: 608 | X92: 427.75 | Y92: 442.25 | Z92: 554.08333 | AA92: 616.25 | AB92: 521.275 | AC92: 529.64583 | AD92: 1000.6042 | AE92: 838.16667 | AF92: 708.05 | AG92: 644.11667 | AH92: 582.19167 | AI92: 599.14041 | AJ92: 651.17952 | AK92: 658.05431 | AL92: 672.29216 | AM92: 686.77523 | AN92: 700.0129 | AO92: 713.50623 | AP92: 727.26018 | AQ92: 741.27979 | AR92: 755.57021 | AS92: 770.13667 | AT92: 784.98452 | AU92: 800.1192 | AV92: 815.54626 | AW92: 831.27137 | AX92: 847.3003 | AY92: 863.63892 | AZ92: 880.29323 | BA92: 897.26934 | BB92: 914.57348 | BC92: 932.21201 | BD92: 950.19139 | BE92: 968.51823 | BF92: 987.19925 | BG92: 1006.2413
A93: Отраслевые | B93: Металлы | C93: Цветная металлургия | D93: Аналитический Хаб | F93: Цинк (London Metals Exchange) | G93: $/т | U93: 1965 | V93: 1938 | W93: 2166 | X93: 1939 | Y93: 2101 | Z93: 2893 | AA93: 2892 | AB93: 2548 | AC93: 2269 | AD93: 3005 | AE93: 3475 | AF93: 2650.2715 | AG93: 2778.9315 | AH93: 2869.9383 | AI93: 3200 | AJ93: 2950 | AK93: 2980.6808 | AL93: 3026.92 | AM93: 3081.0509 | AN93: 3136.5099 | AO93: 3192.967 | AP93: 3250.4404 | AQ93: 3308.9484 | AR93: 3368.5094 | AS93: 3429.1426 | AT93: 3490.8672 | AU93: 3553.7028 | AV93: 3617.6694 | AW93: 3682.7875 | AX93: 3749.0777 | AY93: 3816.5611 | AZ93: 3885.2592 | BA93: 3955.1938 | BB93: 4026.3873 | BC93: 4098.8623 | BD93: 4172.6418 | BE93: 4247.7493 | BF93: 4324.2088 | BG93: 4402.0446
A94: Отраслевые | B94: Металлы | C94: Черная металлургия | D94: Аналитический Хаб | F94: Чугун (Pig iron, EXW Russia) | G94: $/т | I94: Нет исторических данных с 2018 года | U94: 430.1757 | V94: 346.64168 | W94: 339.48556 | X94: 230.82832 | Y94: 221.36705 | Z94: 339.73178 | AA94: 349.25364 | AB94: 384 | AC94: 337 | AD94: 508 | AE94: 457.7186 | AF94: 339.30755 | AG94: 334.51133 | AH94: 290.25305 | AI94: 319.36583 | AJ94: 332.93561 | AK94: 345.45174 | AL94: 361.64893 | AM94: 369.42229 | AN94: 376.52695 | AO94: 383.76861 | AP94: 391.1499 | AQ94: 398.67353 | AR94: 406.34225 | AS94: 414.15886 | AT94: 422.12623 | AU94: 430.24726 | AV94: 438.52493 | AW94: 446.96227 | AX94: 455.56237 | AY94: 464.32837 | AZ94: 473.26348 | BA94: 482.37097 | BB94: 491.65417 | BC94: 501.11649 | BD94: 510.76139 | BE94: 520.5924 | BF94: 530.61312 | BG94: 540.82723
A95: Отраслевые | B95: Металлы | C95: Черная металлургия | D95: Аналитический Хаб | F95: Чугун (Pig iron, FOB Black Sea) | G95: $/т | U95: 415.19608 | V95: 389.71154 | W95: 376.88679 | X95: 243.75 | Y95: 255.91667 | Z95: 352.66667 | AA95: 378.08333 | AB95: 326 | AC95: 340 | AD95: 550 | AE95: 468.95 | AF95: 375.64167 | AG95: 374.64167 | AH95: 313.51667 | AI95: 350.6574 | AJ95: 351.85267 | AK95: 352.57816 | AL95: 359.09012 | AM95: 366.73606 | AN95: 373.72291 | AO95: 380.84323 | AP95: 388.09959 | AQ95: 395.49459 | AR95: 403.03088 | AS95: 410.71117 | AT95: 418.53822 | AU95: 426.51485 | AV95: 434.64391 | AW95: 442.92833 | AX95: 451.37109 | AY95: 459.97522 | AZ95: 468.74381 | BA95: 477.68001 | BB95: 486.78705 | BC95: 496.06818 | BD95: 505.52676 | BE95: 515.16618 | BF95: 524.9899 | BG95: 535.00147
A96: Отраслевые | B96: Металлы | C96: Цветная металлургия | D96: Аналитический Хаб | F96: Платина (LME) | G96: $/унция | X96: 1054 | Y96: 989 | Z96: 949.91 | AA96: 879.64 | AB96: 865 | AC96: 886 | AD96: 1092 | AE96: 964 | AF96: 967.58415 | AG96: 956.0495 | AH96: 1286.3792 | AI96: 1870 | AJ96: 1800 | AK96: 1700 | AL96: 1651.9475 | AM96: 1687.0287 | AN96: 1719.0823 | AO96: 1751.7448 | AP96: 1785.028 | AQ96: 1818.9435 | AR96: 1853.5034 | AS96: 1888.72 | AT96: 1924.6057 | AU96: 1961.1732 | AV96: 1998.4355 | AW96: 2036.4057 | AX96: 2075.0974 | AY96: 2114.5243 | AZ96: 2154.7003 | BA96: 2195.6396 | BB96: 2237.3567 | BC96: 2279.8665 | BD96: 2323.184 | BE96: 2367.3245 | BF96: 2412.3036 | BG96: 2458.1374
A97: Отраслевые | B97: Металлы | C97: Цветная металлургия | D97: Аналитический Хаб | F97: Палладий (LME) | G97: $/унция | X97: 690 | Y97: 615 | Z97: 870.78 | AA97: 1030.49 | AB97: 1541 | AC97: 2201 | AD97: 2397 | AE97: 2109 | AF97: 1339.7181 | AG97: 983.05326 | AH97: 1153.7835 | AI97: 1430 | AJ97: 1380 | AK97: 1300 | AL97: 1100 | AM97: 1117.2125 | AN97: 1135.0879 | AO97: 1153.2494 | AP97: 1171.7013 | AQ97: 1190.4486 | AR97: 1209.4957 | AS97: 1228.8477 | AT97: 1248.5092 | AU97: 1268.4854 | AV97: 1288.7812 | AW97: 1309.4017 | AX97: 1330.3521 | AY97: 1351.6377 | AZ97: 1373.2639 | BA97: 1395.2361 | BB97: 1417.5599 | BC97: 1440.2409 | BD97: 1463.2847 | BE97: 1486.6973 | BF97: 1510.4844 | BG97: 1534.6522
A98: Отраслевые | B98: Металлы | C98: Цветная металлургия | D98: Аналитический Хаб | F98: Феррохром (6-8%, 58-60% Cr/China import CIF) | G98: cents/lb | I98: Добавлен 25.01.2019 | U98: 92 | V98: 87.5 | W98: 83 | X98: 76.5 | Y98: 78.5 | Z98: 95.5 | AA98: 86.305623 | AB98: 76 | AC98: 68 | AD98: 110.44018 | AE98: 103.21221 | AF98: 100.33604 | AG98: 94.321982 | AH98: 88.454225 | AI98: 99 | AJ98: 100 | AK98: 102 | AL98: 103.87901 | AM98: 106.08501 | AN98: 108.10063 | AO98: 110.15454 | AP98: 112.24747 | AQ98: 114.38018 | AR98: 116.5534 | AS98: 118.76791 | AT98: 121.0245 | AU98: 123.32397 | AV98: 125.66712 | AW98: 128.0548 | AX98: 130.48784 | AY98: 132.96711 | AZ98: 135.49349 | BA98: 138.06786 | BB98: 140.69115 | BC98: 143.36428 | BD98: 146.0882 | BE98: 148.86388 | BF98: 151.69229 | BG98: 154.57445
A99: Отраслевые | B99: Металлы | C99: Черная металлургия | D99: Аналитический Хаб | F99: Сварные трубы (EXW Russia) | G99: $/т | Z99: 564 | AA99: 575.80253 | AB99: 533 | AC99: 476 | AD99: 850 | AE99: 790 | AF99: 632.36625 | AG99: 634.51955 | AH99: 598.74901 | AI99: 647.92157 | AJ99: 680.89866 | AK99: 692.17988 | AL99: 713.3177 | AM99: 728.46561 | AN99: 742.28729 | AO99: 756.37193 | AP99: 770.72454 | AQ99: 785.35024 | AR99: 800.25423 | AS99: 815.44183 | AT99: 830.91844 | AU99: 846.68958 | AV99: 862.76087 | AW99: 879.13804 | AX99: 895.82693 | AY99: 912.83348 | AZ99: 930.16375 | BA99: 947.82394 | BB99: 965.82032 | BC99: 984.15933 | BD99: 1002.8475 | BE99: 1021.8915 | BF99: 1041.2981 | BG99: 1061.0743
A100: Отраслевые | B100: Металлы | C100: Черная металлургия | D100: Аналитический Хаб | F100: Кобальт | G100: $/фунт | X100: 13.52102 | Y100: 12.0596 | Z100: 26.931723 | AA100: 37.048163 | AB100: 16.5 | AC100: 15.4 | AD100: 23.7 | AE100: 30.5 | AF100: 15.514876 | AG100: 11.565854 | AH100: 15.570612 | AI100: 24 | AJ100: 23 | AK100: 21 | AL100: 21.366494 | AM100: 21.796357 | AN100: 22.232284 | AO100: 22.67693 | AP100: 23.130468 | AQ100: 23.593078 | AR100: 24.064939 | AS100: 24.546238 | AT100: 25.037163 | AU100: 25.537906 | AV100: 26.048664 | AW100: 26.569638 | AX100: 27.10103 | AY100: 27.643051 | AZ100: 28.195912 | BA100: 28.75983 | BB100: 29.335027 | BC100: 29.921727 | BD100: 30.520162 | BE100: 31.130565 | BF100: 31.753176 | BG100: 32.38824
A101: Отраслевые | B101: Уголь | D101: Аналитический Хаб | F101: PCI Coal Австралия, FOB | G101: $/т | I101: Добавлен 21.11.2020 | X101: 83.875 | Y101: 87.5 | Z101: 139.375 | AA101: 148.875 | AB101: 129 | AC101: 78 | AD101: 164 | AE101: 323 | AF101: 227.14699 | AG101: 169.9726 | AH101: 143.36883 | AI101: 163.83491 | AJ101: 146.02677 | AK101: 149.37398 | AL101: 152.27053 | AM101: 155.67438 | AN101: 158.78786 | AO101: 161.96362 | AP101: 165.20289 | AQ101: 168.50695 | AR101: 171.87709 | AS101: 175.31463 | AT101: 178.82092 | AU101: 182.39734 | AV101: 186.04529 | AW101: 189.7662 | AX101: 193.56152 | AY101: 197.43275 | AZ101: 201.3814 | BA101: 205.40903 | BB101: 209.51721 | BC101: 213.70756 | BD101: 217.98171 | BE101: 222.34134 | BF101: 226.78817 | BG101: 231.32393
A102: Отраслевые | B102: Уголь | D102: Аналитический Хаб | F102: Энергоуголь Baltic, FOB | X102: 0 | Y102: 0 | Z102: 0 | AA102: 0 | AB102: 0 | AC102: 0 | AD102: 111.13783 | AE102: 146.95515 | AF102: 86.985769 | AG102: 77.503433 | AH102: 64.714208 | AI102: 77.30132 | AJ102: 74 | AK102: 78.166427 | AL102: 80.702407 | AM102: 82.242162 | AN102: 83.766674 | AO102: 85.319509 | AP102: 86.901197 | AQ102: 88.512273 | AR102: 90.153287 | AS102: 91.824794 | AT102: 93.527363 | AU102: 95.261573 | AV102: 97.028013 | AW102: 98.827283 | AX102: 100.66 | AY102: 102.52677 | AZ102: 104.42825 | BA102: 106.36508 | BB102: 108.33791 | BC102: 110.34741 | BD102: 112.39428 | BE102: 114.4792 | BF102: 116.60289 | BG102: 118.76606
A103: Отраслевые | B103: Уголь | D103: Аналитический Хаб | F103: Энергоуголь Black sea, FOB | X103: 0 | Y103: 0 | Z103: 0 | AA103: 0 | AB103: 0 | AC103: 0 | AD103: 113.33045 | AE103: 158 | AF103: 92.336538 | AG103: 73.735577 | AH103: 68.899167 | AI103: 77.30132 | AJ103: 81.146765 | AK103: 83.281037 | AL103: 85.916195 | AM103: 87.572499 | AN103: 89.203617 | AO103: 90.865192 | AP103: 92.557793 | AQ103: 94.282001 | AR103: 96.038409 | AS103: 97.827619 | AT103: 99.650244 | AU103: 101.50691 | AV103: 103.39826 | AW103: 105.32493 | AX103: 107.2876 | AY103: 109.28693 | AZ103: 111.32361 | BA103: 113.39834 | BB103: 115.51184 | BC103: 117.66482 | BD103: 119.85804 | BE103: 122.09223 | BF103: 124.36818 | BG103: 126.68666
...

Sheet Inputs Q LTM
A1: INPUTS | B1: Отрасль | C1: Подотрасль/ Дивизион | D1: Источник | E1: Дата обновления | F1: Наименование | G1: Ед. измерения | H1: Link | I1: Комментарий к заполнению (формула) | J1: 2001 Q1 | K1: 2001 Q2 | L1: 2001 Q3 | M1: 2001 Q4 | N1: 2002 Q1 | O1: 2002 Q2 | P1: 2002 Q3 | Q1: 2002 Q4 | R1: 2003 Q1 | S1: 2003 Q2 | T1: 2003 Q3 | U1: 2003 Q4 | V1: 2004 Q1 | W1: 2004 Q2 | X1: 2004 Q3 | Y1: 2004 Q4 | Z1: 2005 Q1 | AA1: 2005 Q2 | AB1: 2005 Q3 | AC1: 2005 Q4 | AD1: 2006 Q1 | AE1: 2006 Q2 | AF1: 2006 Q3 | AG1: 2006 Q4 | AH1: 2007 Q1 | AI1: 2007 Q2 | AJ1: 2007 Q3 | AK1: 2007 Q4 | AL1: 2008 Q1 | AM1: 2008 Q2 | AN1: 2008 Q3 | AO1: 2008 Q4 | AP1: 2009 Q1 | AQ1: 2009 Q2 | AR1: 2009 Q3 | AS1: 2009 Q4 | AT1: 2010 Q1 | AU1: 2010 Q2 | AV1: 2010 Q3 | AW1: 2010 Q4 | AX1: 2011 Q1 | AY1: 2011 Q2 | AZ1: 2011 Q3 | BA1: 2011 Q4 | BB1: 2012 Q1 | BC1: 2012 Q2 | BD1: 2012 Q3 | BE1: 2012 Q4 | BF1: 2013 Q1 | BG1: 2013 Q2 | BH1: 2013 Q3 | BI1: 2013 Q4 | BJ1: 2014 Q1 | BK1: 2014 Q2 | BL1: 2014 Q3 | BM1: 2014 Q4 | BN1: 2015 Q1 | BO1: 2015 Q2 | BP1: 2015 Q3 | BQ1: 2015 Q4 | BR1: 2016 Q1 | BS1: 2016 Q2 | BT1: 2016 Q3 | BU1: 2016 Q4 | BV1: 2017 Q1 | BW1: 2017 Q2 | BX1: 2017 Q3 | BY1: 2017 Q4 | BZ1: 2018 Q1 | CA1: 2018 Q2 | CB1: 2018 Q3 | CC1: 2018 Q4 | CD1: 2019 Q1 | CE1: 2019 Q2 | CF1: 2019 Q3 | CG1: 2019 Q4 | CH1: 2020 Q1 | CI1: 2020 Q2 | CJ1: 2020 Q3 | CK1: 2020 Q4 | CL1: 2021 Q1 | CM1: 2021 Q2 | CN1: 2021 Q3 | CO1: 2021 Q4 | CP1: 2022 Q1 | CQ1: 2022 Q2 | CR1: 2022 Q3 | CS1: 2022 Q4 | CT1: 2023 Q1 | CU1: 2023 Q2 | CV1: 2023 Q3 | CW1: 2023 Q4 | CX1: 2024 Q1 | CY1: 2024 Q2 | CZ1: 2024 Q3 | DA1: 2024 Q4 | DB1: 2025 Q1 | DC1: 2025 Q2 | DD1: 2025 Q3 | DE1: 2025 Q4 | DF1: 2026 Q1 | DG1: 2026 Q2 | DH1: 2026 Q3 | DI1: 2026 Q4 | DJ1: 2027 Q1 | DK1: 2027 Q2 | DL1: 2027 Q3 | DM1: 2027 Q4 | DN1: 2028 Q1 | DO1: 2028 Q2 | DP1: 2028 Q3 | DQ1: 2028 Q4 | DR1: 2029 Q1 | DS1: 2029 Q2 | DT1: 2029 Q3 | DU1: 2029 Q4 | DV1: 2030 Q1 | DW1: 2030 Q2 | DX1: 2030 Q3 | DY1: 2030 Q4 | DZ1: 2031 Q1 | EA1: 2031 Q2 | EB1: 2031 Q3 | EC1: 2031 Q4 | ED1: 2032 Q1 | EE1: 2032 Q2 | EF1: 2032 Q3 | EG1: 2032 Q4 | EH1: 2033 Q1 | EI1: 2033 Q2 | EJ1: 2033 Q3 | EK1: 2033 Q4 | EL1: 2034 Q1 | EM1: 2034 Q2 | EN1: 2034 Q3 | EO1: 2034 Q4 | EP1: 2035 Q1 | EQ1: 2035 Q2 | ER1: 2035 Q3 | ES1: 2035 Q4 | ET1: 2036 Q1 | EU1: 2036 Q2 | EV1: 2036 Q3 | EW1: 2036 Q4 | EX1: 2037 Q1 | EY1: 2037 Q2 | EZ1: 2037 Q3 | FA1: 2037 Q4 | FB1: 2038 Q1 | FC1: 2038 Q2 | FD1: 2038 Q3 | FE1: 2038 Q4 | FF1: 2039 Q1 | FG1: 2039 Q2 | FH1: 2039 Q3 | FI1: 2039 Q4 | FJ1: 2040 Q1 | FK1: 2040 Q2 | FL1: 2040 Q3 | FM1: 2040 Q4 | FN1: 2041 Q1 | FO1: 2041 Q2 | FP1: 2041 Q3 | FQ1: 2041 Q4 | FR1: 2042 Q1 | FS1: 2042 Q2 | FT1: 2042 Q3 | FU1: 2042 Q4 | FV1: 2043 Q1 | FW1: 2043 Q2 | FX1: 2043 Q3 | FY1: 2043 Q4 | FZ1: 2044 Q1 | GA1: 2044 Q2 | GB1: 2044 Q3 | GC1: 2044 Q4 | GD1: 2045 Q1 | GE1: 2045 Q2 | GF1: 2045 Q3 | GG1: 2045 Q4 | GH1: 2046 Q1 | GI1: 2046 Q2 | GJ1: 2046 Q3 | GK1: 2046 Q4 | GL1: 2047 Q1 | GM1: 2047 Q2 | GN1: 2047 Q3 | GO1: 2047 Q4 | GP1: 2048 Q1 | GQ1: 2048 Q2 | GR1: 2048 Q3 | GS1: 2048 Q4 | GT1: 2049 Q1 | GU1: 2049 Q2 | GV1: 2049 Q3 | GW1: 2049 Q4 | GX1: 2050 Q1 | GY1: 2050 Q2 | GZ1: 2050 Q3 | HA1: 2050 Q4
A2: Общие | D2: ЦМИ | F2: Рост реального ВВП | G2: % | H2: Наименование листа, номер строки [например: Scenarios, line 352] | I2: =Inputs!I2 -> Базовый 11.09.2026 | J2: 0.047 | K2: 0.051 | L2: 0.06 | M2: 0.045 | N2: 0.038 | O2: 0.044 | P2: 0.044 | Q2: 0.062 | R2: 0.076 | S2: 0.08 | T2: 0.062 | U2: 0.077 | V2: 0.072 | W2: 0.08 | X2: 0.073 | Y2: 0.062 | Z2: 0.056 | AA2: 0.06 | AB2: 0.06 | AC2: 0.078 | AD2: 0.073 | AE2: 0.081 | AF2: 0.082 | AG2: 0.089 | AH2: 0.081 | AI2: 0.086 | AJ2: 0.082 | AK2: 0.092 | AL2: 0.092 | AM2: 0.079 | AN2: 0.064 | AO2: -0.013 | AP2: -0.092 | AQ2: -0.112 | AR2: -0.086 | AS2: -0.026 | AT2: 0.041 | AU2: 0.05 | AV2: 0.038 | AW2: 0.051 | AX2: 0.033 | AY2: 0.033 | AZ2: 0.05 | BA2: 0.052 | BB2: 0.054 | BC2: 0.044 | BD2: 0.033 | BE2: 0.019 | BF2: 0.013 | BG2: 0.017 | BH2: 0.016 | BI2: 0.025 | BJ2: 0.005 | BK2: 0.013 | BL2: 0.009 | BM2: 0.003 | BN2: -0.018 | BO2: -0.035 | BP2: -0.02 | BQ2: -0.019 | BR2: -0.004 | BS2: 0.003 | BT2: 0.003 | BU2: 0.01 | BV2: 0.015 | BW2: 0.025 | BX2: 0.023 | BY2: 0.003 | BZ2: 0.025631888 | CA2: 0.027290417 | CB2: 0.02633714 | CC2: 0.032389366 | CD2: 0.013884401 | CE2: 0.013573986 | CF2: 0.027674168 | CG2: 0.03069449 | CH2: 0.015160754 | CI2: -0.073154521 | CJ2: -0.033281492 | CK2: -0.01301204 | CL2: 0.0086873079 | CM2: 0.11365971 | CN2: 0.052215697 | CO2: 0.060835967 | CP2: 0.033757193 | CQ2: -0.03703181 | CR2: -0.029390265 | CS2: -0.019173764 | CT2: -0.0083084244 | CU2: 0.053442387 | CV2: 0.06146633 | CW2: 0.051925939 | CX2: 0.058907601 | CY2: 0.048963808 | CZ2: 0.037934539 | DA2: 0.052090712 | DB2: 0.013093854 | DC2: 0.010385269 | DD2: 0.0075002464 | DE2: 0.0095134385 | DF2: -0.0015161431 | DG2: 0.013 | DH2: 0.0065734477 | DI2: 0.006594219 | DJ2: 0.017387688 | DK2: 0.0093453298 | DL2: 0.014243555 | DM2: 0.014751328 | DN2: =Inputs!AK2 -> 0.0163 | DO2: =Inputs!AK2 -> 0.0163 | DP2: =Inputs!AK2 -> 0.0163 | DQ2: =Inputs!AK2 -> 0.0163 | DR2: =Inputs!AL2 -> 0.0182 | DS2: =Inputs!AL2 -> 0.0182 | DT2: =Inputs!AL2 -> 0.0182 | DU2: =Inputs!AL2 -> 0.0182 | DV2: =Inputs!AM2 -> 0.0182 | DW2: =Inputs!AM2 -> 0.0182 | DX2: =Inputs!AM2 -> 0.0182 | DY2: =Inputs!AM2 -> 0.0182 | DZ2: =Inputs!AN2 -> 0.0182 | EA2: =Inputs!AN2 -> 0.0182 | EB2: =Inputs!AN2 -> 0.0182 | EC2: =Inputs!AN2 -> 0.0182 | ED2: =Inputs!AO2 -> 0.0182 | EE2: =Inputs!AO2 -> 0.0182 | EF2: =Inputs!AO2 -> 0.0182 | EG2: =Inputs!AO2 -> 0.0182 | EH2: =Inputs!AP2 -> 0.0182 | EI2: =Inputs!AP2 -> 0.0182 | EJ2: =Inputs!AP2 -> 0.0182 | EK2: =Inputs!AP2 -> 0.0182 | EL2: =Inputs!AQ2 -> 0.0182 | EM2: =Inputs!AP2 -> 0.0182 | EN2: =Inputs!AQ2 -> 0.0182 | EO2: =Inputs!AQ2 -> 0.0182 | EP2: =Inputs!AR2 -> 0.0182 | EQ2: =Inputs!AR2 -> 0.0182 | ER2: =Inputs!AR2 -> 0.0182 | ES2: =Inputs!AR2 -> 0.0182 | ET2: =Inputs!AS2 -> 0.0182 | EU2: =Inputs!AS2 -> 0.0182 | EV2: =Inputs!AS2 -> 0.0182 | EW2: =Inputs!AS2 -> 0.0182 | EX2: =Inputs!AT2 -> 0.0182 | EY2: =Inputs!AT2 -> 0.0182 | EZ2: =Inputs!AT2 -> 0.0182 | FA2: =Inputs!AT2 -> 0.0182 | FB2: =Inputs!AU2 -> 0.0182 | FC2: =Inputs!AU2 -> 0.0182 | FD2: =Inputs!AU2 -> 0.0182 | FE2: =Inputs!AU2 -> 0.0182 | FF2: =Inputs!AV2 -> 0.0182 | FG2: =Inputs!AV2 -> 0.0182 | FH2: =Inputs!AV2 -> 0.0182 | FI2: =Inputs!AV2 -> 0.0182 | FJ2: =Inputs!AW2 -> 0.0182 | FK2: =Inputs!AW2 -> 0.0182 | FL2: =Inputs!AW2 -> 0.0182 | FM2: =Inputs!AW2 -> 0.0182 | FN2: =Inputs!AX2 -> 0.0182 | FO2: =Inputs!AX2 -> 0.0182 | FP2: =Inputs!AX2 -> 0.0182 | FQ2: =Inputs!AX2 -> 0.0182 | FR2: =Inputs!AY2 -> 0.0182 | FS2: =Inputs!AY2 -> 0.0182 | FT2: =Inputs!AY2 -> 0.0182 | FU2: =Inputs!AY2 -> 0.0182 | FV2: =Inputs!AZ2 -> 0.0182 | FW2: =Inputs!AZ2 -> 0.0182 | FX2: =Inputs!AZ2 -> 0.0182 | FY2: =Inputs!AZ2 -> 0.0182 | FZ2: =Inputs!BA2 -> 0.0182 | GA2: =Inputs!BA2 -> 0.0182 | GB2: =Inputs!BA2 -> 0.0182 | GC2: =Inputs!BA2 -> 0.0182 | GD2: =Inputs!BB2 -> 0.0182 | GE2: =Inputs!BB2 -> 0.0182 | GF2: =Inputs!BB2 -> 0.0182 | GG2: =Inputs!BB2 -> 0.0182 | GH2: =Inputs!BC2 -> 0.0182 | GI2: =Inputs!BC2 -> 0.0182 | GJ2: =Inputs!BC2 -> 0.0182 | GK2: =Inputs!BC2 -> 0.0182 | GL2: =Inputs!BD2 -> 0.0182 | GM2: =Inputs!BD2 -> 0.0182 | GN2: =Inputs!BD2 -> 0.0182 | GO2: =Inputs!BD2 -> 0.0182 | GP2: =Inputs!BE2 -> 0.0182 | GQ2: =Inputs!BE2 -> 0.0182 | GR2: =Inputs!BE2 -> 0.0182 | GS2: =Inputs!BE2 -> 0.0182 | GT2: =Inputs!BF2 -> 0.0182 | GU2: =Inputs!BF2 -> 0.0182 | GV2: =Inputs!BF2 -> 0.0182 | GW2: =Inputs!BF2 -> 0.0182 | GX2: =Inputs!BG2 -> 0.0182 | GY2: =Inputs!BG2 -> 0.0182 | GZ2: =Inputs!BG2 -> 0.0182 | HA2: =Inputs!BG2 -> 0.0182
A3: Общие | D3: ЦМИ | F3: Инфляция - Рост индекса потребительских цен (RUB, eop CPI) | G3: % | I3: С 2021 года прогноз CIB | J3: 0.237 | K3: 0.237 | L3: 0.2 | M3: 0.186 | N3: 0.168 | O3: 0.147 | P3: 0.149 | Q3: 0.151 | R3: 0.148 | S3: 0.139 | T3: 0.133 | U3: 0.12 | V3: 0.103 | W3: 0.101 | X3: 0.114 | Y3: 0.117 | Z3: 0.136 | AA3: 0.137 | AB3: 0.123 | AC3: 0.109 | AD3: 0.106 | AE3: 0.09 | AF3: 0.095 | AG3: 0.09 | AH3: 0.074 | AI3: 0.085 | AJ3: 0.094 | AK3: 0.119 | AL3: 0.133 | AM3: 0.151 | AN3: 0.15 | AO3: 0.133 | AP3: 0.14 | AQ3: 0.119 | AR3: 0.107 | AS3: 0.088 | AT3: 0.065 | AU3: 0.058 | AV3: 0.07 | AW3: 0.088 | AX3: 0.095 | AY3: 0.094 | AZ3: 0.072 | BA3: 0.061 | BB3: 0.037 | BC3: 0.043 | BD3: 0.066 | BE3: 0.066 | BF3: 0.07 | BG3: 0.069 | BH3: 0.061 | BI3: 0.065 | BJ3: 0.0692 | BK3: 0.0781 | BL3: 0.0803 | BM3: 0.1135 | BN3: 0.1692 | BO3: 0.1528 | BP3: 0.1568 | BQ3: 0.1291 | BR3: 0.0727 | BS3: 0.0749 | BT3: 0.0643 | BU3: 0.0539 | BV3: 0.0425 | BW3: 0.0435 | BX3: 0.0296 | BY3: 0.0251 | BZ3: 0.0235 | CA3: 0.0229 | CB3: 0.0338 | CC3: 0.0426 | CD3: 0.0525 | CE3: 0.0466 | CF3: 0.0399 | CG3: 0.0304 | CH3: 0.0254 | CI3: 0.0321 | CJ3: 0.0367 | CK3: 0.0491 | CL3: 0.057820226 | CM3: 0.065115255 | CN3: 0.074080861 | CO3: 0.083930153 | CP3: 0.16695122 | CQ3: 0.1589738 | CR3: 0.13670964 | CS3: 0.11922836 | CT3: 0.0351 | CU3: 0.0325 | CV3: 0.06 | CW3: 0.0742 | CX3: 0.0772 | CY3: 0.0859 | CZ3: 0.0863 | DA3: 0.0952 | DB3: 0.1034 | DC3: 0.094 | DD3: 0.0798 | DE3: 0.0559 | DF3: 0.0586 | DG3: 0.0602 | DH3: 0.063349529 | DI3: 0.067380961 | DJ3: 0.05401422 | DK3: 0.051249764 | DL3: 0.049133784 | DM3: 0.047439689 | DN3: 0.043389563 | DO3: 0.047072709 | DP3: 0.042124625 | DQ3: 0.040050205 | DR3: 0.040469247 | DS3: 0.040469043 | DT3: 0.039847139 | DU3: 0.039847139 | DV3: 0.03995079 | DW3: 0.03995079 | DX3: 0.03995079 | DY3: 0.03995079 | DZ3: =Inputs!AN3 -> 0.04 | EA3: =Inputs!AN3 -> 0.04 | EB3: =Inputs!AN3 -> 0.04 | EC3: =Inputs!AN3 -> 0.04 | ED3: =Inputs!AO3 -> 0.04 | EE3: =Inputs!AO3 -> 0.04 | EF3: =Inputs!AO3 -> 0.04 | EG3: =Inputs!AO3 -> 0.04 | EH3: =Inputs!AP3 -> 0.04 | EI3: =Inputs!AP3 -> 0.04 | EJ3: =Inputs!AP3 -> 0.04 | EK3: =Inputs!AP3 -> 0.04 | EL3: =Inputs!AQ3 -> 0.04 | EM3: =Inputs!AP3 -> 0.04 | EN3: =Inputs!AQ3 -> 0.04 | EO3: =Inputs!AQ3 -> 0.04 | EP3: =Inputs!AR3 -> 0.04 | EQ3: =Inputs!AR3 -> 0.04 | ER3: =Inputs!AR3 -> 0.04 | ES3: =Inputs!AR3 -> 0.04 | ET3: =Inputs!AS3 -> 0.04 | EU3: =Inputs!AS3 -> 0.04 | EV3: =Inputs!AS3 -> 0.04 | EW3: =Inputs!AS3 -> 0.04 | EX3: =Inputs!AT3 -> 0.04 | EY3: =Inputs!AT3 -> 0.04 | EZ3: =Inputs!AT3 -> 0.04 | FA3: =Inputs!AT3 -> 0.04 | FB3: =Inputs!AU3 -> 0.04 | FC3: =Inputs!AU3 -> 0.04 | FD3: =Inputs!AU3 -> 0.04 | FE3: =Inputs!AU3 -> 0.04 | FF3: =Inputs!AV3 -> 0.04 | FG3: =Inputs!AV3 -> 0.04 | FH3: =Inputs!AV3 -> 0.04 | FI3: =Inputs!AV3 -> 0.04 | FJ3: =Inputs!AW3 -> 0.04 | FK3: =Inputs!AW3 -> 0.04 | FL3: =Inputs!AW3 -> 0.04 | FM3: =Inputs!AW3 -> 0.04 | FN3: =Inputs!AX3 -> 0.04 | FO3: =Inputs!AX3 -> 0.04 | FP3: =Inputs!AX3 -> 0.04 | FQ3: =Inputs!AX3 -> 0.04 | FR3: =Inputs!AY3 -> 0.04 | FS3: =Inputs!AY3 -> 0.04 | FT3: =Inputs!AY3 -> 0.04 | FU3: =Inputs!AY3 -> 0.04 | FV3: =Inputs!AZ3 -> 0.04 | FW3: =Inputs!AZ3 -> 0.04 | FX3: =Inputs!AZ3 -> 0.04 | FY3: =Inputs!AZ3 -> 0.04 | FZ3: =Inputs!BA3 -> 0.04 | GA3: =Inputs!BA3 -> 0.04 | GB3: =Inputs!BA3 -> 0.04 | GC3: =Inputs!BA3 -> 0.04 | GD3: =Inputs!BB3 -> 0.04 | GE3: =Inputs!BB3 -> 0.04 | GF3: =Inputs!BB3 -> 0.04 | GG3: =Inputs!BB3 -> 0.04 | GH3: =Inputs!BC3 -> 0.04 | GI3: =Inputs!BC3 -> 0.04 | GJ3: =Inputs!BC3 -> 0.04 | GK3: =Inputs!BC3 -> 0.04 | GL3: =Inputs!BD3 -> 0.04 | GM3: =Inputs!BD3 -> 0.04 | GN3: =Inputs!BD3 -> 0.04 | GO3: =Inputs!BD3 -> 0.04 | GP3: =Inputs!BE3 -> 0.04 | GQ3: =Inputs!BE3 -> 0.04 | GR3: =Inputs!BE3 -> 0.04 | GS3: =Inputs!BE3 -> 0.04 | GT3: =Inputs!BF3 -> 0.04 | GU3: =Inputs!BF3 -> 0.04 | GV3: =Inputs!BF3 -> 0.04 | GW3: =Inputs!BF3 -> 0.04 | GX3: =Inputs!BG3 -> 0.04 | GY3: =Inputs!BG3 -> 0.04 | GZ3: =Inputs!BG3 -> 0.04 | HA3: =Inputs!BG3 -> 0.04
A4: Общие | D4: CIB Research | F4: Инфляция - Рост индекса потребительских цен в США, в долларах США (USD, eop CPI) | G4: % | I4: EoY PCE, source: FX/IR team | J4: 0.029 | K4: 0.032 | L4: 0.026 | M4: 0.016 | N4: 0.015 | O4: 0.011 | P4: 0.015 | Q4: 0.024 | R4: 0.03 | S4: 0.021 | T4: 0.023 | U4: 0.019 | V4: 0.017 | W4: 0.033 | X4: 0.025 | Y4: 0.033 | Z4: 0.031 | AA4: 0.025 | AB4: 0.047 | AC4: 0.034 | AD4: 0.034 | AE4: 0.043 | AF4: 0.021 | AG4: 0.025 | AH4: 0.028 | AI4: 0.027 | AJ4: 0.028 | AK4: 0.041 | AL4: 0.04 | AM4: 0.05 | AN4: 0.049 | AO4: 0.001 | AP4: -0.004 | AQ4: -0.014 | AR4: -0.013 | AS4: 0.027 | AT4: 0.023 | AU4: 0.011 | AV4: 0.011 | AW4: 0.015 | AX4: 0.027 | AY4: 0.036 | AZ4: 0.039 | BA4: 0.03 | BB4: 0.027 | BC4: 0.017 | BD4: 0.02 | BE4: 0.017 | BF4: 0.015 | BG4: 0.018 | BH4: 0.012 | BI4: 0.015 | BJ4: 0.015122029 | BK4: 0.020723414 | BL4: 0.016579187 | BM4: 0.0075649327 | BN4: -0.00022030697 | BO4: 0.0017957028 | BP4: 8.8358094e-05 | BQ4: 0.0063871458 | BR4: 0.0089160605 | BS4: 0.010792812 | BT4: 0.015486393 | BU4: 0.020507924 | BV4: 0.024411943 | BW4: 0.016405633 | BX4: 0.021805592 | BY4: 0.021299357 | BZ4: 0.023309485 | CA4: 0.028075393 | CB4: 0.023320482 | CC4: 0.020023707 | CD4: 0.018831787 | CE4: 0.016711976 | CF4: 0.016845036 | CG4: 0.023195291 | CH4: 0.015231471 | CI4: 0.0070177162 | CJ4: 0.013730818 | CK4: 0.013049536 | CL4: 0.026186356 | CM4: 0.053150957 | CN4: 0.053610217 | CO4: 0.071765966 | CP4: 0.085474376 | CQ4: 0.089897548 | CR4: 0.081982851 | CS4: 0.064115004 | CT4: 0.049350904 | CU4: 0.030532585 | CV4: 0.036940422 | CW4: 0.03323156 | CX4: 0.034751249 | CY4: 0.029756235 | CZ4: 0.024075194 | DA4: 0.028965881 | DB4: 0.024055926 | DC4: 0.026726904 | DD4: 0.030227089 | DE4: 0.026899449 | DF4: 0.035429288 | DG4: 0.037169706 | DH4: 0.028660294 | DI4: 0.027326387 | DJ4: 0.023346989 | DK4: 0.021743947 | DL4: 0.027986742 | DM4: 0.026069089 | DN4: 0.021271763 | DO4: 0.020625551 | DP4: 0.021668128 | DQ4: 0.022921913 | DR4: 0.02252651 | DS4: 0.021532968 | DT4: 0.020466105 | DU4: 0.01939121 | DV4: 0.019719505 | DW4: 0.020552486 | DX4: 0.021448954 | DY4: 0.02235396 | DZ4: =Inputs!AN4 -> 0.02 | EA4: =Inputs!AN4 -> 0.02 | EB4: =Inputs!AN4 -> 0.02 | EC4: =Inputs!AN4 -> 0.02 | ED4: =Inputs!AO4 -> 0.02 | EE4: =Inputs!AO4 -> 0.02 | EF4: =Inputs!AO4 -> 0.02 | EG4: =Inputs!AO4 -> 0.02 | EH4: =Inputs!AP4 -> 0.02 | EI4: =Inputs!AP4 -> 0.02 | EJ4: =Inputs!AP4 -> 0.02 | EK4: =Inputs!AP4 -> 0.02 | EL4: =Inputs!AQ4 -> 0.02 | EM4: =Inputs!AP4 -> 0.02 | EN4: =Inputs!AQ4 -> 0.02 | EO4: =Inputs!AQ4 -> 0.02 | EP4: =Inputs!AR4 -> 0.02 | EQ4: =Inputs!AR4 -> 0.02 | ER4: =Inputs!AR4 -> 0.02 | ES4: =Inputs!AR4 -> 0.02 | ET4: =Inputs!AS4 -> 0.02 | EU4: =Inputs!AS4 -> 0.02 | EV4: =Inputs!AS4 -> 0.02 | EW4: =Inputs!AS4 -> 0.02 | EX4: =Inputs!AT4 -> 0.02 | EY4: =Inputs!AT4 -> 0.02 | EZ4: =Inputs!AT4 -> 0.02 | FA4: =Inputs!AT4 -> 0.02 | FB4: =Inputs!AU4 -> 0.02 | FC4: =Inputs!AU4 -> 0.02 | FD4: =Inputs!AU4 -> 0.02 | FE4: =Inputs!AU4 -> 0.02 | FF4: =Inputs!AV4 -> 0.02 | FG4: =Inputs!AV4 -> 0.02 | FH4: =Inputs!AV4 -> 0.02 | FI4: =Inputs!AV4 -> 0.02 | FJ4: =Inputs!AW4 -> 0.02 | FK4: =Inputs!AW4 -> 0.02 | FL4: =Inputs!AW4 -> 0.02 | FM4: =Inputs!AW4 -> 0.02 | FN4: =Inputs!AX4 -> 0.02 | FO4: =Inputs!AX4 -> 0.02 | FP4: =Inputs!AX4 -> 0.02 | FQ4: =Inputs!AX4 -> 0.02 | FR4: =Inputs!AY4 -> 0.02 | FS4: =Inputs!AY4 -> 0.02 | FT4: =Inputs!AY4 -> 0.02 | FU4: =Inputs!AY4 -> 0.02 | FV4: =Inputs!AZ4 -> 0.02 | FW4: =Inputs!AZ4 -> 0.02 | FX4: =Inputs!AZ4 -> 0.02 | FY4: =Inputs!AZ4 -> 0.02 | FZ4: =Inputs!BA4 -> 0.02 | GA4: =Inputs!BA4 -> 0.02 | GB4: =Inputs!BA4 -> 0.02 | GC4: =Inputs!BA4 -> 0.02 | GD4: =Inputs!BB4 -> 0.02 | GE4: =Inputs!BB4 -> 0.02 | GF4: =Inputs!BB4 -> 0.02 | GG4: =Inputs!BB4 -> 0.02 | GH4: =Inputs!BC4 -> 0.02 | GI4: =Inputs!BC4 -> 0.02 | GJ4: =Inputs!BC4 -> 0.02 | GK4: =Inputs!BC4 -> 0.02 | GL4: =Inputs!BD4 -> 0.02 | GM4: =Inputs!BD4 -> 0.02 | GN4: =Inputs!BD4 -> 0.02 | GO4: =Inputs!BD4 -> 0.02 | GP4: =Inputs!BE4 -> 0.02 | GQ4: =Inputs!BE4 -> 0.02 | GR4: =Inputs!BE4 -> 0.02 | GS4: =Inputs!BE4 -> 0.02 | GT4: =Inputs!BF4 -> 0.02 | GU4: =Inputs!BF4 -> 0.02 | GV4: =Inputs!BF4 -> 0.02 | GW4: =Inputs!BF4 -> 0.02 | GX4: =Inputs!BG4 -> 0.02 | GY4: =Inputs!BG4 -> 0.02 | GZ4: =Inputs!BG4 -> 0.02 | HA4: =Inputs!BG4 -> 0.02
A5: Общие | D5: ЦМИ | F5: Инфляция - Рост индекса цен производителей (RUB, eop PPI) | G5: % | I5: С 2021 года прогноз CIB | J5: 0.237 | K5: 0.22 | L5: 0.143 | M5: 0.083 | N5: 0.047 | O5: 0.077 | P5: 0.136 | Q5: 0.177 | R5: 0.222 | S5: 0.154 | T5: 0.151 | U5: 0.125 | V5: 0.158 | W5: 0.242 | X5: 0.242 | Y5: 0.288 | Z5: 0.194 | AA5: 0.198 | AB5: 0.178 | AC5: 0.154 | AD5: 0.167 | AE5: 0.119 | AF5: 0.095 | AG5: 0.104 | AH5: 0.031 | AI5: 0.126 | AJ5: 0.086 | AK5: 0.251 | AL5: 0.274 | AM5: 0.281 | AN5: 0.257 | AO5: -0.07 | AP5: -0.028 | AQ5: -0.094 | AR5: -0.055 | AS5: 0.139 | AT5: 0.192 | AU5: 0.098 | AV5: 0.059 | AW5: 0.167 | AX5: 0.185 | AY5: 0.167 | AZ5: 0.158 | BA5: 0.113 | BB5: 0.069 | BC5: 0.043 | BD5: 0.1 | BE5: 0.052 | BF5: 0.043 | BG5: 0.035 | BH5: 0.02 | BI5: 0.035 | BJ5: 0.048 | BK5: 0.092 | BL5: 0.039 | BM5: 0.063 | BN5: 0.142 | BO5: 0.144 | BP5: 0.144 | BQ5: 0.121 | BR5: 0.021 | BS5: 0.056 | BT5: 0.044 | BU5: 0.075 | BV5: 0.113 | BW5: 0.029 | BX5: 0.068 | BY5: 0.084 | BZ5: 0.0483 | CA5: 0.1606 | CB5: 0.1439 | CC5: 0.1171 | CD5: 0.109 | CE5: 0.0413 | CF5: -0.0122 | CG5: -0.0426 | CH5: -0.032 | CI5: -0.0829 | CJ5: -0.0002 | CK5: 0.0356 | CL5: 0.1596 | CM5: 0.3104 | CN5: 0.2627 | CO5: 0.2852 | CP5: 0.27736565 | CQ5: 0.12171299 | CR5: 0.04446833 | CS5: -0.033181437 | CT5: -0.1069 | CU5: 0.0001 | CV5: 0.1671 | CW5: 0.1916 | CX5: 0.1914 | CY5: 0.14 | CZ5: 0.0557 | DA5: 0.0791 | DB5: 0.059 | DC5: 0.0005 | DD5: -0.0039 | DE5: -0.0328 | DF5: -0.018 | DG5: 0.104 | DH5: 0.080344606 | DI5: 0.12373075 | DJ5: 0.11202318 | DK5: 0.035958275 | DL5: 0.050757244 | DM5: 0.048265541 | DN5: 0.069083849 | DO5: 0.083098045 | DP5: 0.089741434 | DQ5: 0.087119187 | DR5: 0.082315983 | DS5: 0.068387271 | DT5: 0.057811213 | DU5: 0.053103144 | DV5: 0.055142161 | DW5: 0.056857642 | DX5: 0.056908205 | DY5: 0.056887074 | DZ5: =Inputs!AN5 -> 0.04 | EA5: =Inputs!AN5 -> 0.04 | EB5: =Inputs!AN5 -> 0.04 | EC5: =Inputs!AN5 -> 0.04 | ED5: =Inputs!AO5 -> 0.04 | EE5: =Inputs!AO5 -> 0.04 | EF5: =Inputs!AO5 -> 0.04 | EG5: =Inputs!AO5 -> 0.04 | EH5: =Inputs!AP5 -> 0.04 | EI5: =Inputs!AP5 -> 0.04 | EJ5: =Inputs!AP5 -> 0.04 | EK5: =Inputs!AP5 -> 0.04 | EL5: =Inputs!AQ5 -> 0.04 | EM5: =Inputs!AP5 -> 0.04 | EN5: =Inputs!AQ5 -> 0.04 | EO5: =Inputs!AQ5 -> 0.04 | EP5: =Inputs!AR5 -> 0.04 | EQ5: =Inputs!AR5 -> 0.04 | ER5: =Inputs!AR5 -> 0.04 | ES5: =Inputs!AR5 -> 0.04 | ET5: =Inputs!AS5 -> 0.04 | EU5: =Inputs!AS5 -> 0.04 | EV5: =Inputs!AS5 -> 0.04 | EW5: =Inputs!AS5 -> 0.04 | EX5: =Inputs!AT5 -> 0.04 | EY5: =Inputs!AT5 -> 0.04 | EZ5: =Inputs!AT5 -> 0.04 | FA5: =Inputs!AT5 -> 0.04 | FB5: =Inputs!AU5 -> 0.04 | FC5: =Inputs!AU5 -> 0.04 | FD5: =Inputs!AU5 -> 0.04 | FE5: =Inputs!AU5 -> 0.04 | FF5: =Inputs!AV5 -> 0.04 | FG5: =Inputs!AV5 -> 0.04 | FH5: =Inputs!AV5 -> 0.04 | FI5: =Inputs!AV5 -> 0.04 | FJ5: =Inputs!AW5 -> 0.04 | FK5: =Inputs!AW5 -> 0.04 | FL5: =Inputs!AW5 -> 0.04 | FM5: =Inputs!AW5 -> 0.04 | FN5: =Inputs!AX5 -> 0.04 | FO5: =Inputs!AX5 -> 0.04 | FP5: =Inputs!AX5 -> 0.04 | FQ5: =Inputs!AX5 -> 0.04 | FR5: =Inputs!AY5 -> 0.04 | FS5: =Inputs!AY5 -> 0.04 | FT5: =Inputs!AY5 -> 0.04 | FU5: =Inputs!AY5 -> 0.04 | FV5: =Inputs!AZ5 -> 0.04 | FW5: =Inputs!AZ5 -> 0.04 | FX5: =Inputs!AZ5 -> 0.04 | FY5: =Inputs!AZ5 -> 0.04 | FZ5: =Inputs!BA5 -> 0.04 | GA5: =Inputs!BA5 -> 0.04 | GB5: =Inputs!BA5 -> 0.04 | GC5: =Inputs!BA5 -> 0.04 | GD5: =Inputs!BB5 -> 0.04 | GE5: =Inputs!BB5 -> 0.04 | GF5: =Inputs!BB5 -> 0.04 | GG5: =Inputs!BB5 -> 0.04 | GH5: =Inputs!BC5 -> 0.04 | GI5: =Inputs!BC5 -> 0.04 | GJ5: =Inputs!BC5 -> 0.04 | GK5: =Inputs!BC5 -> 0.04 | GL5: =Inputs!BD5 -> 0.04 | GM5: =Inputs!BD5 -> 0.04 | GN5: =Inputs!BD5 -> 0.04 | GO5: =Inputs!BD5 -> 0.04 | GP5: =Inputs!BE5 -> 0.04 | GQ5: =Inputs!BE5 -> 0.04 | GR5: =Inputs!BE5 -> 0.04 | GS5: =Inputs!BE5 -> 0.04 | GT5: =Inputs!BF5 -> 0.04 | GU5: =Inputs!BF5 -> 0.04 | GV5: =Inputs!BF5 -> 0.04 | GW5: =Inputs!BF5 -> 0.04 | GX5: =Inputs!BG5 -> 0.04 | GY5: =Inputs!BG5 -> 0.04 | GZ5: =Inputs!BG5 -> 0.04 | HA5: =Inputs!BG5 -> 0.04
A6: Общие | D6: ЦМИ | F6: Инфляция - Дефлятор ВВП (RUB, GDP Deflator) | G6: % | I6: =0.8CPI+0.2PPI; С 2021 года прогноз CIB | BJ6: 0.057 | BK6: 0.077 | BL6: 0.08 | BM6: 0.084 | BN6: 0.084 | BO6: 0.074 | BP6: 0.089 | BQ6: 0.075 | BR6: 0.034 | BS6: 0.042 | BT6: 0.025 | BU6: 0.039 | BV6: 0.069 | BW6: 0.042 | BX6: 0.041 | BY6: 0.058 | BZ6: 0.064 | CA6: 0.109 | CB6: 0.117 | CC6: 0.105 | CD6: 0.08 | CE6: 0.052 | CF6: 0.014 | CG6: -0.003 | CH6: -0.0046325265 | CI6: -0.036674774 | CJ6: 0.013999643 | CK6: 0.053859177 | CL6: 0.11663621 | CM6: 0.20946845 | CN6: 0.21820742 | CO6: 0.17987697 | CP6: 0.28973736 | CQ6: 0.22212763 | CR6: 0.1454369 | CS6: 0.10577648 | CT6: 0.0207582 | CU6: 0.0965861 | CV6: 0.1424466 | CW6: 0.1510461 | CX6: 0.1275925 | CY6: 0.0807596 | CZ6: 0.0817403 | DA6: 0.0676184 | DB6: 0.0256859 | DC6: 0.0606908 | DD6: 0.0421024 | DE6: 0.041603 | DF6: 0.06193409 | DG6: 0.074143104 | DH6: 0.097730764 | DI6: 0.086055585 | DJ6: 0.053870765 | DK6: 0.038267441 | DL6: 0.018347743 | DM6: 0.012447417 | DN6: =0.8*DN3+0.2*DN5 -> 0.04852842 | DO6: =0.8*DO3+0.2*DO5 -> 0.054277776 | DP6: =0.8*DP3+0.2*DP5 -> 0.051647987 | DQ6: =0.8*DQ3+0.2*DQ5 -> 0.049464001 | DR6: =0.8*DR3+0.2*DR5 -> 0.048838594 | DS6: =0.8*DS3+0.2*DS5 -> 0.046052689 | DT6: =0.8*DT3+0.2*DT5 -> 0.043439954 | DU6: =0.8*DU3+0.2*DU5 -> 0.04249834 | ... HA6: =0.8*HA3+0.2*HA5 -> 0.04
A7: Общие | D7: Расчет | F7: Курс рубля к доллару США в конце года (eop USD/RUB) | G7: $/руб | I7: 2015-17 модель ЦМИ c ценой на нефть CIB Research, после - CIB Research, с 2019 года прогноз CIB; =предыдущий год*1.02 | J7: 28.76 | K7: 29.147 | L7: 29.467 | M7: 30.505 | N7: 31.21 | O7: 31.475 | P7: 31.69 | Q7: 31.955 | R7: 31.3863 | S7: 30.3655 | T7: 30.587 | U7: 29.2425 | V7: 28.519 | W7: 29.0698 | X7: 29.2229 | Y7: 27.72 | Z7: 27.8621 | AA7: 28.63 | AB7: 28.4977 | AC7: 28.7414 | AD7: 27.705 | AE7: 26.8455 | AF7: 26.7958 | AG7: 26.3255 | AH7: 25.986 | AI7: 25.7449 | AJ7: 24.8588 | AK7: 24.6006 | AL7: 23.4929 | AM7: 23.4446 | AN7: 25.6439 | AO7: 29.4027 | AP7: 33.954 | AQ7: 31.1527 | AR7: 30.0154 | AS7: 30.035 | AT7: 29.4205 | AU7: 31.2095 | AV7: 30.535 | AW7: 30.537 | AX7: 28.418 | AY7: 27.8693 | AZ7: 32.184 | BA7: 32.137 | BB7: 29.347 | BC7: 32.4245 | BD7: 31.18 | BE7: 30.525 | BF7: 31.0564 | BG7: 32.8395 | BH7: 32.3906 | BI7: 32.8696 | BJ7: 35.6871 | BK7: 33.6306 | BL7: 39.3866 | BM7: 56.2584 | BN7: 58.4643 | BO7: 55.524 | BP7: 66.2367 | BQ7: 72.8827 | BR7: 67.6076 | BS7: 64.2575 | BT7: 63.1581 | BU7: 60.6569 | BV7: 56.3779 | BW7: 59.0855 | BX7: 58.0169 | BY7: 57.6002 | BZ7: 57.2649 | CA7: 62.7565 | CB7: 65.5906 | CC7: 69.4706 | CD7: 64.7347 | CE7: 63.0756 | CF7: 64.4156 | CG7: 61.9057 | CH7: 77.7325 | CI7: 69.9513 | CJ7: 79.6845 | CK7: 73.8757 | CL7: 75.7023 | CM7: 72.3723 | CN7: 72.7608 | CO7: 74.2926 | CP7: 84.1 | CQ7: 51.158 | CR7: 57.413 | CS7: 70.3375 | CT7: 77.09 | CU7: 87.03 | CV7: 97.41 | CW7: 89.69 | CX7: 92.37 | CY7: 85.75 | CZ7: 92.71 | DA7: 101.68 | DB7: 83.68 | DC7: 78.47 | DD7: 82.87 | DE7: 78.23 | DF7: 81.2955 | DG7: 77.7539 | DH7: 84.253982 | DI7: 88.047138 | DJ7: 89.803836 | DK7: 91.087323 | DL7: 92.181412 | DM7: 93.201775 | DN7: 94.198616 | DO7: 95.193278 | DP7: 96.194511 | DQ7: 97.205694 | DR7: 98.228 | DS7: 99.261758 | DT7: 100.30701 | DU7: 101.36373 | DV7: 102.4319 | DW7: 103.51155 | DX7: 104.60272 | DY7: 105.70549 | DZ7: =(EC7-DY7)/4+DY7 -> 105.76889 | EA7: =(EC7-DY7)/4*2+DY7 -> 105.8323 | EB7: =(EC7-DY7)/4*3+DY7 -> 105.8957 | EC7: =Inputs!AN7 -> 105.95911 | ED7: =(EG7-EC7)/4+EC7 -> 106.4889 | EE7: =(EG7-EC7)/4*2+EC7 -> 107.0187 | EF7: =(EG7-EC7)/4*3+EC7 -> 107.54849 | EG7: =Inputs!AO7 -> 108.07829 | EH7: =(EK7-EG7)/4+EG7 -> 108.61868 | EI7: =(EK7-EG7)/4*2+EG7 -> 109.15907 | EJ7: =(EK7-EG7)/4*3+EG7 -> 109.69946 | EK7: =Inputs!AP7 -> 110.23985 | EL7: =(EO7-EK7)/4+EK7 -> 110.79105 | EM7: =(EO7-EK7)/4*2+EK7 -> 111.34225 | EN7: =(EO7-EK7)/4*3+EK7 -> 111.89345 | EO7: =Inputs!AQ7 -> 112.44465 | EP7: =(ES7-EO7)/4+EO7 -> 113.00687 | EQ7: =(ES7-EO7)/4*2+EO7 -> 113.5691 | ER7: =(ES7-EO7)/4*3+EO7 -> 114.13132 | ES7: =Inputs!AR7 -> 114.69354 | ET7: =(EW7-ES7)/4+ES7 -> 115.26701 | EU7: =(EW7-ES7)/4*2+ES7 -> 115.84048 | EV7: =(EW7-ES7)/4*3+ES7 -> 116.41395 | EW7: =Inputs!AS7 -> 116.98741 | EX7: =(FA7-EW7)/4+EW7 -> 117.57235 | EY7: =(FA7-EW7)/4*2+EW7 -> 118.15729 | EZ7: =(FA7-EW7)/4*3+EW7 -> 118.74223 | FA7: =Inputs!AT7 -> 119.32716 | FB7: =(FE7-FA7)/4+FA7 -> 119.9238 | FC7: =(FE7-FA7)/4*2+FA7 -> 120.52043 | FD7: =(FE7-FA7)/4*3+FA7 -> 121.11707 | FE7: =Inputs!AU7 -> 121.71371 | FF7: =(FI7-FE7)/4+FE7 -> 122.32227 | FG7: =(FI7-FE7)/4*2+FE7 -> 122.93084 | FH7: =(FI7-FE7)/4*3+FE7 -> 123.53941 | FI7: =Inputs!AV7 -> 124.14798 | FJ7: =(FM7-FI7)/4+FI7 -> 124.76872 | FK7: =(FM7-FI7)/4*2+FI7 -> 125.38946 | FL7: =(FM7-FI7)/4*3+FI7 -> 126.0102 | FM7: =Inputs!AW7 -> 126.63094 | FN7: =(FQ7-FM7)/4+FM7 -> 127.26409 | FO7: =(FQ7-FM7)/4*2+FM7 -> 127.89725 | FP7: =(FQ7-FM7)/4*3+FM7 -> 128.5304 | FQ7: =Inputs!AX7 -> 129.16356 | FR7: =(FU7-FQ7)/4+FQ7 -> 129.80938 | FS7: =(FU7-FQ7)/4*2+FQ7 -> 130.45519 | FT7: =(FU7-FQ7)/4*3+FQ7 -> 131.10101 | FU7: =Inputs!AY7 -> 131.74683 | FV7: =(FY7-FU7)/4+FU7 -> 132.40556 | FW7: =(FY7-FU7)/4*2+FU7 -> 133.0643 | FX7: =(FY7-FU7)/4*3+FU7 -> 133.72303 | FY7: =Inputs!AZ7 -> 134.38177 | FZ7: =(GC7-FY7)/4+FY7 -> 135.05368 | GA7: =(GC7-FY7)/4*2+FY7 -> 135.72558 | GB7: =(GC7-FY7)/4*3+FY7 -> 136.39749 | GC7: =Inputs!BA7 -> 137.0694 | GD7: =(GG7-GC7)/4+GC7 -> 137.75475 | GE7: =(GG7-GC7)/4*2+GC7 -> 138.4401 | GF7: =(GG7-GC7)/4*3+GC7 -> 139.12544 | GG7: =Inputs!BB7 -> 139.81079 | GH7: =(GK7-GG7)/4+GG7 -> 140.50984 | GI7: =(GK7-GG7)/4*2+GG7 -> 141.2089 | GJ7: =(GK7-GG7)/4*3+GG7 -> 141.90795 | GK7: =Inputs!BC7 -> 142.60701 | GL7: =(GO7-GK7)/4+GK7 -> 143.32004 | GM7: =(GO7-GK7)/4*2+GK7 -> 144.03308 | GN7: =(GO7-GK7)/4*3+GK7 -> 144.74611 | GO7: =Inputs!BD7 -> 145.45915 | GP7: =(GS7-GO7)/4+GO7 -> 146.18644 | GQ7: =(GS7-GO7)/4*2+GO7 -> 146.91374 | GR7: =(GS7-GO7)/4*3+GO7 -> 147.64103 | GS7: =Inputs!BE7 -> 148.36833 | GT7: =(GW7-GS7)/4+GS7 -> 149.11017 | GU7: =(GW7-GS7)/4*2+GS7 -> 149.85201 | GV7: =(GW7-GS7)/4*3+GS7 -> 150.59385 | GW7: =Inputs!BF7 -> 151.3357 | GX7: =(HA7-GW7)/4+GW7 -> 152.09237 | GY7: =(HA7-GW7)/4*2+GW7 -> 152.84905 | GZ7: =(HA7-GW7)/4*3+GW7 -> 153.60573 | HA7: =Inputs!BG7 -> 154.36241
A8: Общие | D8: Расчет | F8: Курс рубля к EUR в конце года (eop EUR/RUB) | G8: EUR/руб | I8: =EUR/USD*курс доллара | J8: 25.2891 | K8: 24.6932 | L8: 26.8106 | M8: 27.1421 | N8: 27.1503 | O8: 31.0662 | P8: 31.3235 | Q8: 33.5123 | R8: 34.2366 | S8: 34.9359 | T8: 35.6573 | U8: 36.8234 | V8: 35.1254 | W8: 35.4697 | X8: 36.3425 | Y8: 37.5689 | Z8: 36.1357 | AA8: 34.67 | AB8: 34.2772 | AC8: 34.0542 | AD8: 33.5703 | AE8: 34.3354 | AF8: 33.9589 | AG8: 34.7483 | AH8: 34.707 | AI8: 34.8609 | AJ8: 35.4542 | AK8: 35.9442 | AL8: 37.0882 | AM8: 36.9345 | AN8: 36.1407 | AO8: 42.6587 | AP8: 44.9904 | AQ8: 43.7165 | AR8: 43.9365 | AS8: 43.0244 | AT8: 39.7668 | AU8: 38.2568 | AV8: 41.6154 | AW8: 40.8504 | AX8: 40.2377 | AY8: 40.4245 | AZ8: 43.1635 | BA8: 41.736 | BB8: 39.2407 | BC8: 41.0478 | BD8: 40.1366 | BE8: 40.3115 | BF8: 39.8259 | BG8: 42.72 | BH8: 43.7919 | BI8: 45.5995 | BJ8: 48.3055 | BK8: 46.5445 | BL8: 50.0916 | BM8: 73.5065 | BN8: 62.4678 | BO8: 61.6005 | BP8: 73.1696 | BQ8: 79.6995 | BR8: 75.9913 | BS8: 71.124 | BT8: 70.633 | BU8: 64.6778 | BV8: 59.4954 | BW8: 67.0103 | BX8: 68.0269 | BY8: 69.1837 | BZ8: 70.1779 | CA8: 73.3411 | CB8: 76.1155 | CC8: =Inputs!AA8 -> 79.4605 | CD8: 73.7145 | CE8: 71.9157 | CF8: 70.6363 | CG8: =Inputs!AB8 -> 69.3406 | CH8: 86.7152 | CI8: 79.9539 | CJ8: 91.0048 | CK8: =Inputs!AC8 -> 90.6824 | CL8: 88.717 | CM8: 86.7363 | CN8: 84.2151 | CO8: =Inputs!AD8 -> 84.0695 | CP8: 93.696 | CQ8: 53.858 | CR8: =CR7*CR36 -> 55.41 | CS8: =Inputs!AE8 -> 75.6553 | CT8: 83.7639 | CU8: 95.1052 | CV8: 102.0979 | CW8: =Inputs!AF8 -> 99.2 | CX8: 99.5299 | CY8: 92.4184 | CZ8: 103.4694 | DA8: =Inputs!AG8 -> 106.1028 | DB8: =DB7*DB36 -> 89.653907 | DC8: =DC7*DC36 -> 92.280264 | DD8: =DD7*DD36 -> 97.143813 | DE8: 92.097683 | DF8: =DF7*DF36 -> 93.636157 | DG8: =DG7*DG36 -> 88.771628 | DH8: =DH7*DH36 -> 98.135785 | DI8: =DI7*DI36 -> 102.13468 | DJ8: =DJ7*DJ36 -> 103.83661 | DK8: =DK7*DK36 -> 105.05623 | DL8: =DL7*DL36 -> 106.12605 | DM8: =DM7*DM36 -> 107.18204 | ... FU8: =FU7*FU36 -> 151.49251 | FV8: =FV7*FY36 -> 152.24997 | FW8: =FW7*FW36 -> 153.00743 | FX8: =FX7*FX36 -> 153.7649 | FY8: =FY7*FY36 -> 154.52236 | FZ8: =FZ7*FZ36 -> 155.29497 | GA8: =GA7*GA36 -> 156.06758 | GB8: =GB7*GB36 -> 156.8402 | GC8: =GC7*GC36 -> 157.61281 | GD8: =GD7*GD36 -> 158.40087 | ... HA8: =HA7*HA36 -> 177.49762
A9: Общие | D9: ЦМИ | F9: Рост реальных расп. денежных доходов населения | G9: % | I9: С 2021 года прогноз CIB | BJ9: -0.042 | BK9: 0.008 | BL9: 0.018 | BM9: -0.035 | BN9: 0.001 | BO9: -0.0258 | BP9: -0.0558 | BQ9: -0.0088 | BR9: -0.026 | BS9: -0.052 | BT9: -0.038 | BU9: -0.056 | BV9: 0.001 | BW9: -0.007 | BX9: -0.01 | BY9: -0.002 | BZ9: 0.013 | CA9: 0.007 | CB9: 0.008 | CC9: -0.001 | CD9: -0.019 | CE9: 0.008 | CF9: 0.026 | CG9: 0.03 | CH9: 0.026 | CI9: -0.061 | CJ9: -0.039 | CK9: -0.005 | CL9: -0.032 | CM9: 0.069 | CN9: 0.0863 | CO9: 0.0057 | CP9: 0.089 | CQ9: 0.04 | CR9: -0.017 | CS9: 0.074 | CT9: 0.07795959 | CU9: 0.040619149 | CV9: 0.052100403 | CW9: 0.071741888 | CX9: 0.058345114 | CY9: 0.071337075 | CZ9: 0.087279591 | DA9: 0.10460676 | DB9: 0.071049082 | DC9: 0.10002336 | DD9: 0.07529165 | DE9: 0.057580964 | DF9: 0.017 | DG9: 0.015 | DH9: 0.0240335 | DI9: 0.020767045 | DJ9: 0.04969411 | DK9: 0.074585847 | DL9: 0.06116187 | DM9: 0.025981786 | DN9: =Inputs!AK9 -> 0.022596442 | DO9: =Inputs!AK9 -> 0.022596442 | DP9: =Inputs!AK9 -> 0.022596442 | DQ9: =Inputs!AK9 -> 0.022596442 | DR9: =Inputs!AL9 -> 0.021191425 | DS9: =Inputs!AL9 -> 0.021191425 | DT9: =Inputs!AL9 -> 0.021191425 | DU9: =Inputs!AL9 -> 0.021191425 | DV9: =Inputs!AM9 -> 0.021023688 | DW9: =Inputs!AM9 -> 0.021023688 | DX9: =Inputs!AM9 -> 0.021023688 | DY9: =Inputs!AM9 -> 0.021023688 | DZ9: =Inputs!AN9 -> 0.021023688 | EA9: =Inputs!AN9 -> 0.021023688 | EB9: =Inputs!AN9 -> 0.021023688 | EC9: =Inputs!AN9 -> 0.021023688 | ED9: =Inputs!AO9 -> 0.021023688 | EE9: =Inputs!AO9 -> 0.021023688 | EF9: =Inputs!AO9 -> 0.021023688 | EG9: =Inputs!AO9 -> 0.021023688 | EH9: =Inputs!AP9 -> 0.021023688 | EI9: =Inputs!AP9 -> 0.021023688 | EJ9: =Inputs!AP9 -> 0.021023688 | EK9: =Inputs!AP9 -> 0.021023688 | EL9: =Inputs!AQ9 -> 0.021023688 | EM9: =Inputs!AP9 -> 0.021023688 | EN9: =Inputs!AQ9 -> 0.021023688 | EO9: =Inputs!AQ9 -> 0.021023688 | EP9: =Inputs!AR9 -> 0.021023688 | EQ9: =Inputs!AR9 -> 0.021023688 | ER9: =Inputs!AR9 -> 0.021023688 | ES9: =Inputs!AR9 -> 0.021023688 | ET9: =Inputs!AS9 -> 0.021023688 | EU9: =Inputs!AS9 -> 0.021023688 | EV9: =Inputs!AS9 -> 0.021023688 | EW9: =Inputs!AS9 -> 0.021023688 | EX9: =Inputs!AT9 -> 0.021023688 | EY9: =Inputs!AT9 -> 0.021023688 | EZ9: =Inputs!AT9 -> 0.021023688 | FA9: =Inputs!AT9 -> 0.021023688 | FB9: =Inputs!AU9 -> 0.021023688 | FC9: =Inputs!AU9 -> 0.021023688 | FD9: =Inputs!AU9 -> 0.021023688 | FE9: =Inputs!AU9 -> 0.021023688 | FF9: =Inputs!AV9 -> 0.021023688 | FG9: =Inputs!AV9 -> 0.021023688 | FH9: =Inputs!AV9 -> 0.021023688 | FI9: =Inputs!AV9 -> 0.021023688 | FJ9: =Inputs!AW9 -> 0.021023688 | FK9: =Inputs!AW9 -> 0.021023688 | FL9: =Inputs!AW9 -> 0.021023688 | FM9: =Inputs!AW9 -> 0.021023688 | FN9: =Inputs!AX9 -> 0.021023688 | FO9: =Inputs!AX9 -> 0.021023688 | FP9: =Inputs!AX9 -> 0.021023688 | FQ9: =Inputs!AX9 -> 0.021023688 | FR9: =Inputs!AY9 -> 0.021023688 | FS9: =Inputs!AY9 -> 0.021023688 | FT9: =Inputs!AY9 -> 0.021023688 | FU9: =Inputs!AY9 -> 0.021023688 | FV9: =Inputs!AZ9 -> 0.021023688 | FW9: =Inputs!AZ9 -> 0.021023688 | FX9: =Inputs!AZ9 -> 0.021023688 | FY9: =Inputs!AZ9 -> 0.021023688 | FZ9: =Inputs!BA9 -> 0.021023688 | GA9: =Inputs!BA9 -> 0.021023688 | GB9: =Inputs!BA9 -> 0.021023688 | GC9: =Inputs!BA9 -> 0.021023688 | GD9: =Inputs!BB9 -> 0.021023688 | GE9: =Inputs!BB9 -> 0.021023688 | GF9: =Inputs!BB9 -> 0.021023688 | GG9: =Inputs!BB9 -> 0.021023688 | GH9: =Inputs!BC9 -> 0.021023688 | GI9: =Inputs!BC9 -> 0.021023688 | GJ9: =Inputs!BC9 -> 0.021023688 | GK9: =Inputs!BC9 -> 0.021023688 | GL9: =Inputs!BD9 -> 0.021023688 | GM9: =Inputs!BD9 -> 0.021023688 | GN9: =Inputs!BD9 -> 0.021023688 | GO9: =Inputs!BD9 -> 0.021023688 | GP9: =Inputs!BE9 -> 0.021023688 | GQ9: =Inputs!BE9 -> 0.021023688 | GR9: =Inputs!BE9 -> 0.021023688 | GS9: =Inputs!BE9 -> 0.021023688 | GT9: =Inputs!BF9 -> 0.021023688 | GU9: =Inputs!BF9 -> 0.021023688 | GV9: =Inputs!BF9 -> 0.021023688 | GW9: =Inputs!BF9 -> 0.021023688 | GX9: =Inputs!BG9 -> 0.021023688 | GY9: =Inputs!BG9 -> 0.021023688 | GZ9: =Inputs!BG9 -> 0.021023688 | HA9: =Inputs!BG9 -> 0.021023688
A10: Общие | D10: ЦМИ | F10: Ставка Libor 3m | G10: % | I10: ЦМИ, 2022 и далее = 2021 | J10: 0.0487875 | K10: 0.0383625 | L10: 0.0259 | M10: 0.0188125 | N10: 0.0203 | O10: 0.0186 | P10: 0.0179 | Q10: 0.0138 | R10: 0.0127875 | S10: 0.0111625 | T10: 0.0116 | U10: 0.0115188 | V10: 0.0111 | W10: 0.0161 | X10: 0.0202 | Y10: 0.0256438 | Z10: 0.0312 | AA10: 0.0351625 | AB10: 0.04065 | AC10: 0.0453625 | AD10: 0.05 | AE10: 0.0548063 | AF10: 0.0537 | AG10: 0.0536 | AH10: 0.0535 | AI10: 0.0536 | AJ10: 0.0522875 | AK10: 0.047025 | AL10: 0.0268813 | AM10: 0.0278313 | AN10: 0.040525 | AO10: 0.01425 | AP10: 0.0119188 | AQ10: 0.00595 | AR10: 0.0028688 | AS10: 0.0025063 | AT10: 0.002915 | AU10: 0.0053394 | AV10: 0.0029 | AW10: 0.0030281 | AX10: 0.00303 | AY10: 0.0024575 | AZ10: 0.0037433 | BA10: 0.00581 | BB10: 0.0046815 | BC10: 0.004606 | BD10: 0.003585 | BE10: 0.00306 | BF10: 0.002826 | BG10: 0.002731 | BH10: 0.0024885 | BI10: 0.002461 | BJ10: 0.002306 | BK10: 0.002307 | BL10: 0.002351 | BM10: 0.002556 | BN10: 0.0027075 | BO10: 0.002832 | BP10: 0.00325 | BQ10: 0.006127 | BR10: 0.006286 | BS10: 0.006541 | BT10: 0.0085367 | BU10: 0.0099789 | BV10: 0.0114956 | BW10: 0.0129917 | BX10: 0.0133389 | BY10: 0.0169428 | BZ10: 0.0231175 | CA10: 0.0233575 | CB10: 0.0239838 | CC10: 0.0280763 | CD10: 0.0259975 | CE10: 0.0231988 | CF10: 0.0209863 | CG10: 0.0190838 | CH10: 0.014505 | CI10: 0.00302 | CJ10: 0.0022513 | CK10: 0.002375 | CL10: 0.0020163 | CM10: 0.0014488 | CN10: 0.0013088 | CO10: 0.0021438 | CP10: 0.0096157 | CQ10: 0.0228514 | CR10: 0.0375471 | CS10: 0.0476729 | CT10: 0.0519271 | CU10: 0.0554543 | CV10: 0.0565711 | CW10: 0.0559301 | CX10: 0.0555984 | CY10: 0.0558621 | CZ10: 0.0495 | DA10: 0.0395 | DB10: =Inputs!AH10 -> 0.0295 | DC10: =Inputs!AH10 -> 0.0295 | DD10: =Inputs!AH10 -> 0.0295 | DE10: =Inputs!AH10 -> 0.0295 | DF10: =Inputs!AI10 -> 0.0255 | DG10: =Inputs!AI10 -> 0.0255 | DH10: =Inputs!AI10 -> 0.0255 | DI10: =Inputs!AI10 -> 0.0255 | DJ10: =Inputs!AJ10 -> 0.0255 | DK10: =Inputs!AJ10 -> 0.0255 | DL10: =Inputs!AJ10 -> 0.0255 | DM10: =Inputs!AJ10 -> 0.0255 | DN10: =Inputs!AK10 -> 0.0255 | DO10: =Inputs!AK10 -> 0.0255 | DP10: =Inputs!AK10 -> 0.0255 | DQ10: =Inputs!AK10 -> 0.0255 | DR10: =Inputs!AL10 -> 0.0255 | DS10: =Inputs!AL10 -> 0.0255 | DT10: =Inputs!AL10 -> 0.0255 | DU10: =Inputs!AL10 -> 0.0255 | DV10: =Inputs!AM10 -> 0.0255 | DW10: =Inputs!AM10 -> 0.0255 | DX10: =Inputs!AM10 -> 0.0255 | DY10: =Inputs!AM10 -> 0.0255 | DZ10: =Inputs!AN10 -> 0.0255 | EA10: =Inputs!AN10 -> 0.0255 | EB10: =Inputs!AN10 -> 0.0255 | EC10: =Inputs!AN10 -> 0.0255 | ED10: =Inputs!AO10 -> 0.0255 | EE10: =Inputs!AO10 -> 0.0255 | EF10: =Inputs!AO10 -> 0.0255 | EG10: =Inputs!AO10 -> 0.0255 | EH10: =Inputs!AP10 -> 0.0255 | EI10: =Inputs!AP10 -> 0.0255 | EJ10: =Inputs!AP10 -> 0.0255 | EK10: =Inputs!AP10 -> 0.0255 | EL10: =Inputs!AQ10 -> 0.0255 | EM10: =Inputs!AP10 -> 0.0255 | EN10: =Inputs!AQ10 -> 0.0255 | EO10: =Inputs!AQ10 -> 0.0255 | EP10: =Inputs!AR10 -> 0.0255 | EQ10: =Inputs!AR10 -> 0.0255 | ER10: =Inputs!AR10 -> 0.0255 | ES10: =Inputs!AR10 -> 0.0255 | ET10: =Inputs!AS10 -> 0.0255 | EU10: =Inputs!AS10 -> 0.0255 | EV10: =Inputs!AS10 -> 0.0255 | EW10: =Inputs!AS10 -> 0.0255 | EX10: =Inputs!AT10 -> 0.0255 | EY10: =Inputs!AT10 -> 0.0255 | EZ10: =Inputs!AT10 -> 0.0255 | FA10: =Inputs!AT10 -> 0.0255 | FB10: =Inputs!AU10 -> 0.0255 | FC10: =Inputs!AU10 -> 0.0255 | FD10: =Inputs!AU10 -> 0.0255 | FE10: =Inputs!AU10 -> 0.0255 | FF10: =Inputs!AV10 -> 0.0255 | FG10: =Inputs!AV10 -> 0.0255 | FH10: =Inputs!AV10 -> 0.0255 | FI10: =Inputs!AV10 -> 0.0255 | FJ10: =Inputs!AW10 -> 0.0255 | FK10: =Inputs!AW10 -> 0.0255 | FL10: =Inputs!AW10 -> 0.0255 | FM10: =Inputs!AW10 -> 0.0255 | FN10: =Inputs!AX10 -> 0.0255 | FO10: =Inputs!AX10 -> 0.0255 | FP10: =Inputs!AX10 -> 0.0255 | FQ10: =Inputs!AX10 -> 0.0255 | FR10: =Inputs!AY10 -> 0.0255 | FS10: =Inputs!AY10 -> 0.0255 | FT10: =Inputs!AY10 -> 0.0255 | FU10: =Inputs!AY10 -> 0.0255 | FV10: =Inputs!AZ10 -> 0.0255 | FW10: =Inputs!AZ10 -> 0.0255 | FX10: =Inputs!AZ10 -> 0.0255 | FY10: =Inputs!AZ10 -> 0.0255 | FZ10: =Inputs!BA10 -> 0.0255 | GA10: =Inputs!BA10 -> 0.0255 | GB10: =Inputs!BA10 -> 0.0255 | GC10: =Inputs!BA10 -> 0.0255 | GD10: =Inputs!BB10 -> 0.0255 | GE10: =Inputs!BB10 -> 0.0255 | GF10: =Inputs!BB10 -> 0.0255 | GG10: =Inputs!BB10 -> 0.0255 | GH10: =Inputs!BC10 -> 0.0255 | GI10: =Inputs!BC10 -> 0.0255 | GJ10: =Inputs!BC10 -> 0.0255 | GK10: =Inputs!BC10 -> 0.0255 | GL10: =Inputs!BD10 -> 0.0255 | GM10: =Inputs!BD10 -> 0.0255 | GN10: =Inputs!BD10 -> 0.0255 | GO10: =Inputs!BD10 -> 0.0255 | GP10: =Inputs!BE10 -> 0.0255 | GQ10: =Inputs!BE10 -> 0.0255 | GR10: =Inputs!BE10 -> 0.0255 | GS10: =Inputs!BE10 -> 0.0255 | GT10: =Inputs!BF10 -> 0.0255 | GU10: =Inputs!BF10 -> 0.0255 | GV10: =Inputs!BF10 -> 0.0255 | GW10: =Inputs!BF10 -> 0.0255 | GX10: =Inputs!BG10 -> 0.0255 | GY10: =Inputs!BG10 -> 0.0255 | GZ10: =Inputs!BG10 -> 0.0255 | HA10: =Inputs!BG10 -> 0.0255
A11: Общие | D11: ЦМИ | F11: Ставка Mosprime 3m | G11: % | I11: EoY | AA11: 0.0547 | AB11: 0.0419 | AC11: 0.0622 | AD11: 0.0553 | AE11: 0.0503 | AF11: 0.0447 | AG11: 0.058 | AH11: 0.0563 | AI11: 0.0476 | AJ11: 0.0735 | AK11: 0.0671 | AL11: 0.0748 | AM11: 0.0597 | AN11: 0.0911 | AO11: 0.218 | AP11: 0.165 | AQ11: 0.1182 | AR11: 0.1054 | AS11: 0.0705 | AT11: 0.0447 | AU11: 0.0394 | AV11: 0.0375 | AW11: 0.0406 | AX11: 0.0396 | AY11: 0.0425 | AZ11: 0.0654 | BA11: 0.0722 | BB11: 0.0673 | BC11: 0.0722 | BD11: 0.0717 | BE11: 0.0747 | BF11: 0.0711 | BG11: 0.0705 | BH11: 0.0682 | BI11: 0.0715 | BJ11: 0.0918 | BK11: 0.0945 | BL11: 0.1053 | BM11: 0.2377 | BN11: 0.157 | BO11: 0.1254 | BP11: 0.1195 | BQ11: 0.1179 | BR11: 0.118 | BS11: 0.1099 | BT11: 0.1057 | BU11: 0.1049 | BV11: 0.1021 | BW11: 0.0923 | BX11: 0.0869 | BY11: 0.0788 | BZ11: 0.0728 | CA11: 0.0747 | CB11: 0.0812 | CC11: 0.0858 | CD11: 0.0831 | CE11: 0.0803 | CF11: 0.0721 | CG11: 0.0645 | CH11: 0.0668 | CI11: 0.0486 | CJ11: 0.0464 | CK11: 0.0492 | CL11: 0.0533 | CM11: 0.0642 | CN11: 0.0755 | CO11: 0.095 | CP11: 0.2296 | CQ11: 0.096 | CR11: 0.0817 | CS11: 0.0841 | CT11: 0.0833 | CU11: 0.0835 | CV11: 0.096 | CW11: 0.0955 | CX11: 0.0545 | CY11: =Inputs!AG11 -> 0.083 | CZ11: =Inputs!AG11 -> 0.083 | DA11: =Inputs!AG11 -> 0.083 | DB11: =Inputs!AH11 -> 0.07 | DC11: =Inputs!AH11 -> 0.07 | DD11: =Inputs!AH11 -> 0.07 | DE11: =Inputs!AH11 -> 0.07 | DF11: =Inputs!AI11 -> 0.0655 | DG11: =Inputs!AI11 -> 0.0655 | DH11: =Inputs!AI11 -> 0.0655 | DI11: =Inputs!AI11 -> 0.0655 | DJ11: =Inputs!AJ11 -> 0.048 | DK11: =Inputs!AJ11 -> 0.048 | DL11: =Inputs!AJ11 -> 0.048 | DM11: =Inputs!AJ11 -> 0.048 | DN11: =Inputs!AK11 -> 0.023 | DO11: =Inputs!AK11 -> 0.023 | DP11: =Inputs!AK11 -> 0.023 | DQ11: =Inputs!AK11 -> 0.023 | DR11: =Inputs!AL11 -> 0.018 | DS11: =Inputs!AL11 -> 0.018 | DT11: =Inputs!AL11 -> 0.018 | DU11: =Inputs!AL11 -> 0.018 | DV11: =Inputs!AM11 -> 0.018 | DW11: =Inputs!AM11 -> 0.018 | DX11: =Inputs!AM11 -> 0.018 | DY11: =Inputs!AM11 -> 0.018 | DZ11: =Inputs!AN11 -> 0.018 | EA11: =Inputs!AN11 -> 0.018 | EB11: =Inputs!AN11 -> 0.018 | EC11: =Inputs!AN11 -> 0.018 | ED11: =Inputs!AO11 -> 0.018 | EE11: =Inputs!AO11 -> 0.018 | EF11: =Inputs!AO11 -> 0.018 | EG11: =Inputs!AO11 -> 0.018 | EH11: =Inputs!AP11 -> 0.018 | EI11: =Inputs!AP11 -> 0.018 | EJ11: =Inputs!AP11 -> 0.018 | EK11: =Inputs!AP11 -> 0.018 | EL11: =Inputs!AQ11 -> 0.018 | EM11: =Inputs!AP11 -> 0.018 | EN11: =Inputs!AQ11 -> 0.018 | EO11: =Inputs!AQ11 -> 0.018 | EP11: =Inputs!AR11 -> 0.018 | EQ11: =Inputs!AR11 -> 0.018 | ER11: =Inputs!AR11 -> 0.018 | ES11: =Inputs!AR11 -> 0.018 | ET11: =Inputs!AS11 -> 0.018 | EU11: =Inputs!AS11 -> 0.018 | EV11: =Inputs!AS11 -> 0.018 | EW11: =Inputs!AS11 -> 0.018 | EX11: =Inputs!AT11 -> 0.018 | EY11: =Inputs!AT11 -> 0.018 | EZ11: =Inputs!AT11 -> 0.018 | FA11: =Inputs!AT11 -> 0.018 | FB11: =Inputs!AU11 -> 0.018 | FC11: =Inputs!AU11 -> 0.018 | FD11: =Inputs!AU11 -> 0.018 | FE11: =Inputs!AU11 -> 0.018 | FF11: =Inputs!AV11 -> 0.018 | FG11: =Inputs!AV11 -> 0.018 | FH11: =Inputs!AV11 -> 0.018 | FI11: =Inputs!AV11 -> 0.018 | FJ11: =Inputs!AW11 -> 0.018 | FK11: =Inputs!AW11 -> 0.018 | FL11: =Inputs!AW11 -> 0.018 | FM11: =Inputs!AW11 -> 0.018 | FN11: =Inputs!AX11 -> 0.018 | FO11: =Inputs!AX11 -> 0.018 | FP11: =Inputs!AX11 -> 0.018 | FQ11: =Inputs!AX11 -> 0.018 | FR11: =Inputs!AY11 -> 0.018 | FS11: =Inputs!AY11 -> 0.018 | FT11: =Inputs!AY11 -> 0.018 | FU11: =Inputs!AY11 -> 0.018 | FV11: =Inputs!AZ11 -> 0.018 | FW11: =Inputs!AZ11 -> 0.018 | FX11: =Inputs!AZ11 -> 0.018 | FY11: =Inputs!AZ11 -> 0.018 | FZ11: =Inputs!BA11 -> 0.018 | GA11: =Inputs!BA11 -> 0.018 | GB11: =Inputs!BA11 -> 0.018 | GC11: =Inputs!BA11 -> 0.018 | GD11: =Inputs!BB11 -> 0.018 | GE11: =Inputs!BB11 -> 0.018 | GF11: =Inputs!BB11 -> 0.018 | GG11: =Inputs!BB11 -> 0.018 | GH11: =Inputs!BC11 -> 0.018 | GI11: =Inputs!BC11 -> 0.018 | GJ11: =Inputs!BC11 -> 0.018 | GK11: =Inputs!BC11 -> 0.018 | GL11: =Inputs!BD11 -> 0.018 | GM11: =Inputs!BD11 -> 0.018 | GN11: =Inputs!BD11 -> 0.018 | GO11: =Inputs!BD11 -> 0.018 | GP11: =Inputs!BE11 -> 0.018 | GQ11: =Inputs!BE11 -> 0.018 | GR11: =Inputs!BE11 -> 0.018 | GS11: =Inputs!BE11 -> 0.018 | GT11: =Inputs!BF11 -> 0.018 | GU11: =Inputs!BF11 -> 0.018 | GV11: =Inputs!BF11 -> 0.018 | GW11: =Inputs!BF11 -> 0.018 | GX11: =Inputs!BG11 -> 0.018 | GY11: =Inputs!BG11 -> 0.018 | GZ11: =Inputs!BG11 -> 0.018 | HA11: =Inputs!BG11 -> 0.018
A12: Общие | D12: Законодательство | F12: Ставка НДС | G12: % | I12: С 2019 года прогноз CIB | BJ12: 0.18 | BK12: 0.18 | BL12: 0.18 | BM12: 0.18 | BN12: 0.18 | BO12: 0.18 | BP12: 0.18 | BQ12: 0.18 | BR12: 0.18 | BS12: 0.18 | BT12: 0.18 | BU12: 0.18 | BV12: 0.18 | BW12: 0.18 | BX12: 0.18 | BY12: 0.18 | BZ12: 0.18 | CA12: 0.18 | CB12: 0.18 | CC12: 0.18 | CD12: 0.2 | CE12: 0.18 | CF12: 0.18 | CG12: 0.18 | CH12: 0.2 | CI12: 0.2 | CJ12: 0.2 | CK12: 0.2 | CL12: =Inputs!AD12 -> 0.2 | CM12: =Inputs!AD12 -> 0.2 | CN12: =Inputs!AD12 -> 0.2 | CO12: =Inputs!AD12 -> 0.2 | CP12: =Inputs!AE12 -> 0.2 | CQ12: =Inputs!AE12 -> 0.2 | CR12: =Inputs!AE12 -> 0.2 | CS12: =Inputs!AE12 -> 0.2 | CT12: =Inputs!AF12 -> 0.2 | CU12: =Inputs!AF12 -> 0.2 | CV12: =Inputs!AF12 -> 0.2 | CW12: =Inputs!AF12 -> 0.2 | CX12: =Inputs!AG12 -> 0.2 | CY12: =Inputs!AG12 -> 0.2 | CZ12: =Inputs!AG12 -> 0.2 | DA12: =Inputs!AG12 -> 0.2 | DB12: =Inputs!AH12 -> 0.2 | DC12: =Inputs!AH12 -> 0.2 | DD12: =Inputs!AH12 -> 0.2 | DE12: =Inputs!AH12 -> 0.2 | DF12: =Inputs!AI12 -> 0.22 | DG12: =Inputs!AI12 -> 0.22 | DH12: =Inputs!AI12 -> 0.22 | DI12: =Inputs!AI12 -> 0.22 | DJ12: =Inputs!AJ12 -> 0.22 | DK12: =Inputs!AJ12 -> 0.22 | DL12: =Inputs!AJ12 -> 0.22 | DM12: =Inputs!AJ12 -> 0.22 | DN12: =Inputs!AK12 -> 0.22 | DO12: =Inputs!AK12 -> 0.22 | DP12: =Inputs!AK12 -> 0.22 | DQ12: =Inputs!AK12 -> 0.22 | DR12: =Inputs!AL12 -> 0.22 | DS12: =Inputs!AL12 -> 0.22 | DT12: =Inputs!AL12 -> 0.22 | DU12: =Inputs!AL12 -> 0.22 | DV12: =Inputs!AM12 -> 0.22 | DW12: =Inputs!AM12 -> 0.22 | DX12: =Inputs!AM12 -> 0.22 | DY12: =Inputs!AM12 -> 0.22 | DZ12: =Inputs!AN12 -> 0.22 | EA12: =Inputs!AN12 -> 0.22 | EB12: =Inputs!AN12 -> 0.22 | EC12: =Inputs!AN12 -> 0.22 | ED12: =Inputs!AO12 -> 0.22 | EE12: =Inputs!AO12 -> 0.22 | EF12: =Inputs!AO12 -> 0.22 | EG12: =Inputs!AO12 -> 0.22 | EH12: =Inputs!AP12 -> 0.22 | EI12: =Inputs!AP12 -> 0.22 | EJ12: =Inputs!AP12 -> 0.22 | EK12: =Inputs!AP12 -> 0.22 | EL12: =Inputs!AQ12 -> 0.22 | EM12: =Inputs!AP12 -> 0.22 | EN12: =Inputs!AQ12 -> 0.22 | EO12: =Inputs!AQ12 -> 0.22 | EP12: =Inputs!AR12 -> 0.22 | EQ12: =Inputs!AR12 -> 0.22 | ER12: =Inputs!AR12 -> 0.22 | ES12: =Inputs!AR12 -> 0.22 | ET12: =Inputs!AS12 -> 0.22 | EU12: =Inputs!AS12 -> 0.22 | EV12: =Inputs!AS12 -> 0.22 | EW12: =Inputs!AS12 -> 0.22 | EX12: =Inputs!AT12 -> 0.22 | EY12: =Inputs!AT12 -> 0.22 | EZ12: =Inputs!AT12 -> 0.22 | FA12: =Inputs!AT12 -> 0.22 | FB12: =Inputs!AU12 -> 0.22 | FC12: =Inputs!AU12 -> 0.22 | FD12: =Inputs!AU12 -> 0.22 | FE12: =Inputs!AU12 -> 0.22 | FF12: =Inputs!AV12 -> 0.22 | FG12: =Inputs!AV12 -> 0.22 | FH12: =Inputs!AV12 -> 0.22 | FI12: =Inputs!AV12 -> 0.22 | FJ12: =Inputs!AW12 -> 0.22 | FK12: =Inputs!AW12 -> 0.22 | FL12: =Inputs!AW12 -> 0.22 | FM12: =Inputs!AW12 -> 0.22 | FN12: =Inputs!AX12 -> 0.22 | FO12: =Inputs!AX12 -> 0.22 | FP12: =Inputs!AX12 -> 0.22 | FQ12: =Inputs!AX12 -> 0.22 | FR12: =Inputs!AY12 -> 0.22 | FS12: =Inputs!AY12 -> 0.22 | FT12: =Inputs!AY12 -> 0.22 | FU12: =Inputs!AY12 -> 0.22 | FV12: =Inputs!AZ12 -> 0.22 | FW12: =Inputs!AZ12 -> 0.22 | FX12: =Inputs!AZ12 -> 0.22 | FY12: =Inputs!AZ12 -> 0.22 | FZ12: =Inputs!BA12 -> 0.22 | GA12: =Inputs!BA12 -> 0.22 | GB12: =Inputs!BA12 -> 0.22 | GC12: =Inputs!BA12 -> 0.22 | GD12: =Inputs!BB12 -> 0.22 | GE12: =Inputs!BB12 -> 0.22 | GF12: =Inputs!BB12 -> 0.22 | GG12: =Inputs!BB12 -> 0.22 | GH12: =Inputs!BC12 -> 0.22 | GI12: =Inputs!BC12 -> 0.22 | GJ12: =Inputs!BC12 -> 0.22 | GK12: =Inputs!BC12 -> 0.22 | GL12: =Inputs!BD12 -> 0.22 | GM12: =Inputs!BD12 -> 0.22 | GN12: =Inputs!BD12 -> 0.22 | GO12: =Inputs!BD12 -> 0.22 | GP12: =Inputs!BE12 -> 0.22 | GQ12: =Inputs!BE12 -> 0.22 | GR12: =Inputs!BE12 -> 0.22 | GS12: =Inputs!BE12 -> 0.22 | GT12: =Inputs!BF12 -> 0.22 | GU12: =Inputs!BF12 -> 0.22 | GV12: =Inputs!BF12 -> 0.22 | GW12: =Inputs!BF12 -> 0.22 | GX12: =Inputs!BG12 -> 0.22 | GY12: =Inputs!BG12 -> 0.22 | GZ12: =Inputs!BG12 -> 0.22 | HA12: =Inputs!BG12 -> 0.22
A13: Общие | D13: Законодательство | F13: Ставка НДФЛ | G13: % | I13: Базовая ставка при доходе до 200 тыс. руб./мес, далее прогрессивная шкала | BJ13: 0.13 | BK13: 0.13 | BL13: 0.13 | BM13: 0.13 | BN13: 0.13 | BO13: 0.13 | BP13: 0.13 | BQ13: 0.13 | BR13: 0.13 | BS13: 0.13 | BT13: 0.13 | BU13: 0.13 | BV13: 0.13 | BW13: 0.13 | BX13: 0.13 | BY13: 0.13 | BZ13: 0.13 | CA13: 0.13 | CB13: 0.13 | CC13: 0.13 | CD13: 0.13 | CE13: 0.13 | CF13: 0.13 | CG13: 0.13 | CH13: 0.13 | CI13: 0.13 | CJ13: 0.13 | CK13: 0.13 | CL13: =Inputs!AD13 -> 0.13 | CM13: =Inputs!AD13 -> 0.13 | CN13: =Inputs!AD13 -> 0.13 | CO13: =Inputs!AD13 -> 0.13 | CP13: =Inputs!AE13 -> 0.13 | CQ13: =Inputs!AE13 -> 0.13 | CR13: =Inputs!AE13 -> 0.13 | CS13: =Inputs!AE13 -> 0.13 | CT13: =Inputs!AF13 -> 0.13 | CU13: =Inputs!AF13 -> 0.13 | CV13: =Inputs!AF13 -> 0.13 | CW13: =Inputs!AF13 -> 0.13 | CX13: =Inputs!AG13 -> 0.13 | CY13: =Inputs!AG13 -> 0.13 | CZ13: =Inputs!AG13 -> 0.13 | DA13: =Inputs!AG13 -> 0.13 | DB13: =Inputs!AH13 -> 0.13 | DC13: =Inputs!AH13 -> 0.13 | DD13: =Inputs!AH13 -> 0.13 | DE13: =Inputs!AH13 -> 0.13 | DF13: =Inputs!AI13 -> 0.13 | DG13: =Inputs!AI13 -> 0.13 | DH13: =Inputs!AI13 -> 0.13 | DI13: =Inputs!AI13 -> 0.13 | DJ13: =Inputs!AJ13 -> 0.13 | DK13: =Inputs!AJ13 -> 0.13 | DL13: =Inputs!AJ13 -> 0.13 | DM13: =Inputs!AJ13 -> 0.13 | DN13: =Inputs!AK13 -> 0.13 | DO13: =Inputs!AK13 -> 0.13 | DP13: =Inputs!AK13 -> 0.13 | DQ13: =Inputs!AK13 -> 0.13 | DR13: =Inputs!AL13 -> 0.13 | DS13: =Inputs!AL13 -> 0.13 | DT13: =Inputs!AL13 -> 0.13 | DU13: =Inputs!AL13 -> 0.13 | DV13: =Inputs!AM13 -> 0.13 | DW13: =Inputs!AM13 -> 0.13 | DX13: =Inputs!AM13 -> 0.13 | DY13: =Inputs!AM13 -> 0.13 | DZ13: =Inputs!AN13 -> 0.13 | EA13: =Inputs!AN13 -> 0.13 | EB13: =Inputs!AN13 -> 0.13 | EC13: =Inputs!AN13 -> 0.13 | ED13: =Inputs!AO13 -> 0.13 | EE13: =Inputs!AO13 -> 0.13 | EF13: =Inputs!AO13 -> 0.13 | EG13: =Inputs!AO13 -> 0.13 | EH13: =Inputs!AP13 -> 0.13 | EI13: =Inputs!AP13 -> 0.13 | EJ13: =Inputs!AP13 -> 0.13 | EK13: =Inputs!AP13 -> 0.13 | EL13: =Inputs!AQ13 -> 0.13 | EM13: =Inputs!AP13 -> 0.13 | EN13: =Inputs!AQ13 -> 0.13 | EO13: =Inputs!AQ13 -> 0.13 | EP13: =Inputs!AR13 -> 0.13 | EQ13: =Inputs!AR13 -> 0.13 | ER13: =Inputs!AR13 -> 0.13 | ES13: =Inputs!AR13 -> 0.13 | ET13: =Inputs!AS13 -> 0.13 | EU13: =Inputs!AS13 -> 0.13 | EV13: =Inputs!AS13 -> 0.13 | EW13: =Inputs!AS13 -> 0.13 | EX13: =Inputs!AT13 -> 0.13 | EY13: =Inputs!AT13 -> 0.13 | EZ13: =Inputs!AT13 -> 0.13 | FA13: =Inputs!AT13 -> 0.13 | FB13: =Inputs!AU13 -> 0.13 | FC13: =Inputs!AU13 -> 0.13 | FD13: =Inputs!AU13 -> 0.13 | FE13: =Inputs!AU13 -> 0.13 | FF13: =Inputs!AV13 -> 0.13 | FG13: =Inputs!AV13 -> 0.13 | FH13: =Inputs!AV13 -> 0.13 | FI13: =Inputs!AV13 -> 0.13 | FJ13: =Inputs!AW13 -> 0.13 | FK13: =Inputs!AW13 -> 0.13 | FL13: =Inputs!AW13 -> 0.13 | FM13: =Inputs!AW13 -> 0.13 | FN13: =Inputs!AX13 -> 0.13 | FO13: =Inputs!AX13 -> 0.13 | FP13: =Inputs!AX13 -> 0.13 | FQ13: =Inputs!AX13 -> 0.13 | FR13: =Inputs!AY13 -> 0.13 | FS13: =Inputs!AY13 -> 0.13 | FT13: =Inputs!AY13 -> 0.13 | FU13: =Inputs!AY13 -> 0.13 | FV13: =Inputs!AZ13 -> 0.13 | FW13: =Inputs!AZ13 -> 0.13 | FX13: =Inputs!AZ13 -> 0.13 | FY13: =Inputs!AZ13 -> 0.13 | FZ13: =Inputs!BA13 -> 0.13 | GA13: =Inputs!BA13 -> 0.13 | GB13: =Inputs!BA13 -> 0.13 | GC13: =Inputs!BA13 -> 0.13 | GD13: =Inputs!BB13 -> 0.13 | GE13: =Inputs!BB13 -> 0.13 | GF13: =Inputs!BB13 -> 0.13 | GG13: =Inputs!BB13 -> 0.13 | GH13: =Inputs!BC13 -> 0.13 | GI13: =Inputs!BC13 -> 0.13 | GJ13: =Inputs!BC13 -> 0.13 | GK13: =Inputs!BC13 -> 0.13 | GL13: =Inputs!BD13 -> 0.13 | GM13: =Inputs!BD13 -> 0.13 | GN13: =Inputs!BD13 -> 0.13 | GO13: =Inputs!BD13 -> 0.13 | GP13: =Inputs!BE13 -> 0.13 | GQ13: =Inputs!BE13 -> 0.13 | GR13: =Inputs!BE13 -> 0.13 | GS13: =Inputs!BE13 -> 0.13 | GT13: =Inputs!BF13 -> 0.13 | GU13: =Inputs!BF13 -> 0.13 | GV13: =Inputs!BF13 -> 0.13 | GW13: =Inputs!BF13 -> 0.13 | GX13: =Inputs!BG13 -> 0.13 | GY13: =Inputs!BG13 -> 0.13 | GZ13: =Inputs!BG13 -> 0.13 | HA13: =Inputs!BG13 -> 0.13
A14: Общие | D14: ЦМИ | F14: Средний за период курс рубля к доллару США (av USD/RUB) | G14: $/руб | I14: С 2021 года прогноз CIB | J14: 28.5606 | K14: 29.0192 | L14: 29.3484 | M14: 29.8563 | N14: 30.8415 | O14: 31.291 | P14: 31.584 | Q14: 31.8019 | R14: 31.6596 | S14: 30.8727 | T14: 30.4357 | U14: 29.7747 | V14: 28.6281 | W14: 28.9124 | X14: 29.1742 | Y14: 28.4893 | Z14: 27.8442 | AA14: 28.096 | AB14: 28.5182 | AC14: 28.7071 | AD14: 28.1317 | AE14: 27.1755 | AF14: 26.8037 | AG14: 26.5866 | AH14: 26.2996 | AI14: 25.855 | AJ14: 25.4961 | AK14: 24.6478 | AL14: 24.2419 | AM14: 23.6198 | AN14: 24.2912 | AO14: 27.3346 | AP14: 34.0567 | AQ14: 32.181 | AR14: 31.3032 | AS14: 29.505 | AT14: 29.8346 | AU14: 30.3182 | AV14: 30.5957 | AW14: 30.7119 | AX14: 29.2325 | AY14: 27.9891 | AZ14: 29.1693 | BA14: 31.2199 | BB14: 30.1556 | BC14: 31.0719 | BD14: 31.949 | BE14: 31.0752 | BF14: 30.424 | BG14: 31.6454 | BH14: 32.7889 | BI14: 32.5502 | BJ14: 34.963333 | BK14: 35 | BL14: 36.206667 | BM14: 47.343333 | BN14: 62.186667 | BO14: 52.65 | BP14: 62.996667 | BQ14: 65.92 | BR14: 74.646667 | BS14: 65.883333 | BT14: 64.616667 | BU14: 63.073333 | BV14: 58.816667 | BW14: 57.14 | BX14: 59.003333 | BY14: 58.413333 | BZ14: 56.873333 | CA14: 61.783333 | CB14: 65.54 | CC14: 66.476667 | CD14: 66.1116 | CE14: 64.552267 | CF14: 64.568533 | CG14: 63.718167 | CH14: 66.2688 | CI14: 72.349867 | CJ14: 73.576933 | CK14: 76.224033 | CL14: 74.3378 | CM14: 74.214233 | CN14: 73.4671 | CO14: 72.598267 | CP14: 85.6294 | CQ14: 66.543333 | CR14: 59.4082 | CS14: 62.359967 | CT14: 72.77 | CU14: 80.99 | CV14: 94.11 | CW14: 92.82 | CX14: 90.76 | CY14: 90.602 | CZ14: 89.223333 | DA14: 99.623333 | DB14: 93.253333 | DC14: 80.826667 | DD14: 80.616667 | DE14: 79.92 | DF14: 78.264133 | DG14: 74.475 | DH14: 82.102188 | DI14: 87.6178 | DJ14: 89.544574 | DK14: 90.886435 | DL14: 92.00433 | DM14: 93.033603 | DN14: 94.032911 | DO14: 95.02733 | DP14: 96.027228 | DQ14: 97.036664 | DR14: 98.057089 | DS14: 99.088932 | DT14: 100.13227 | DU14: 101.18708 | DV14: 102.25334 | DW14: 103.33108 | DX14: 104.42033 | DY14: 105.52116 | DZ14: =DV14*(1+(DZ3-DZ4)) -> 104.29841 | EA14: =DW14*(1+(EA3-EA4)) -> 105.3977 | EB14: =DX14*(1+(EB3-EB4)) -> 106.50873 | EC14: =DY14*(1+(EC3-EC4)) -> 107.63158 | ED14: =DZ14*(1+(ED3-ED4)) -> 106.38438 | EE14: =EA14*(1+(EE3-EE4)) -> 107.50565 | EF14: =EB14*(1+(EF3-EF4)) -> 108.63891 | EG14: =EC14*(1+(EG3-EG4)) -> 109.78421 | ... HA14: =GW14*(1+(HA3-HA4)) -> 156.79889
A15: Общие | D15: ЦМИ | F15: Средний за период курс рубля к EUR (av EUR/RUB) | G15: EUR/руб | I15: формула | J15: 26.3747 | K15: 25.349 | L15: 26.1478 | M15: 26.7193 | N15: 27.0529 | O15: 28.7601 | P15: 31.0924 | Q15: 31.8304 | R15: 33.957 | S15: 35.0903 | T15: 34.2844 | U15: 35.4828 | V15: 35.7718 | W15: 34.8545 | X15: 35.6741 | Y15: 36.9858 | Z15: 36.4914 | AA15: 35.3656 | AB15: 34.7937 | AC15: 34.1385 | AD15: 33.8487 | AE15: 34.1884 | AF15: 34.1615 | AG15: 34.2894 | AH15: 34.4844 | AI15: 34.859 | AJ15: 35.0391 | AK15: 35.6952 | AL15: 36.3273 | AM15: 36.9215 | AN15: 36.4809 | AO15: 36.1145 | AP15: 44.4274 | AQ15: 43.8158 | AR15: 44.7688 | AS15: 43.5441 | AT15: 41.2707 | AU15: 38.5567 | AV15: 39.5486 | AW15: 41.6866 | AX15: 40.0071 | AY15: 40.2907 | AZ15: 41.1732 | BA15: 42.0394 | BB15: 39.5338 | BC15: 39.8296 | BD15: 39.9672 | BE15: 40.3153 | BF15: 40.1508 | BG15: 41.3383 | BH15: 43.4303 | BI15: 44.3158 | BJ15: 47.943979 | BK15: 48.027409 | BL15: 48.000184 | BM15: 59.099297 | BN15: 70.434887 | BO15: 58.23422 | BP15: 70.138228 | BQ15: 72.233264 | BR15: 82.372885 | BS15: 74.389575 | BT15: 72.147792 | BU15: 68.133501 | BV15: 62.625963 | BW15: 62.780388 | BX15: 69.278595 | BY15: 68.781737 | BZ15: 69.881304 | CA15: 73.735904 | CB15: 76.195989 | CC15: 75.910917 | CD15: 75.150953 | CE15: 72.517347 | CF15: 71.82569 | CG15: 70.53982 | CH15: 73.09325 | CI15: 79.646017 | CJ15: 85.996354 | CK15: 90.807926 | CL15: 89.706234 | CM15: 89.381959 | CN15: 86.649861 | CO15: 83.064098 | CP15: 95.960926 | CQ15: 70.68238 | CR15: 59.781307 | CS15: 63.539551 | CT15: 78.138026 | CU15: 88.253059 | CV15: 102.43427 | CW15: 99.7939 | CX15: =CX14*CX35 -> 98.630137 | CY15: =CY14*CY35 -> 97.573064 | CZ15: =CZ14*CZ35 -> 98.003841 | DA15: =DA14*DA35 -> 106.62496 | DB15: =DB14*DB35 -> 98.193948 | DC15: =DC14*DC35 -> 91.790997 | DD15: =DD14*DD35 -> 94.282881 | DE15: 94.584736 | DF15: =DF14*DF35 -> 91.634483 | DG15: =DG14*DG35 -> 86.625978 | DH15: =DH14*DH35 -> 94.861965 | DI15: =DI14*DI35 -> 101.8389 | DJ15: =DJ14*DJ35 -> 103.6983 | DK15: =DK14*DK35 -> 104.95069 | DL15: =DL14*DL35 -> 106.01167 | DM15: =DM14*DM35 -> 107.04245 | ... HA15: =HA14*HA35 -> 180.30383
A16: Общие | D16: Законодательство | F16: Налог на имущество, инвентаризационная стоимость (НК Часть 2 Статья 380, максимальная ставка) | G16: % | I16: С 2019 года = 2018 | BJ16: 0.022 | BK16: 0.022 | BL16: 0.022 | BM16: 0.022 | BN16: 0.022 | BO16: 0.022 | BP16: 0.022 | BQ16: 0.022 | BR16: 0.022 | BS16: 0.022 | BT16: 0.022 | BU16: 0.022 | BV16: 0.022 | BW16: 0.022 | BX16: 0.022 | BY16: 0.022 | BZ16: 0.022 | CA16: 0.022 | CB16: 0.022 | CC16: 0.022 | CD16: 0.022 | CE16: 0.022 | CF16: 0.022 | CG16: 0.022 | CH16: 0.022 | CI16: 0.022 | CJ16: 0.022 | CK16: 0.022 | CL16: =Inputs!AD16 -> 0.022 | CM16: =Inputs!AD16 -> 0.022 | CN16: =Inputs!AD16 -> 0.022 | CO16: =Inputs!AD16 -> 0.022 | CP16: =Inputs!AE16 -> 0.022 | CQ16: =Inputs!AE16 -> 0.022 | CR16: =Inputs!AE16 -> 0.022 | CS16: =Inputs!AE16 -> 0.022 | CT16: =Inputs!AF16 -> 0.022 | CU16: =Inputs!AF16 -> 0.022 | CV16: =Inputs!AF16 -> 0.022 | CW16: =Inputs!AF16 -> 0.022 | CX16: =Inputs!AG16 -> 0.022 | CY16: =Inputs!AG16 -> 0.022 | CZ16: =Inputs!AG16 -> 0.022 | DA16: =Inputs!AG16 -> 0.022 | DB16: =Inputs!AH16 -> 0.022 | DC16: =Inputs!AH16 -> 0.022 | DD16: =Inputs!AH16 -> 0.022 | DE16: =Inputs!AH16 -> 0.022 | DF16: =Inputs!AI16 -> 0.022 | DG16: =Inputs!AI16 -> 0.022 | DH16: =Inputs!AI16 -> 0.022 | DI16: =Inputs!AI16 -> 0.022 | DJ16: =Inputs!AJ16 -> 0.022 | DK16: =Inputs!AJ16 -> 0.022 | DL16: =Inputs!AJ16 -> 0.022 | DM16: =Inputs!AJ16 -> 0.022 | DN16: =Inputs!AK16 -> 0.022 | DO16: =Inputs!AK16 -> 0.022 | DP16: =Inputs!AK16 -> 0.022 | DQ16: =Inputs!AK16 -> 0.022 | DR16: =Inputs!AL16 -> 0.022 | DS16: =Inputs!AL16 -> 0.022 | DT16: =Inputs!AL16 -> 0.022 | DU16: =Inputs!AL16 -> 0.022 | DV16: =Inputs!AM16 -> 0.022 | DW16: =Inputs!AM16 -> 0.022 | DX16: =Inputs!AM16 -> 0.022 | DY16: =Inputs!AM16 -> 0.022 | DZ16: =Inputs!AN16 -> 0.022 | EA16: =Inputs!AN16 -> 0.022 | EB16: =Inputs!AN16 -> 0.022 | EC16: =Inputs!AN16 -> 0.022 | ED16: =Inputs!AO16 -> 0.022 | EE16: =Inputs!AO16 -> 0.022 | EF16: =Inputs!AO16 -> 0.022 | EG16: =Inputs!AO16 -> 0.022 | EH16: =Inputs!AP16 -> 0.022 | EI16: =Inputs!AP16 -> 0.022 | EJ16: =Inputs!AP16 -> 0.022 | EK16: =Inputs!AP16 -> 0.022 | EL16: =Inputs!AQ16 -> 0.022 | EM16: =Inputs!AP16 -> 0.022 | EN16: =Inputs!AQ16 -> 0.022 | EO16: =Inputs!AQ16 -> 0.022 | EP16: =Inputs!AR16 -> 0.022 | EQ16: =Inputs!AR16 -> 0.022 | ER16: =Inputs!AR16 -> 0.022 | ES16: =Inputs!AR16 -> 0.022 | ET16: =Inputs!AS16 -> 0.022 | EU16: =Inputs!AS16 -> 0.022 | EV16: =Inputs!AS16 -> 0.022 | EW16: =Inputs!AS16 -> 0.022 | EX16: =Inputs!AT16 -> 0.022 | EY16: =Inputs!AT16 -> 0.022 | EZ16: =Inputs!AT16 -> 0.022 | FA16: =Inputs!AT16 -> 0.022 | FB16: =Inputs!AU16 -> 0.022 | FC16: =Inputs!AU16 -> 0.022 | FD16: =Inputs!AU16 -> 0.022 | FE16: =Inputs!AU16 -> 0.022 | FF16: =Inputs!AV16 -> 0.022 | FG16: =Inputs!AV16 -> 0.022 | FH16: =Inputs!AV16 -> 0.022 | FI16: =Inputs!AV16 -> 0.022 | FJ16: =Inputs!AW16 -> 0.022 | FK16: =Inputs!AW16 -> 0.022 | FL16: =Inputs!AW16 -> 0.022 | FM16: =Inputs!AW16 -> 0.022 | FN16: =Inputs!AX16 -> 0.022 | FO16: =Inputs!AX16 -> 0.022 | FP16: =Inputs!AX16 -> 0.022 | FQ16: =Inputs!AX16 -> 0.022 | FR16: =Inputs!AY16 -> 0.022 | FS16: =Inputs!AY16 -> 0.022 | FT16: =Inputs!AY16 -> 0.022 | FU16: =Inputs!AY16 -> 0.022 | FV16: =Inputs!AZ16 -> 0.022 | FW16: =Inputs!AZ16 -> 0.022 | FX16: =Inputs!AZ16 -> 0.022 | FY16: =Inputs!AZ16 -> 0.022 | FZ16: =Inputs!BA16 -> 0.022 | GA16: =Inputs!BA16 -> 0.022 | GB16: =Inputs!BA16 -> 0.022 | GC16: =Inputs!BA16 -> 0.022 | GD16: =Inputs!BB16 -> 0.022 | GE16: =Inputs!BB16 -> 0.022 | GF16: =Inputs!BB16 -> 0.022 | GG16: =Inputs!BB16 -> 0.022 | GH16: =Inputs!BC16 -> 0.022 | GI16: =Inputs!BC16 -> 0.022 | GJ16: =Inputs!BC16 -> 0.022 | GK16: =Inputs!BC16 -> 0.022 | GL16: =Inputs!BD16 -> 0.022 | GM16: =Inputs!BD16 -> 0.022 | GN16: =Inputs!BD16 -> 0.022 | GO16: =Inputs!BD16 -> 0.022 | GP16: =Inputs!BE16 -> 0.022 | GQ16: =Inputs!BE16 -> 0.022 | GR16: =Inputs!BE16 -> 0.022 | GS16: =Inputs!BE16 -> 0.022 | GT16: =Inputs!BF16 -> 0.022 | GU16: =Inputs!BF16 -> 0.022 | GV16: =Inputs!BF16 -> 0.022 | GW16: =Inputs!BF16 -> 0.022 | GX16: =Inputs!BG16 -> 0.022 | GY16: =Inputs!BG16 -> 0.022 | GZ16: =Inputs!BG16 -> 0.022 | HA16: =Inputs!BG16 -> 0.022
A17: Общие | D17: Законодательство | F17: Налог на имущество, кадастровая стоимость Москва (Закон г. Москвы от 05.11.2003 N 64, ред. от 25.11.2015, "О налоге на имущество организаций") | G17: % | I17: С 2019 года = 2018 | BJ17: 0.009 | BK17: 0.009 | BL17: 0.009 | BM17: 0.009 | BN17: 0.012 | BO17: 0.012 | BP17: 0.012 | BQ17: 0.012 | BR17: 0.013 | BS17: 0.013 | BT17: 0.013 | BU17: 0.013 | BV17: 0.014 | BW17: 0.014 | BX17: 0.014 | BY17: 0.014 | BZ17: 0.015 | CA17: 0.015 | CB17: 0.015 | CC17: 0.015 | CD17: 0.016 | CE17: 0.015 | CF17: 0.015 | CG17: 0.015 | CH17: 0.017 | CI17: 0.017 | CJ17: 0.017 | CK17: 0.017 | CL17: =Inputs!AD17 -> 0.018 | CM17: =Inputs!AD17 -> 0.018 | CN17: =Inputs!AD17 -> 0.018 | CO17: =Inputs!AD17 -> 0.018 | CP17: =Inputs!AE17 -> 0.019 | CQ17: =Inputs!AE17 -> 0.019 | CR17: =Inputs!AE17 -> 0.019 | CS17: =Inputs!AE17 -> 0.019 | CT17: =Inputs!AF17 -> 0.02 | CU17: =Inputs!AF17 -> 0.02 | CV17: =Inputs!AF17 -> 0.02 | CW17: =Inputs!AF17 -> 0.02 | CX17: =Inputs!AG17 -> 0.02 | CY17: =Inputs!AG17 -> 0.02 | CZ17: =Inputs!AG17 -> 0.02 | DA17: =Inputs!AG17 -> 0.02 | DB17: =Inputs!AH17 -> 0.02 | DC17: =Inputs!AH17 -> 0.02 | DD17: =Inputs!AH17 -> 0.02 | DE17: =Inputs!AH17 -> 0.02 | DF17: =Inputs!AI17 -> 0.02 | DG17: =Inputs!AI17 -> 0.02 | DH17: =Inputs!AI17 -> 0.02 | DI17: =Inputs!AI17 -> 0.02 | DJ17: =Inputs!AJ17 -> 0.02 | DK17: =Inputs!AJ17 -> 0.02 | DL17: =Inputs!AJ17 -> 0.02 | DM17: =Inputs!AJ17 -> 0.02 | DN17: =Inputs!AK17 -> 0.02 | DO17: =Inputs!AK17 -> 0.02 | DP17: =Inputs!AK17 -> 0.02 | DQ17: =Inputs!AK17 -> 0.02 | DR17: =Inputs!AL17 -> 0.02 | DS17: =Inputs!AL17 -> 0.02 | DT17: =Inputs!AL17 -> 0.02 | DU17: =Inputs!AL17 -> 0.02 | DV17: =Inputs!AM17 -> 0.02 | DW17: =Inputs!AM17 -> 0.02 | DX17: =Inputs!AM17 -> 0.02 | DY17: =Inputs!AM17 -> 0.02 | DZ17: =Inputs!AN17 -> 0.02 | EA17: =Inputs!AN17 -> 0.02 | EB17: =Inputs!AN17 -> 0.02 | EC17: =Inputs!AN17 -> 0.02 | ED17: =Inputs!AO17 -> 0.02 | EE17: =Inputs!AO17 -> 0.02 | EF17: =Inputs!AO17 -> 0.02 | EG17: =Inputs!AO17 -> 0.02 | EH17: =Inputs!AP17 -> 0.02 | EI17: =Inputs!AP17 -> 0.02 | EJ17: =Inputs!AP17 -> 0.02 | EK17: =Inputs!AP17 -> 0.02 | EL17: =Inputs!AQ17 -> 0.02 | EM17: =Inputs!AP17 -> 0.02 | EN17: =Inputs!AQ17 -> 0.02 | EO17: =Inputs!AQ17 -> 0.02 | EP17: =Inputs!AR17 -> 0.02 | EQ17: =Inputs!AR17 -> 0.02 | ER17: =Inputs!AR17 -> 0.02 | ES17: =Inputs!AR17 -> 0.02 | ET17: =Inputs!AS17 -> 0.02 | EU17: =Inputs!AS17 -> 0.02 | EV17: =Inputs!AS17 -> 0.02 | EW17: =Inputs!AS17 -> 0.02 | EX17: =Inputs!AT17 -> 0.02 | EY17: =Inputs!AT17 -> 0.02 | EZ17: =Inputs!AT17 -> 0.02 | FA17: =Inputs!AT17 -> 0.02 | FB17: =Inputs!AU17 -> 0.02 | FC17: =Inputs!AU17 -> 0.02 | FD17: =Inputs!AU17 -> 0.02 | FE17: =Inputs!AU17 -> 0.02 | FF17: =Inputs!AV17 -> 0.02 | FG17: =Inputs!AV17 -> 0.02 | FH17: =Inputs!AV17 -> 0.02 | FI17: =Inputs!AV17 -> 0.02 | FJ17: =Inputs!AW17 -> 0.02 | FK17: =Inputs!AW17 -> 0.02 | FL17: =Inputs!AW17 -> 0.02 | FM17: =Inputs!AW17 -> 0.02 | FN17: =Inputs!AX17 -> 0.02 | FO17: =Inputs!AX17 -> 0.02 | FP17: =Inputs!AX17 -> 0.02 | FQ17: =Inputs!AX17 -> 0.02 | FR17: =Inputs!AY17 -> 0.02 | FS17: =Inputs!AY17 -> 0.02 | FT17: =Inputs!AY17 -> 0.02 | FU17: =Inputs!AY17 -> 0.02 | FV17: =Inputs!AZ17 -> 0.02 | FW17: =Inputs!AZ17 -> 0.02 | FX17: =Inputs!AZ17 -> 0.02 | FY17: =Inputs!AZ17 -> 0.02 | FZ17: =Inputs!BA17 -> 0.02 | GA17: =Inputs!BA17 -> 0.02 | GB17: =Inputs!BA17 -> 0.02 | GC17: =Inputs!BA17 -> 0.02 | GD17: =Inputs!BB17 -> 0.02 | GE17: =Inputs!BB17 -> 0.02 | GF17: =Inputs!BB17 -> 0.02 | GG17: =Inputs!BB17 -> 0.02 | GH17: =Inputs!BC17 -> 0.02 | GI17: =Inputs!BC17 -> 0.02 | GJ17: =Inputs!BC17 -> 0.02 | GK17: =Inputs!BC17 -> 0.02 | GL17: =Inputs!BD17 -> 0.02 | GM17: =Inputs!BD17 -> 0.02 | GN17: =Inputs!BD17 -> 0.02 | GO17: =Inputs!BD17 -> 0.02 | GP17: =Inputs!BE17 -> 0.02 | GQ17: =Inputs!BE17 -> 0.02 | GR17: =Inputs!BE17 -> 0.02 | GS17: =Inputs!BE17 -> 0.02 | GT17: =Inputs!BF17 -> 0.02 | GU17: =Inputs!BF17 -> 0.02 | GV17: =Inputs!BF17 -> 0.02 | GW17: =Inputs!BF17 -> 0.02 | GX17: =Inputs!BG17 -> 0.02 | GY17: =Inputs!BG17 -> 0.02 | GZ17: =Inputs!BG17 -> 0.02 | HA17: =Inputs!BG17 -> 0.02
A18: Общие | D18: Законодательство | F18: Налог на имущество, кадастровая стоимость кроме Москвы (НК Часть 2 Статья 380, максимальная ставка) | G18: % | I18: С 2019 года = 2018 | BJ18: 0.01 | BK18: 0.01 | BL18: 0.01 | BM18: 0.01 | BN18: 0.015 | BO18: 0.015 | BP18: 0.015 | BQ18: 0.015 | BR18: 0.02 | BS18: 0.02 | BT18: 0.02 | BU18: 0.02 | BV18: 0.02 | BW18: 0.02 | BX18: 0.02 | BY18: 0.02 | BZ18: 0.02 | CA18: 0.02 | CB18: 0.02 | CC18: 0.02 | CD18: 0.02 | CE18: 0.02 | CF18: 0.02 | CG18: 0.02 | CH18: 0.02 | CI18: 0.02 | CJ18: 0.02 | CK18: 0.02 | CL18: =Inputs!AD18 -> 0.02 | CM18: =Inputs!AD18 -> 0.02 | CN18: =Inputs!AD18 -> 0.02 | CO18: =Inputs!AD18 -> 0.02 | CP18: =Inputs!AE18 -> 0.02 | CQ18: =Inputs!AE18 -> 0.02 | CR18: =Inputs!AE18 -> 0.02 | CS18: =Inputs!AE18 -> 0.02 | CT18: =Inputs!AF18 -> 0.02 | CU18: =Inputs!AF18 -> 0.02 | CV18: =Inputs!AF18 -> 0.02 | CW18: =Inputs!AF18 -> 0.02 | CX18: =Inputs!AG18 -> 0.02 | CY18: =Inputs!AG18 -> 0.02 | CZ18: =Inputs!AG18 -> 0.02 | DA18: =Inputs!AG18 -> 0.02 | DB18: =Inputs!AH18 -> 0.02 | DC18: =Inputs!AH18 -> 0.02 | DD18: =Inputs!AH18 -> 0.02 | DE18: =Inputs!AH18 -> 0.02 | DF18: =Inputs!AI18 -> 0.02 | DG18: =Inputs!AI18 -> 0.02 | DH18: =Inputs!AI18 -> 0.02 | DI18: =Inputs!AI18 -> 0.02 | DJ18: =Inputs!AJ18 -> 0.02 | DK18: =Inputs!AJ18 -> 0.02 | DL18: =Inputs!AJ18 -> 0.02 | DM18: =Inputs!AJ18 -> 0.02 | DN18: =Inputs!AK18 -> 0.02 | DO18: =Inputs!AK18 -> 0.02 | DP18: =Inputs!AK18 -> 0.02 | DQ18: =Inputs!AK18 -> 0.02 | DR18: =Inputs!AL18 -> 0.02 | DS18: =Inputs!AL18 -> 0.02 | DT18: =Inputs!AL18 -> 0.02 | DU18: =Inputs!AL18 -> 0.02 | DV18: =Inputs!AM18 -> 0.02 | DW18: =Inputs!AM18 -> 0.02 | DX18: =Inputs!AM18 -> 0.02 | DY18: =Inputs!AM18 -> 0.02 | DZ18: =Inputs!AN18 -> 0.02 | EA18: =Inputs!AN18 -> 0.02 | EB18: =Inputs!AN18 -> 0.02 | EC18: =Inputs!AN18 -> 0.02 | ED18: =Inputs!AO18 -> 0.02 | EE18: =Inputs!AO18 -> 0.02 | EF18: =Inputs!AO18 -> 0.02 | EG18: =Inputs!AO18 -> 0.02 | EH18: =Inputs!AP18 -> 0.02 | EI18: =Inputs!AP18 -> 0.02 | EJ18: =Inputs!AP18 -> 0.02 | EK18: =Inputs!AP18 -> 0.02 | EL18: =Inputs!AQ18 -> 0.02 | EM18: =Inputs!AP18 -> 0.02 | EN18: =Inputs!AQ18 -> 0.02 | EO18: =Inputs!AQ18 -> 0.02 | EP18: =Inputs!AR18 -> 0.02 | EQ18: =Inputs!AR18 -> 0.02 | ER18: =Inputs!AR18 -> 0.02 | ES18: =Inputs!AR18 -> 0.02 | ET18: =Inputs!AS18 -> 0.02 | EU18: =Inputs!AS18 -> 0.02 | EV18: =Inputs!AS18 -> 0.02 | EW18: =Inputs!AS18 -> 0.02 | EX18: =Inputs!AT18 -> 0.02 | EY18: =Inputs!AT18 -> 0.02 | EZ18: =Inputs!AT18 -> 0.02 | FA18: =Inputs!AT18 -> 0.02 | FB18: =Inputs!AU18 -> 0.02 | FC18: =Inputs!AU18 -> 0.02 | FD18: =Inputs!AU18 -> 0.02 | FE18: =Inputs!AU18 -> 0.02 | FF18: =Inputs!AV18 -> 0.02 | FG18: =Inputs!AV18 -> 0.02 | FH18: =Inputs!AV18 -> 0.02 | FI18: =Inputs!AV18 -> 0.02 | FJ18: =Inputs!AW18 -> 0.02 | FK18: =Inputs!AW18 -> 0.02 | FL18: =Inputs!AW18 -> 0.02 | FM18: =Inputs!AW18 -> 0.02 | FN18: =Inputs!AX18 -> 0.02 | FO18: =Inputs!AX18 -> 0.02 | FP18: =Inputs!AX18 -> 0.02 | FQ18: =Inputs!AX18 -> 0.02 | FR18: =Inputs!AY18 -> 0.02 | FS18: =Inputs!AY18 -> 0.02 | FT18: =Inputs!AY18 -> 0.02 | FU18: =Inputs!AY18 -> 0.02 | FV18: =Inputs!AZ18 -> 0.02 | FW18: =Inputs!AZ18 -> 0.02 | FX18: =Inputs!AZ18 -> 0.02 | FY18: =Inputs!AZ18 -> 0.02 | FZ18: =Inputs!BA18 -> 0.02 | GA18: =Inputs!BA18 -> 0.02 | GB18: =Inputs!BA18 -> 0.02 | GC18: =Inputs!BA18 -> 0.02 | GD18: =Inputs!BB18 -> 0.02 | GE18: =Inputs!BB18 -> 0.02 | GF18: =Inputs!BB18 -> 0.02 | GG18: =Inputs!BB18 -> 0.02 | GH18: =Inputs!BC18 -> 0.02 | GI18: =Inputs!BC18 -> 0.02 | GJ18: =Inputs!BC18 -> 0.02 | GK18: =Inputs!BC18 -> 0.02 | GL18: =Inputs!BD18 -> 0.02 | GM18: =Inputs!BD18 -> 0.02 | GN18: =Inputs!BD18 -> 0.02 | GO18: =Inputs!BD18 -> 0.02 | GP18: =Inputs!BE18 -> 0.02 | GQ18: =Inputs!BE18 -> 0.02 | GR18: =Inputs!BE18 -> 0.02 | GS18: =Inputs!BE18 -> 0.02 | GT18: =Inputs!BF18 -> 0.02 | GU18: =Inputs!BF18 -> 0.02 | GV18: =Inputs!BF18 -> 0.02 | GW18: =Inputs!BF18 -> 0.02 | GX18: =Inputs!BG18 -> 0.02 | GY18: =Inputs!BG18 -> 0.02 | GZ18: =Inputs!BG18 -> 0.02 | HA18: =Inputs!BG18 -> 0.02
A19: Общие | D19: ЦМИ | F19: Инфляция з.платы (Рост номинальных заработных плат) | G19: % | I19: С 2021 года прогноз CIB; =CPI+рост реальных доходов | BJ19: 0.091 | BK19: 0.091 | BL19: 0.091 | BM19: 0.091 | BN19: 0.051174064 | BO19: 0.052623068 | BP19: 0.039712374 | BQ19: 0.027922656 | BR19: 0.075219187 | BS19: 0.077406099 | BT19: 0.082313008 | BU19: 0.085240482 | BV19: 0.056686987 | BW19: 0.072575614 | BX19: 0.0567783 | BY19: 0.074310867 | BZ19: 0.13083956 | CA19: 0.10906915 | CB19: 0.10887257 | CC19: 0.0947029 | CD19: 0.079943968 | CE19: 0.089394519 | CF19: 0.093138896 | CG19: 0.10318036 | CH19: 0.10117422 | CI19: 0.048108476 | CJ19: 0.07205966 | CK19: 0.084358796 | CL19: 0.074278432 | CM19: 0.1261224 | CN19: 0.10301027 | CO19: 0.11984631 | CP19: 0.15613678 | CQ19: 0.11531938 | CR19: 0.13527359 | CS19: 0.13728875 | CT19: 0.10751568 | CU19: 0.15315753 | CV19: 0.15001005 | CW19: 0.17230807 | CX19: 0.20791193 | CY19: 0.17558767 | CZ19: 0.18783257 | DA19: 0.20164524 | DB19: 0.14537781 | DC19: 0.1564201 | DD19: 0.14626253 | DE19: 0.1192822 | DF19: 0.15887965 | DG19: 0.11344423 | DH19: 0.10596088 | DI19: 0.10771092 | DJ19: 0.090135527 | DK19: 0.099754056 | DL19: 0.08332444 | DM19: 0.078278885 | DN19: =DN3+DN9 -> 0.065986005 | DO19: =DO3+DO9 -> 0.069669151 | DP19: =DP3+DP9 -> 0.064721067 | DQ19: =DQ3+DQ9 -> 0.062646647 | DR19: =DR3+DR9 -> 0.061660672 | DS19: =DS3+DS9 -> 0.061660467 | DT19: =DT3+DT9 -> 0.061038564 | DU19: =DU3+DU9 -> 0.061038564 | ... HA19: =HA3+HA9 -> 0.061023688
A20: Общие | D20: ЦМИ | F20: Ставка Euribor 3m | G20: % | I20: EoY, ЦМИ, 2022 и далее = 2021 | J20: 0.04561 | K20: 0.04441 | L20: 0.03656 | M20: 0.03294 | N20: 0.03448 | O20: 0.03441 | P20: 0.03297 | Q20: 0.02865 | R20: 0.02522 | S20: 0.02147 | T20: 0.02128 | U20: 0.02124 | V20: 0.01958 | W20: 0.0212 | X20: 0.0215 | Y20: 0.02155 | Z20: 0.02147 | AA20: 0.02106 | AB20: 0.02176 | AC20: 0.02488 | AD20: 0.02816 | AE20: 0.03056 | AF20: 0.03417 | AG20: 0.03725 | AH20: 0.03924 | AI20: 0.04175 | AJ20: 0.04792 | AK20: 0.04684 | AL20: 0.04727 | AM20: 0.04947 | AN20: 0.05277 | AO20: 0.02892 | AP20: 0.0151 | AQ20: 0.01099 | AR20: 0.00753 | AS20: 0.007 | AT20: 0.00634 | AU20: 0.00767 | AV20: 0.00892 | AW20: 0.01006 | AX20: 0.01239 | AY20: 0.01547 | AZ20: 0.01554 | BA20: 0.01356 | BB20: 0.00777 | BC20: 0.00653 | BD20: 0.0022 | BE20: 0.00187 | BF20: 0.00211 | BG20: 0.00218 | BH20: 0.00225 | BI20: 0.00287 | BJ20: 0.00313 | BK20: 0.00207 | BL20: 0.00083 | BM20: 0.00078 | BN20: 0.00019 | BO20: -0.00014 | BP20: -0.0004 | BQ20: -0.00131 | BR20: -0.00244 | BS20: -0.00286 | BT20: -0.00301 | BU20: -0.00319 | BV20: -0.00329 | BW20: -0.00331 | BX20: -0.00329 | BY20: -0.00329 | BZ20: -0.00328 | CA20: -0.00321 | CB20: -0.00318 | CC20: -0.00309 | CD20: -0.0031 | CE20: -0.00345 | CF20: -0.00418 | CG20: -0.00383 | CH20: -0.00363 | CI20: -0.0042 | CJ20: -0.00498 | CK20: -0.00545 | CL20: -0.00538 | CM20: -0.0054 | CN20: -0.0055 | CO20: -0.00572 | CP20: -0.00458 | CQ20: -0.00195 | CR20: 0.01173 | CS20: 0.02132 | CT20: 0.03038 | CU20: 0.03577 | CV20: 0.03952 | CW20: 0.03909 | CX20: 0.03892 | CY20: 0.03711 | CZ20: 0.03279 | DA20: 0.02678 | DB20: 0.02336 | DC20: 0.02 | DD20: 0.02032 | DE20: 0.02026 | DF20: 0.0209 | DG20: 0.0226 | DH20: 0.0286 | DI20: 0.0285 | DJ20: 0.0284 | DK20: 0.0283 | DL20: 0.0282 | DM20: 0.0281 | DN20: 0.0258 | DO20: 0.0257 | DP20: 0.0256 | DQ20: 0.023 | DR20: 0.0229 | DS20: 0.0229 | DT20: =Inputs!AL20 -> 0.0228 | DU20: =Inputs!AL20 -> 0.0228 | DV20: =Inputs!AM20 -> 0.0228 | DW20: =Inputs!AM20 -> 0.0228 | DX20: =Inputs!AM20 -> 0.0228 | DY20: =Inputs!AM20 -> 0.0228 | DZ20: =Inputs!AN20 -> 0.0228 | EA20: =Inputs!AN20 -> 0.0228 | EB20: =Inputs!AN20 -> 0.0228 | EC20: =Inputs!AN20 -> 0.0228 | ED20: =Inputs!AO20 -> 0.0228 | EE20: =Inputs!AO20 -> 0.0228 | EF20: =Inputs!AO20 -> 0.0228 | EG20: =Inputs!AO20 -> 0.0228 | EH20: =Inputs!AP20 -> 0.0228 | EI20: =Inputs!AP20 -> 0.0228 | EJ20: =Inputs!AP20 -> 0.0228 | EK20: =Inputs!AP20 -> 0.0228 | EL20: =Inputs!AQ20 -> 0.0228 | EM20: =Inputs!AP20 -> 0.0228 | EN20: =Inputs!AQ20 -> 0.0228 | EO20: =Inputs!AQ20 -> 0.0228 | EP20: =Inputs!AR20 -> 0.0228 | EQ20: =Inputs!AR20 -> 0.0228 | ER20: =Inputs!AR20 -> 0.0228 | ES20: =Inputs!AR20 -> 0.0228 | ET20: =Inputs!AS20 -> 0.0228 | EU20: =Inputs!AS20 -> 0.0228 | EV20: =Inputs!AS20 -> 0.0228 | EW20: =Inputs!AS20 -> 0.0228 | EX20: =Inputs!AT20 -> 0.0228 | EY20: =Inputs!AT20 -> 0.0228 | EZ20: =Inputs!AT20 -> 0.0228 | FA20: =Inputs!AT20 -> 0.0228 | FB20: =Inputs!AU20 -> 0.0228 | FC20: =Inputs!AU20 -> 0.0228 | FD20: =Inputs!AU20 -> 0.0228 | FE20: =Inputs!AU20 -> 0.0228 | FF20: =Inputs!AV20 -> 0.0228 | FG20: =Inputs!AV20 -> 0.0228 | FH20: =Inputs!AV20 -> 0.0228 | FI20: =Inputs!AV20 -> 0.0228 | FJ20: =Inputs!AW20 -> 0.0228 | FK20: =Inputs!AW20 -> 0.0228 | FL20: =Inputs!AW20 -> 0.0228 | FM20: =Inputs!AW20 -> 0.0228 | FN20: =Inputs!AX20 -> 0.0228 | FO20: =Inputs!AX20 -> 0.0228 | FP20: =Inputs!AX20 -> 0.0228 | FQ20: =Inputs!AX20 -> 0.0228 | FR20: =Inputs!AY20 -> 0.0228 | FS20: =Inputs!AY20 -> 0.0228 | FT20: =Inputs!AY20 -> 0.0228 | FU20: =Inputs!AY20 -> 0.0228 | FV20: =Inputs!AZ20 -> 0.0228 | FW20: =Inputs!AZ20 -> 0.0228 | FX20: =Inputs!AZ20 -> 0.0228 | FY20: =Inputs!AZ20 -> 0.0228 | FZ20: =Inputs!BA20 -> 0.0228 | GA20: =Inputs!BA20 -> 0.0228 | GB20: =Inputs!BA20 -> 0.0228 | GC20: =Inputs!BA20 -> 0.0228 | GD20: =Inputs!BB20 -> 0.0228 | GE20: =Inputs!BB20 -> 0.0228 | GF20: =Inputs!BB20 -> 0.0228 | GG20: =Inputs!BB20 -> 0.0228 | GH20: =Inputs!BC20 -> 0.0228 | GI20: =Inputs!BC20 -> 0.0228 | GJ20: =Inputs!BC20 -> 0.0228 | GK20: =Inputs!BC20 -> 0.0228 | GL20: =Inputs!BD20 -> 0.0228 | GM20: =Inputs!BD20 -> 0.0228 | GN20: =Inputs!BD20 -> 0.0228 | GO20: =Inputs!BD20 -> 0.0228 | GP20: =Inputs!BE20 -> 0.0228 | GQ20: =Inputs!BE20 -> 0.0228 | GR20: =Inputs!BE20 -> 0.0228 | GS20: =Inputs!BE20 -> 0.0228 | GT20: =Inputs!BF20 -> 0.0228 | GU20: =Inputs!BF20 -> 0.0228 | GV20: =Inputs!BF20 -> 0.0228 | GW20: =Inputs!BF20 -> 0.0228 | GX20: =Inputs!BG20 -> 0.0228 | GY20: =Inputs!BG20 -> 0.0228 | GZ20: =Inputs!BG20 -> 0.0228 | HA20: =Inputs!BG20 -> 0.0228
A21: Общие | D21: ЦМИ | F21: Процентный своп IRS 1Y Mosprime | G21: % | I21: EoY | AF21: 0.0519 | AG21: 0.0578 | AH21: 0.059 | AI21: 0.056 | AJ21: 0.066 | AK21: 0.0568 | AL21: 0.0764 | AM21: 0.0655 | AN21: 0.08375 | AO21: 0.1575 | AP21: 0.154 | AQ21: 0.118 | AR21: 0.102055 | AS21: 0.0732 | AT21: 0.04938 | AU21: 0.048 | AV21: 0.046 | AW21: 0.05335 | AX21: 0.0487 | AY21: 0.048 | AZ21: 0.0708 | BA21: 0.0733 | BB21: 0.0671 | BC21: 0.0771 | BD21: 0.0764 | BE21: 0.0739 | BF21: 0.0726 | BG21: 0.0701 | BH21: 0.0672 | BI21: 0.0697 | BJ21: 0.0892 | BK21: 0.094155 | BL21: 0.108933 | BM21: 0.204348 | BN21: 0.149 | BO21: 0.125112 | BP21: 0.12715 | BQ21: 0.116875 | BR21: 0.113675 | BS21: 0.1065 | BT21: 0.104 | BU21: 0.10455 | BV21: 0.0992 | BW21: 0.0899 | BX21: 0.0848 | BY21: 0.07805 | BZ21: 0.0699 | CA21: 0.0772 | CB21: 0.0894 | CC21: 0.0956 | CD21: 0.0847 | CE21: 0.0792 | CF21: 0.0711 | CG21: 0.0646 | CH21: 0.0696 | CI21: 0.0464 | CJ21: 0.0477 | CK21: 0.0504 | CL21: 0.0617 | CM21: 0.0762 | CN21: 0.0811 | CO21: 0.1022 | CP21: 0.22 | CQ21: 0.102 | CR21: 0.0885 | CS21: 0.088 | CT21: 0.089 | CU21: 0.087 | CV21: 0.14075 | CW21: 0.1516 | CX21: 0.152 | CY21: 0.1915 | CZ21: 0.2068 | DA21: 0.215 | DB21: 0.2059 | DC21: 0.1692 | DD21: 0.1568 | DE21: 0.1515 | DF21: 0.142 | DG21: 0.1442 | DH21: 0.1419 | DI21: 0.13642095 | DJ21: 0.13159031 | DK21: 0.12640968 | DL21: 0.12051127 | DM21: 0.11417202 | DN21: 0.10772648 | DO21: 0.10149529 | DP21: 0.096990776 | DQ21: 0.094298272 | DR21: 0.092974323 | DS21: 0.09297435 | DT21: 0.092975358 | DU21: 0.092975259 | DV21: 0.092974323 | DW21: 0.09297435 | DX21: 0.092975358 | DY21: 0.092975259 | DZ21: =DY21+(DZ$39-DY$39) -> 0.092975259 | EA21: =DZ21+(EA$39-DZ$39) -> 0.092975259 | EB21: =EA21+(EB$39-EA$39) -> 0.092975259 | EC21: =EB21+(EC$39-EB$39) -> 0.092975259 | ED21: =EC21+(ED$39-EC$39) -> 0.092975259 | EE21: =ED21+(EE$39-ED$39) -> 0.092975259 | EF21: =EE21+(EF$39-EE$39) -> 0.092975259 | EG21: =EF21+(EG$39-EF$39) -> 0.092975259 | ... HA21: =GZ21+(HA$39-GZ$39) -> 0.092975259
A22: Общие | D22: ЦМИ | F22: Процентный своп IRS 3Y Mosprime | G22: % | I22: EoY | AF22: 0.05815 | AG22: 0.0615 | AH22: 0.06315 | AI22: 0.0633 | AJ22: 0.06955 | AK22: 0.0667 | AL22: 0.0792 | AM22: 0.079051 | AN22: 0.0869 | AO22: 0.16 | AP22: 0.1425 | AQ22: 0.116 | AR22: 0.10254 | AS22: 0.076 | AT22: 0.05941 | AU22: 0.061 | AV22: 0.0595 | AW22: 0.0675 | AX22: 0.06401 | AY22: 0.06 | AZ22: 0.0747 | BA22: 0.074 | BB22: 0.06975 | BC22: 0.0792 | BD22: 0.0801 | BE22: 0.0738 | BF22: 0.0726 | BG22: 0.0712 | BH22: 0.0682 | BI22: 0.0702 | BJ22: 0.0861 | BK22: 0.0901 | BL22: 0.1045 | BM22: 0.1493 | BN22: 0.13065 | BO22: 0.11715 | BP22: 0.12075 | BQ22: 0.1089 | BR22: 0.1041 | BS22: 0.0958 | BT22: 0.092801 | BU22: 0.0959 | BV22: 0.0882 | BW22: 0.0832 | BX22: 0.0812 | BY22: 0.0765 | BZ22: 0.06855 | CA22: 0.0791 | CB22: 0.0927 | CC22: 0.0968 | CD22: 0.0831 | CE22: 0.0776 | CF22: 0.0706 | CG22: 0.0634 | CH22: 0.0702 | CI22: 0.0492 | CJ22: 0.0517 | CK22: 0.0554 | CL22: 0.0678 | CM22: 0.0756 | CN22: 0.078 | CO22: 0.0935 | CP22: 0.18 | CQ22: 0.102 | CR22: 0.1025 | CS22: 0.097 | CT22: 0.0995 | CU22: 0.096 | CV22: 0.12755 | CW22: 0.1293 | CX22: 0.1358 | CY22: 0.1745 | CZ22: 0.1892 | DA22: 0.1915 | DB22: 0.1634 | DC22: 0.14395 | DD22: 0.1439 | DE22: 0.14 | DF22: 0.1325 | DG22: 0.1408 | DH22: 0.1454 | DI22: 0.13311142 | DJ22: 0.12040281 | DK22: 0.11540692 | DL22: 0.11072368 | DM22: 0.10648377 | DN22: 0.10266596 | DO22: 0.099373252 | DP22: 0.096693176 | DQ22: 0.095726654 | DR22: 0.095252956 | DS22: 0.09525281 | DT22: 0.095253791 | DU22: 0.095253555 | DV22: 0.095253149 | DW22: 0.09525316 | DX22: 0.095254134 | DY22: 0.095253891 | DZ22: =DY22+(DZ$39-DY$39) -> 0.095253891 | EA22: =DZ22+(EA$39-DZ$39) -> 0.095253891 | EB22: =EA22+(EB$39-EA$39) -> 0.095253891 | EC22: =EB22+(EC$39-EB$39) -> 0.095253891 | ED22: =EC22+(ED$39-EC$39) -> 0.095253891 | EE22: =ED22+(EE$39-ED$39) -> 0.095253891 | EF22: =EE22+(EF$39-EE$39) -> 0.095253891 | EG22: =EF22+(EG$39-EF$39) -> 0.095253891 | ... HA22: =GZ22+(HA$39-GZ$39) -> 0.095253891
A23: Общие | D23: ЦМИ | F23: Процентный своп IRS 5Y Mosprime | G23: % | I23: EoY | AF23: 0.0616 | AG23: 0.064 | AH23: 0.066 | AI23: 0.06745 | AJ23: 0.07245 | AK23: 0.0718 | AL23: 0.0838 | AM23: 0.0901 | AN23: 0.10234 | AO23: 0.165 | AP23: 0.148 | AQ23: 0.11654 | AR23: 0.10956 | AS23: 0.0785 | AT23: 0.0679 | AU23: 0.0675 | AV23: 0.0665 | AW23: 0.0735 | AX23: 0.0708 | AY23: 0.0668 | AZ23: 0.0774 | BA23: 0.0756 | BB23: 0.0719 | BC23: 0.0804 | BD23: 0.0824 | BE23: 0.0743 | BF23: 0.0728 | BG23: 0.0725 | BH23: 0.0703 | BI23: 0.0721 | BJ23: 0.0853 | BK23: 0.0886 | BL23: 0.1028 | BM23: 0.1337 | BN23: 0.1256 | BO23: 0.1147 | BP23: 0.118 | BQ23: 0.1062 | BR23: 0.10095 | BS23: 0.0914 | BT23: 0.0885 | BU23: 0.0918 | BV23: 0.0856 | BW23: 0.0809 | BX23: 0.0798 | BY23: 0.076 | BZ23: 0.0706 | CA23: 0.0808 | CB23: 0.092 | CC23: 0.0956 | CD23: 0.084 | CE23: 0.0786 | CF23: 0.0712 | CG23: 0.0646 | CH23: 0.0717 | CI23: 0.053 | CJ23: 0.0554 | CK23: 0.0588 | CL23: 0.0704 | CM23: 0.0735 | CN23: 0.0761 | CO23: 0.0894 | CP23: 0.16 | CQ23: 0.1025 | CR23: 0.111 | CS23: 0.102 | CT23: 0.1025 | CU23: 0.0985 | CV23: 0.1243 | CW23: 0.124 | CX23: 0.1317 | CY23: 0.163 | CZ23: 0.1723 | DA23: 0.182 | DB23: 0.1523 | DC23: 0.1408 | DD23: 0.1405 | DE23: 0.1395 | DF23: 0.1325 | DG23: 0.1415 | DH23: 0.1488 | DI23: 0.13307039 | DJ23: 0.11898239 | DK23: 0.11465384 | DL23: 0.11051528 | DM23: 0.10666102 | DN23: 0.10308826 | DO23: 0.099852765 | DP23: 0.097002772 | DQ23: 0.096383824 | DR23: 0.096079148 | DS23: 0.096079164 | DT23: 0.096080045 | DU23: 0.096079831 | DV23: 0.096079377 | DW23: 0.096079389 | DX23: 0.096080264 | DY23: 0.096080046 | DZ23: =DY23+(DZ$39-DY$39) -> 0.096080046 | EA23: =DZ23+(EA$39-DZ$39) -> 0.096080046 | EB23: =EA23+(EB$39-EA$39) -> 0.096080046 | EC23: =EB23+(EC$39-EB$39) -> 0.096080046 | ED23: =EC23+(ED$39-EC$39) -> 0.096080046 | EE23: =ED23+(EE$39-ED$39) -> 0.096080046 | EF23: =EE23+(EF$39-EE$39) -> 0.096080046 | EG23: =EF23+(EG$39-EF$39) -> 0.096080046 | ... HA23: =GZ23+(HA$39-GZ$39) -> 0.096080046
A24: Общие | D24: ЦМИ | F24: Процентный своп IRS 7Y Mosprime | G24: % | I24: EoY | AF24: 0.0631 | AG24: 0.0646 | AH24: 0.06915 | AI24: 0.07005 | AJ24: 0.0733 | AK24: 0.0737 | AL24: 0.087 | AM24: 0.0959 | AN24: 0.10452 | AO24: 0.165 | AP24: 0.151 | AQ24: 0.119 | AR24: 0.11206 | AS24: 0.0815 | AT24: 0.071684 | AU24: 0.071137 | AV24: 0.070655 | AW24: 0.07651 | AX24: 0.0746 | AY24: 0.07 | AZ24: 0.0779 | BA24: 0.07674 | BB24: 0.0735 | BC24: 0.0811 | BD24: 0.0846 | BE24: 0.0761 | BF24: 0.074 | BG24: 0.0742 | BH24: 0.0726 | BI24: 0.0736 | BJ24: 0.0847 | BK24: 0.0883 | BL24: 0.102 | BM24: 0.1243 | BN24: 0.1226 | BO24: 0.1147 | BP24: 0.11705 | BQ24: 0.1055 | BR24: 0.0994 | BS24: 0.0893 | BT24: 0.0856 | BU24: 0.0901 | BV24: 0.0834 | BW24: 0.0798 | BX24: 0.0787 | BY24: 0.075499 | BZ24: 0.072151 | CA24: 0.0822 | CB24: 0.0919 | CC24: 0.0945 | CD24: 0.0855 | CE24: 0.0815 | CF24: 0.0733 | CG24: 0.0682 | CH24: 0.0726 | CI24: 0.0563 | CJ24: 0.0597 | CK24: 0.0613 | CL24: 0.0721 | CM24: 0.0733 | CN24: 0.0765 | CO24: 0.0879 | CP24: =CP23+(CP25-CP23)*2/5 -> 0.152 | CQ24: =CQ23+(CQ25-CQ23)*2/5 -> 0.1027 | CR24: =CR23+(CR25-CR23)*2/5 -> 0.1126 | CS24: =CS23+(CS25-CS23)*2/5 -> 0.1048 | CT24: =CT23+(CT25-CT23)*2/5 -> 0.1059 | CU24: =CU23+(CU25-CU23)*2/5 -> 0.1007 | CV24: =CV23+(CV25-CV23)*2/5 -> 0.12202 | CW24: =CW23+(CW25-CW23)*2/5 -> 0.12216 | ... HA24: =HA23+(HA25-HA23)*2/5 -> 0.097156938
A25: Общие | D25: ЦМИ | F25: Процентный своп IRS 10Y Mosprime | G25: % | I25: EoY | AF25: 0.06385 | AG25: 0.0651 | AH25: 0.07025 | AI25: 0.0715 | AJ25: 0.075 | AK25: 0.0766 | AL25: 0.0881 | AM25: 0.0991 | AN25: 0.11652 | AO25: 0.165 | AP25: 0.14625 | AQ25: 0.119 | AR25: 0.11356 | AS25: 0.082 | AT25: 0.074 | AU25: 0.07483 | AV25: 0.074825 | AW25: 0.07951 | AX25: 0.0768 | AY25: 0.0729 | AZ25: 0.08169 | BA25: 0.078165 | BB25: 0.0758 | BC25: 0.0829 | BD25: 0.0884 | BE25: 0.0795 | BF25: 0.0772 | BG25: 0.0769 | BH25: 0.0761 | BI25: 0.0765 | BJ25: 0.0853 | BK25: 0.0892 | BL25: 0.1021 | BM25: 0.1253 | BN25: 0.1207 | BO25: 0.1135 | BP25: 0.1167 | BQ25: 0.1063 | BR25: 0.0974 | BS25: 0.0866 | BT25: 0.0835 | BU25: 0.0872 | BV25: 0.081425 | BW25: 0.0789 | BX25: 0.0782 | BY25: 0.07505 | BZ25: 0.0727 | CA25: 0.0831 | CB25: 0.091 | CC25: 0.0932 | CD25: 0.0865 | CE25: 0.0827 | CF25: 0.0734 | CG25: 0.0684 | CH25: 0.0748 | CI25: 0.0599 | CJ25: 0.0623 | CK25: 0.0646 | CL25: 0.0735 | CM25: 0.0727 | CN25: 0.0772 | CO25: 0.0877 | CP25: 0.14 | CQ25: 0.103 | CR25: 0.115 | CS25: 0.109 | CT25: 0.111 | CU25: 0.104 | CV25: 0.1186 | CW25: 0.1194 | CX25: 0.1282 | CY25: 0.15 | CZ25: 0.1488 | DA25: 0.1585 | DB25: 0.1422 | DC25: 0.1387 | DD25: 0.1414 | DE25: 0.142 | DF25: 0.134 | DG25: 0.1638 | DH25: 0.1507 | DI25: 0.13328078 | DJ25: 0.12067908 | DK25: 0.11674339 | DL25: 0.11290005 | DM25: 0.10921864 | DN25: 0.10571326 | DO25: 0.10240139 | DP25: 0.099302519 | DQ25: 0.098946654 | DR25: 0.098772277 | DS25: 0.098772277 | DT25: 0.098772277 | DU25: 0.098772277 | DV25: 0.098772277 | DW25: 0.098772277 | DX25: 0.098772277 | DY25: 0.098772277 | DZ25: =DY25+(DZ$39-DY$39) -> 0.098772277 | EA25: =DZ25+(EA$39-DZ$39) -> 0.098772277 | EB25: =EA25+(EB$39-EA$39) -> 0.098772277 | EC25: =EB25+(EC$39-EB$39) -> 0.098772277 | ED25: =EC25+(ED$39-EC$39) -> 0.098772277 | EE25: =ED25+(EE$39-ED$39) -> 0.098772277 | EF25: =EE25+(EF$39-EE$39) -> 0.098772277 | EG25: =EF25+(EG$39-EF$39) -> 0.098772277 | ... HA25: =GZ25+(HA$39-GZ$39) -> 0.098772277
A26: Общие | D26: Расчет | F26: Средний за период курс рубля к CHF (av CHF/RUB) | G26: CHF/руб | I26: формула | J26: 17.1931 | K26: 16.5916 | L26: 17.3735 | M26: 18.1322 | N26: 18.3625 | O26: 19.6485 | P26: 21.2406 | Q26: 21.7274 | R26: 23.1746 | S26: 23.1272 | T26: 22.1975 | U26: 22.8366 | V26: 22.8223 | W26: 22.6648 | X26: 23.2206 | Y26: 24.125 | Z26: 23.5592 | AA26: 22.9062 | AB26: 22.3976 | AC26: 22.0631 | AD26: 21.7089 | AE26: 21.8758 | AF26: 21.663 | AG26: 21.522 | AH26: 21.3308 | AI26: 21.1494 | AJ26: 21.2611 | AK26: 21.5073 | AL26: 22.6992 | AM26: 22.899 | AN26: 22.641 | AO26: 23.7102 | AP26: 29.6732 | AQ26: 28.9476 | AR26: 29.4707 | AS26: 28.8783 | AT26: 28.225 | AU26: 27.3523 | AV26: 29.6881 | AW26: 31.5486 | AX26: 31.0745 | AY26: 32.2107 | AZ26: 35.4158 | BA26: 34.2038 | BB26: 32.7301 | BC26: 33.1454 | BD26: 33.2013 | BE26: 33.3818 | BF26: 32.6935 | BG26: 33.5929 | BH26: 35.2075 | BI26: 36.0525 | BJ26: 39.263 | BK26: 39.3424 | BL26: 39.674 | BM26: 49.7768 | BN26: 66.1202 | BO26: 55.9971 | BP26: 65.4826 | BQ26: 66.8298 | BR26: 75.0467 | BS26: 67.7608 | BT26: 66.2176 | BU26: 62.9265 | BV26: 58.4609 | BW26: 58.1694 | BX26: 61.2408 | BY26: 59.2064 | BZ26: 59.9715 | CA26: 62.939 | CB26: 66.6866 | CC26: 66.9313 | CD26: 66.1792 | CE26: 64.3433 | CF26: 65.5747 | CG26: 64.3407 | CH26: 69.1857 | CI26: 75.066 | CJ26: 80.2179 | CK26: 84.2081 | CL26: 82.2552 | CM26: 81.4603 | CN26: 80.0259 | CO26: 78.9016 | CP26: 94.473982 | CQ26: 69.319685 | CR26: 61.581241 | CS26: 65.182474 | CT26: 79.005084 | CU26: 90.34171 | CV26: 106.61479 | CW26: 104.49862 | CX26: 103.62164 | CY26: 100.03021 | CZ26: 103.01284 | DA26: 113.62648 | DB26: =DB14/DB41 -> 106.24739 | DC26: =DC14/DC41 -> 92.089172 | DD26: =DD14/DD41 -> 91.849911 | DE26: =DE14/DE41 -> 91.05617 | DF26: =DF14/DF41 -> 89.169572 | DG26: =DG14/DG41 -> 84.852455 | DH26: =DH14/DH41 -> 93.542427 | DI26: =DI14/DI41 -> 99.826592 | ... HA26: =HA14/HA41 -> 178.64747
A27: Общие | D27: Расчет | F27: Курс рубля к CHF в конце года (eop CHF/RUB) | G27: CHF/руб | I27: формула | J27: 16.5021 | K27: 16.2641 | L27: 18.185 | M27: 18.2369 | N27: 18.563 | O27: 21.2525 | P27: 21.4818 | Q27: 23.0955 | R27: 23.2249 | S27: 22.4779 | T27: 23.186 | U27: 23.5997 | V27: 22.52 | W27: 23.275 | X27: 23.4514 | Y27: 24.3093 | Z27: 23.2863 | AA27: 22.3427 | AB27: 22.0246 | AC27: 21.8849 | AD27: 21.2424 | AE27: 21.9474 | AF27: 21.4275 | AG27: 21.5933 | AH27: 21.3792 | AI27: 21.0731 | AJ27: 21.3489 | AK27: 21.7309 | AL27: 23.6097 | AM27: 22.9614 | AN27: 22.8558 | AO27: 28.5061 | AP27: 29.7974 | AQ27: 28.6771 | AR27: 28.9626 | AS27: 29.0201 | AT27: 27.9287 | AU27: 29.0139 | AV27: 31.1267 | AW27: 32.6538 | AX27: 30.8777 | AY27: 33.1655 | AZ27: 35.511 | BA27: 34.2922 | BB27: 32.521 | BC27: 34.1309 | BD27: 33.1639 | BE27: 33.3727 | BF27: 32.7206 | BG27: 34.7507 | BH27: 35.7863 | BI27: 36.8481 | BJ27: 39.6267 | BK27: 38.3189 | BL27: 41.4575 | BM27: 58.3849 | BN27: 59.8523 | BO27: 59.1474 | BP27: 67.1128 | BQ27: 72.3809 | BR27: 69.6978 | BS27: 65.4219 | BT27: 64.7262 | BU27: 60.4368 | BV27: 56.1017 | BW27: 61.4015 | BX27: 59.3967 | BY27: 59.1824 | BZ27: 59.856 | CA27: 63.3645 | CB27: 66.776 | CC27: =Inputs!AA27 -> 70.5787 | CD27: 66.0035 | CE27: 64.7582 | CF27: 64.9239 | CG27: =Inputs!AB27 -> 63.6039 | CH27: 81.745 | CI27: 75.1295 | CJ27: 84.3125 | CK27: =Inputs!AC27 -> 83.5131 | CL27: 80.1611 | CM27: 79.0799 | CN27: 78.0871 | CO27: =Inputs!AD27 -> 80.9376 | CP27: 90.8145 | CQ27: 53.5406 | CR27: 58.4178 | CS27: =Inputs!AE27 -> 76.1805 | CT27: 84.1278 | CU27: 97.2448 | CV27: 107.0844 | CW27: =Inputs!AF27 -> 106.7591 | CX27: 101.9267 | CY27: 95.3073 | CZ27: 109.7061 | DA27: =Inputs!AG27 -> 112.9774 | DB27: =DB7/DB40 -> 94.228929 | DC27: =DC7/DC40 -> 90.309587 | DD27: =DD7/DD40 -> 97.522801 | DE27: 99.1969 | DF27: =DF7/DF40 -> 98.977902 | DG27: =DG7/DG40 -> 95.744243 | DH27: =DH7/DH40 -> 104.94362 | DI27: =DI7/DI40 -> 110.94649 | DJ27: =DJ7/DJ40 -> 111.85631 | DK27: =DK7/DK40 -> 112.16269 | DL27: =DL7/DL40 -> 112.23158 | DM27: =DM7/DM40 -> 112.21018 | ... HA27: =HA7/HA40 -> 185.84446
A28: Общие | D28: CIB Research | F28: Инфляция - Рост индекса цен производителей в США, в долларах США (USD, eop PPI) | G28: % | I28: =CPI | J28: 0.03 | K28: 0.026 | L28: 0.016 | M28: -0.016 | N28: -0.016 | O28: -0.023 | P28: -0.018 | Q28: 0.012 | R28: 0.04 | S28: 0.029 | T28: 0.035 | U28: 0.04 | V28: 0.015 | W28: 0.04 | X28: 0.033 | Y28: 0.042 | Z28: 0.05 | AA28: 0.037 | AB28: 0.069 | AC28: 0.054 | AD28: 0.036 | AE28: 0.049 | AF28: 0.009 | AG28: 0.011 | AH28: 0.031 | AI28: 0.033 | AJ28: 0.044 | AK28: 0.062 | AL28: 0.067 | AM28: 0.091 | AN28: 0.088 | AO28: -0.009 | AP28: -0.034 | AQ28: -0.044 | AR28: -0.049 | AS28: 0.043 | AT28: 0.059 | AU28: 0.027 | AV28: 0.039 | AW28: 0.038 | AX28: 0.057 | AY28: 0.07 | AZ28: 0.071 | BA28: 0.047 | BB28: 0.027 | BC28: 0.007 | BD28: 0.021 | BE28: 0.014 | BF28: 0.011 | BG28: 0.023 | BH28: 0.002 | BI28: 0.014 | BJ28: 0.018 | BK28: 0.028 | BL28: 0.022 | BM28: -0.006 | BN28: -0.033 | BO28: -0.026 | BP28: -0.041 | BQ28: -0.027 | BR28: -0.023 | BS28: -0.02 | BT28: -0.001 | BU28: 0.019 | BV28: 0.038 | BW28: 0.021 | BX28: 0.033 | BY28: 0.032 | BZ28: 0.03 | CA28: 0.041 | CB28: 0.032 | CC28: 0.013 | CD28: 0.014 | CE28: 0.005 | CF28: -0.001 | CG28: 0.017 | CH28: -0.015 | CI28: -0.023 | CJ28: -0.012 | CK28: -0.008 | CL28: 0.059 | CM28: 0.097 | CN28: 0.118 | CO28: 0.122 | CP28: =CP4 -> 0.085474376 | CQ28: =CQ4 -> 0.089897548 | CR28: =CR4 -> 0.081982851 | CS28: =CS4 -> 0.064115004 | CT28: =Inputs!AF28 -> 0.03323156 | CU28: =Inputs!AF28 -> 0.03323156 | CV28: =Inputs!AF28 -> 0.03323156 | CW28: =Inputs!AF28 -> 0.03323156 | CX28: =Inputs!AG28 -> 0.028723677 | CY28: =Inputs!AG28 -> 0.028723677 | CZ28: =Inputs!AG28 -> 0.028723677 | DA28: =Inputs!AG28 -> 0.028723677 | DB28: =Inputs!AH28 -> 0.026899449 | DC28: =Inputs!AH28 -> 0.026899449 | DD28: =Inputs!AH28 -> 0.026899449 | DE28: =Inputs!AH28 -> 0.026899449 | DF28: =Inputs!AI28 -> 0.027326387 | DG28: =Inputs!AI28 -> 0.027326387 | DH28: =Inputs!AI28 -> 0.027326387 | DI28: =Inputs!AI28 -> 0.027326387 | DJ28: =Inputs!AJ28 -> 0.026069089 | DK28: =Inputs!AJ28 -> 0.026069089 | DL28: =Inputs!AJ28 -> 0.026069089 | DM28: =Inputs!AJ28 -> 0.026069089 | DN28: =Inputs!AK28 -> 0.022921913 | DO28: =Inputs!AK28 -> 0.022921913 | DP28: =Inputs!AK28 -> 0.022921913 | DQ28: =Inputs!AK28 -> 0.022921913 | DR28: =Inputs!AL28 -> 0.01939121 | DS28: =Inputs!AL28 -> 0.01939121 | DT28: =Inputs!AL28 -> 0.01939121 | DU28: =Inputs!AL28 -> 0.01939121 | DV28: =Inputs!AM28 -> 0.02235396 | DW28: =Inputs!AM28 -> 0.02235396 | DX28: =Inputs!AM28 -> 0.02235396 | DY28: =Inputs!AM28 -> 0.02235396 | DZ28: =Inputs!AN28 -> 0.02 | EA28: =Inputs!AN28 -> 0.02 | EB28: =Inputs!AN28 -> 0.02 | EC28: =Inputs!AN28 -> 0.02 | ED28: =Inputs!AO28 -> 0.02 | EE28: =Inputs!AO28 -> 0.02 | EF28: =Inputs!AO28 -> 0.02 | EG28: =Inputs!AO28 -> 0.02 | EH28: =Inputs!AP28 -> 0.02 | EI28: =Inputs!AP28 -> 0.02 | EJ28: =Inputs!AP28 -> 0.02 | EK28: =Inputs!AP28 -> 0.02 | EL28: =Inputs!AQ28 -> 0.02 | EM28: =Inputs!AP28 -> 0.02 | EN28: =Inputs!AQ28 -> 0.02 | EO28: =Inputs!AQ28 -> 0.02 | EP28: =Inputs!AR28 -> 0.02 | EQ28: =Inputs!AR28 -> 0.02 | ER28: =Inputs!AR28 -> 0.02 | ES28: =Inputs!AR28 -> 0.02 | ET28: =Inputs!AS28 -> 0.02 | EU28: =Inputs!AS28 -> 0.02 | EV28: =Inputs!AS28 -> 0.02 | EW28: =Inputs!AS28 -> 0.02 | EX28: =Inputs!AT28 -> 0.02 | EY28: =Inputs!AT28 -> 0.02 | EZ28: =Inputs!AT28 -> 0.02 | FA28: =Inputs!AT28 -> 0.02 | FB28: =Inputs!AU28 -> 0.02 | FC28: =Inputs!AU28 -> 0.02 | FD28: =Inputs!AU28 -> 0.02 | FE28: =Inputs!AU28 -> 0.02 | FF28: =Inputs!AV28 -> 0.02 | FG28: =Inputs!AV28 -> 0.02 | FH28: =Inputs!AV28 -> 0.02 | FI28: =Inputs!AV28 -> 0.02 | FJ28: =Inputs!AW28 -> 0.02 | FK28: =Inputs!AW28 -> 0.02 | FL28: =Inputs!AW28 -> 0.02 | FM28: =Inputs!AW28 -> 0.02 | FN28: =Inputs!AX28 -> 0.02 | FO28: =Inputs!AX28 -> 0.02 | FP28: =Inputs!AX28 -> 0.02 | FQ28: =Inputs!AX28 -> 0.02 | FR28: =Inputs!AY28 -> 0.02 | FS28: =Inputs!AY28 -> 0.02 | FT28: =Inputs!AY28 -> 0.02 | FU28: =Inputs!AY28 -> 0.02 | FV28: =Inputs!AZ28 -> 0.02 | FW28: =Inputs!AZ28 -> 0.02 | FX28: =Inputs!AZ28 -> 0.02 | FY28: =Inputs!AZ28 -> 0.02 | FZ28: =Inputs!BA28 -> 0.02 | GA28: =Inputs!BA28 -> 0.02 | GB28: =Inputs!BA28 -> 0.02 | GC28: =Inputs!BA28 -> 0.02 | GD28: =Inputs!BB28 -> 0.02 | GE28: =Inputs!BB28 -> 0.02 | GF28: =Inputs!BB28 -> 0.02 | GG28: =Inputs!BB28 -> 0.02 | GH28: =Inputs!BC28 -> 0.02 | GI28: =Inputs!BC28 -> 0.02 | GJ28: =Inputs!BC28 -> 0.02 | GK28: =Inputs!BC28 -> 0.02 | GL28: =Inputs!BD28 -> 0.02 | GM28: =Inputs!BD28 -> 0.02 | GN28: =Inputs!BD28 -> 0.02 | GO28: =Inputs!BD28 -> 0.02 | GP28: =Inputs!BE28 -> 0.02 | GQ28: =Inputs!BE28 -> 0.02 | GR28: =Inputs!BE28 -> 0.02 | GS28: =Inputs!BE28 -> 0.02 | GT28: =Inputs!BF28 -> 0.02 | GU28: =Inputs!BF28 -> 0.02 | GV28: =Inputs!BF28 -> 0.02 | GW28: =Inputs!BF28 -> 0.02 | GX28: =Inputs!BG28 -> 0.02 | GY28: =Inputs!BG28 -> 0.02 | GZ28: =Inputs!BG28 -> 0.02 | HA28: =Inputs!BG28 -> 0.02
A29: Общие | D29: CIB Research | F29: Инфляция - Рост индекса потребительских цен в Еврозоне (EUR, eop CPI) | G29: % | I29: EoY HICP, source: FX/IR team | J29: 0.022 | K29: 0.029 | L29: 0.022 | M29: 0.021 | N29: 0.025 | O29: 0.019 | P29: 0.021 | Q29: 0.023 | R29: 0.024 | S29: 0.02 | T29: 0.021 | U29: 0.02 | V29: 0.017 | W29: 0.024 | X29: 0.021 | Y29: 0.023 | Z29: 0.022 | AA29: 0.02 | AB29: 0.026 | AC29: 0.023 | AD29: 0.022 | AE29: 0.025 | AF29: 0.018 | AG29: 0.019 | AH29: 0.019 | AI29: 0.019 | AJ29: 0.021 | AK29: 0.031 | AL29: 0.036 | AM29: 0.039 | AN29: 0.036 | AO29: 0.016 | AP29: 0.006 | AQ29: -0.001 | AR29: -0.003 | AS29: 0.009 | AT29: 0.016 | AU29: 0.015 | AV29: 0.019 | AW29: 0.022 | AX29: 0.027 | AY29: 0.027 | AZ29: 0.03 | BA29: 0.028 | BB29: 0.027 | BC29: 0.024 | BD29: 0.026 | BE29: 0.022 | BF29: 0.017 | BG29: 0.016 | BH29: 0.011 | BI29: 0.008 | BJ29: 0.005 | BK29: 0.005 | BL29: 0.003 | BM29: -0.002 | BN29: 0.0011846616 | BO29: 0.0042915806 | BP29: 0.00058242169 | BQ29: 0.0044947037 | BR29: -0.00061121524 | BS29: 0.00058550559 | BT29: 0.0041940861 | BU29: 0.011242984 | BV29: 0.01641181 | BW29: 0.011953199 | BX29: 0.015395863 | BY29: 0.01357189 | BZ29: 0.013777072 | CA29: 0.020175714 | CB29: 0.020990694 | CC29: 0.015592772 | CD29: 0.014478233 | CE29: 0.012254474 | CF29: 0.0091263858 | CG29: 0.013479362 | CH29: 0.0078203669 | CI29: 0.0023911136 | CJ29: -0.003116928 | CK29: -0.0026189844 | CL29: 0.012608608 | CM29: 0.020128839 | CN29: 0.034706513 | CO29: 0.050069593 | CP29: 0.074932878 | CQ29: 0.086328075 | CR29: 0.099360615 | CS29: 0.092074037 | CT29: 0.068961838 | CU29: 0.054899984 | CV29: 0.042706096 | CW29: 0.029353964 | CX29: 0.024139392 | CY29: 0.024448382 | CZ29: 0.016710416 | DA29: 0.024256107 | DB29: 0.02160223 | DC29: 0.019968016 | DD29: 0.022620241 | DE29: 0.019664407 | DF29: 0.025336819 | DG29: 0.027328945 | DH29: 0.029231496 | DI29: 0.029057119 | DJ29: 0.01817661 | DK29: 0.015843531 | DL29: 0.016119207 | DM29: 0.019429195 | DN29: 0.021236854 | DO29: 0.020376806 | DP29: 0.021643677 | DQ29: 0.023805054 | DR29: 0.024152761 | DS29: 0.022928544 | DT29: 0.02104899 | DU29: 0.018896804 | DV29: 0.018268754 | DW29: 0.018883613 | DX29: 0.020020567 | DY29: 0.021378704 | DZ29: =Inputs!AN29 -> 0.02 | EA29: =Inputs!AN29 -> 0.02 | EB29: =Inputs!AN29 -> 0.02 | EC29: =Inputs!AN29 -> 0.02 | ED29: =Inputs!AO29 -> 0.02 | EE29: =Inputs!AO29 -> 0.02 | EF29: =Inputs!AO29 -> 0.02 | EG29: =Inputs!AO29 -> 0.02 | EH29: =Inputs!AP29 -> 0.02 | EI29: =Inputs!AP29 -> 0.02 | EJ29: =Inputs!AP29 -> 0.02 | EK29: =Inputs!AP29 -> 0.02 | EL29: =Inputs!AQ29 -> 0.02 | EM29: =Inputs!AP29 -> 0.02 | EN29: =Inputs!AQ29 -> 0.02 | EO29: =Inputs!AQ29 -> 0.02 | EP29: =Inputs!AR29 -> 0.02 | EQ29: =Inputs!AR29 -> 0.02 | ER29: =Inputs!AR29 -> 0.02 | ES29: =Inputs!AR29 -> 0.02 | ET29: =Inputs!AS29 -> 0.02 | EU29: =Inputs!AS29 -> 0.02 | EV29: =Inputs!AS29 -> 0.02 | EW29: =Inputs!AS29 -> 0.02 | EX29: =Inputs!AT29 -> 0.02 | EY29: =Inputs!AT29 -> 0.02 | EZ29: =Inputs!AT29 -> 0.02 | FA29: =Inputs!AT29 -> 0.02 | FB29: =Inputs!AU29 -> 0.02 | FC29: =Inputs!AU29 -> 0.02 | FD29: =Inputs!AU29 -> 0.02 | FE29: =Inputs!AU29 -> 0.02 | FF29: =Inputs!AV29 -> 0.02 | FG29: =Inputs!AV29 -> 0.02 | FH29: =Inputs!AV29 -> 0.02 | FI29: =Inputs!AV29 -> 0.02 | FJ29: =Inputs!AW29 -> 0.02 | FK29: =Inputs!AW29 -> 0.02 | FL29: =Inputs!AW29 -> 0.02 | FM29: =Inputs!AW29 -> 0.02 | FN29: =Inputs!AX29 -> 0.02 | FO29: =Inputs!AX29 -> 0.02 | FP29: =Inputs!AX29 -> 0.02 | FQ29: =Inputs!AX29 -> 0.02 | FR29: =Inputs!AY29 -> 0.02 | FS29: =Inputs!AY29 -> 0.02 | FT29: =Inputs!AY29 -> 0.02 | FU29: =Inputs!AY29 -> 0.02 | FV29: =Inputs!AZ29 -> 0.02 | FW29: =Inputs!AZ29 -> 0.02 | FX29: =Inputs!AZ29 -> 0.02 | FY29: =Inputs!AZ29 -> 0.02 | FZ29: =Inputs!BA29 -> 0.02 | GA29: =Inputs!BA29 -> 0.02 | GB29: =Inputs!BA29 -> 0.02 | GC29: =Inputs!BA29 -> 0.02 | GD29: =Inputs!BB29 -> 0.02 | GE29: =Inputs!BB29 -> 0.02 | GF29: =Inputs!BB29 -> 0.02 | GG29: =Inputs!BB29 -> 0.02 | GH29: =Inputs!BC29 -> 0.02 | GI29: =Inputs!BC29 -> 0.02 | GJ29: =Inputs!BC29 -> 0.02 | GK29: =Inputs!BC29 -> 0.02 | GL29: =Inputs!BD29 -> 0.02 | GM29: =Inputs!BD29 -> 0.02 | GN29: =Inputs!BD29 -> 0.02 | GO29: =Inputs!BD29 -> 0.02 | GP29: =Inputs!BE29 -> 0.02 | GQ29: =Inputs!BE29 -> 0.02 | GR29: =Inputs!BE29 -> 0.02 | GS29: =Inputs!BE29 -> 0.02 | GT29: =Inputs!BF29 -> 0.02 | GU29: =Inputs!BF29 -> 0.02 | GV29: =Inputs!BF29 -> 0.02 | GW29: =Inputs!BF29 -> 0.02 | GX29: =Inputs!BG29 -> 0.02 | GY29: =Inputs!BG29 -> 0.02 | GZ29: =Inputs!BG29 -> 0.02 | HA29: =Inputs!BG29 -> 0.02
A30: Общие | D30: CIB Research | F30: Инфляция - Рост индекса цен производителей в Еврозоне (EUR, eop PPI) | G30: % | I30: =CPI | J30: 0.039 | K30: 0.032 | L30: 0.01 | M30: -0.005 | N30: -0.005 | O30: -0.009 | P30: 0.001 | Q30: 0.015 | R30: 0.024 | S30: 0.013 | T30: 0.01 | U30: 0.009 | V30: 0.002 | W30: 0.025 | X30: 0.033 | Y30: 0.038 | Z30: 0.045 | AA30: 0.042 | AB30: 0.046 | AC30: 0.045 | AD30: 0.054 | AE30: 0.057 | AF30: 0.045 | AG30: 0.038 | AH30: 0.022 | AI30: 0.02 | AJ30: 0.026 | AK30: 0.046 | AL30: 0.058 | AM30: 0.079 | AN30: 0.077 | AO30: 0.014 | AP30: -0.03 | AQ30: -0.063 | AR30: -0.075 | AS30: -0.029 | AT30: 0.007 | AU30: 0.03 | AV30: 0.042 | AW30: 0.05 | AX30: 0.064 | AY30: 0.056 | AZ30: 0.056 | BA30: 0.045 | BB30: 0.034 | BC30: 0.02 | BD30: 0.027 | BE30: 0.02 | BF30: 0.006 | BG30: 0.002 | BH30: -0.009 | BI30: -0.008 | BJ30: -0.017 | BK30: -0.01 | BL30: -0.015 | BM30: -0.027 | BN30: -0.022 | BO30: -0.021 | BP30: -0.031 | BQ30: -0.028 | BR30: -0.039 | BS30: -0.03 | BT30: -0.013 | BU30: 0.015 | BV30: 0.037 | BW30: 0.024 | BX30: 0.026 | BY30: 0.022 | BZ30: 0.02 | CA30: 0.036 | CB30: 0.046 | CC30: 0.031 | CD30: 0.028 | CE30: 0.007 | CF30: -0.012 | CG30: -0.007 | CH30: -0.028 | CI30: -0.037 | CJ30: -0.023 | CK30: -0.011 | CL30: 0.044 | CM30: 0.103 | CN30: 0.161 | CO30: 0.237 | CP30: =CP29 -> 0.074932878 | CQ30: =CQ29 -> 0.086328075 | CR30: =CR29 -> 0.099360615 | CS30: =CS29 -> 0.092074037 | CT30: =Inputs!AF30 -> 0.029353964 | CU30: =Inputs!AF30 -> 0.029353964 | CV30: =Inputs!AF30 -> 0.029353964 | CW30: =Inputs!AF30 -> 0.029353964 | CX30: =Inputs!AG30 -> 0.024563883 | CY30: =Inputs!AG30 -> 0.024563883 | CZ30: =Inputs!AG30 -> 0.024563883 | DA30: =Inputs!AG30 -> 0.024563883 | DB30: =Inputs!AH30 -> 0.019664407 | DC30: =Inputs!AH30 -> 0.019664407 | DD30: =Inputs!AH30 -> 0.019664407 | DE30: =Inputs!AH30 -> 0.019664407 | DF30: =Inputs!AI30 -> 0.029057119 | DG30: =Inputs!AI30 -> 0.029057119 | DH30: =Inputs!AI30 -> 0.029057119 | DI30: =Inputs!AI30 -> 0.029057119 | DJ30: =Inputs!AJ30 -> 0.019429195 | DK30: =Inputs!AJ30 -> 0.019429195 | DL30: =Inputs!AJ30 -> 0.019429195 | DM30: =Inputs!AJ30 -> 0.019429195 | DN30: =Inputs!AK30 -> 0.023805054 | DO30: =Inputs!AK30 -> 0.023805054 | DP30: =Inputs!AK30 -> 0.023805054 | DQ30: =Inputs!AK30 -> 0.023805054 | DR30: =Inputs!AL30 -> 0.018896804 | DS30: =Inputs!AL30 -> 0.018896804 | DT30: =Inputs!AL30 -> 0.018896804 | DU30: =Inputs!AL30 -> 0.018896804 | DV30: =Inputs!AM30 -> 0.021378704 | DW30: =Inputs!AM30 -> 0.021378704 | DX30: =Inputs!AM30 -> 0.021378704 | DY30: =Inputs!AM30 -> 0.021378704 | DZ30: =Inputs!AN30 -> 0.02 | EA30: =Inputs!AN30 -> 0.02 | EB30: =Inputs!AN30 -> 0.02 | EC30: =Inputs!AN30 -> 0.02 | ED30: =Inputs!AO30 -> 0.02 | EE30: =Inputs!AO30 -> 0.02 | EF30: =Inputs!AO30 -> 0.02 | EG30: =Inputs!AO30 -> 0.02 | EH30: =Inputs!AP30 -> 0.02 | EI30: =Inputs!AP30 -> 0.02 | EJ30: =Inputs!AP30 -> 0.02 | EK30: =Inputs!AP30 -> 0.02 | EL30: =Inputs!AQ30 -> 0.02 | EM30: =Inputs!AP30 -> 0.02 | EN30: =Inputs!AQ30 -> 0.02 | EO30: =Inputs!AQ30 -> 0.02 | EP30: =Inputs!AR30 -> 0.02 | EQ30: =Inputs!AR30 -> 0.02 | ER30: =Inputs!AR30 -> 0.02 | ES30: =Inputs!AR30 -> 0.02 | ET30: =Inputs!AS30 -> 0.02 | EU30: =Inputs!AS30 -> 0.02 | EV30: =Inputs!AS30 -> 0.02 | EW30: =Inputs!AS30 -> 0.02 | EX30: =Inputs!AT30 -> 0.02 | EY30: =Inputs!AT30 -> 0.02 | EZ30: =Inputs!AT30 -> 0.02 | FA30: =Inputs!AT30 -> 0.02 | FB30: =Inputs!AU30 -> 0.02 | FC30: =Inputs!AU30 -> 0.02 | FD30: =Inputs!AU30 -> 0.02 | FE30: =Inputs!AU30 -> 0.02 | FF30: =Inputs!AV30 -> 0.02 | FG30: =Inputs!AV30 -> 0.02 | FH30: =Inputs!AV30 -> 0.02 | FI30: =Inputs!AV30 -> 0.02 | FJ30: =Inputs!AW30 -> 0.02 | FK30: =Inputs!AW30 -> 0.02 | FL30: =Inputs!AW30 -> 0.02 | FM30: =Inputs!AW30 -> 0.02 | FN30: =Inputs!AX30 -> 0.02 | FO30: =Inputs!AX30 -> 0.02 | FP30: =Inputs!AX30 -> 0.02 | FQ30: =Inputs!AX30 -> 0.02 | FR30: =Inputs!AY30 -> 0.02 | FS30: =Inputs!AY30 -> 0.02 | FT30: =Inputs!AY30 -> 0.02 | FU30: =Inputs!AY30 -> 0.02 | FV30: =Inputs!AZ30 -> 0.02 | FW30: =Inputs!AZ30 -> 0.02 | FX30: =Inputs!AZ30 -> 0.02 | FY30: =Inputs!AZ30 -> 0.02 | FZ30: =Inputs!BA30 -> 0.02 | GA30: =Inputs!BA30 -> 0.02 | GB30: =Inputs!BA30 -> 0.02 | GC30: =Inputs!BA30 -> 0.02 | GD30: =Inputs!BB30 -> 0.02 | GE30: =Inputs!BB30 -> 0.02 | GF30: =Inputs!BB30 -> 0.02 | GG30: =Inputs!BB30 -> 0.02 | GH30: =Inputs!BC30 -> 0.02 | GI30: =Inputs!BC30 -> 0.02 | GJ30: =Inputs!BC30 -> 0.02 | GK30: =Inputs!BC30 -> 0.02 | GL30: =Inputs!BD30 -> 0.02 | GM30: =Inputs!BD30 -> 0.02 | GN30: =Inputs!BD30 -> 0.02 | GO30: =Inputs!BD30 -> 0.02 | GP30: =Inputs!BE30 -> 0.02 | GQ30: =Inputs!BE30 -> 0.02 | GR30: =Inputs!BE30 -> 0.02 | GS30: =Inputs!BE30 -> 0.02 | GT30: =Inputs!BF30 -> 0.02 | GU30: =Inputs!BF30 -> 0.02 | GV30: =Inputs!BF30 -> 0.02 | GW30: =Inputs!BF30 -> 0.02 | GX30: =Inputs!BG30 -> 0.02 | GY30: =Inputs!BG30 -> 0.02 | GZ30: =Inputs!BG30 -> 0.02 | HA30: =Inputs!BG30 -> 0.02
A31: Общие | D31: Законодательство | F31: Ставка страхового взноса в ФОМС | G31: % | I31: Не меняется | BJ31: 0.051 | BK31: 0.051 | BL31: 0.051 | BM31: 0.051 | BN31: 0.051 | BO31: 0.051 | BP31: 0.051 | BQ31: 0.051 | BR31: 0.051 | BS31: 0.051 | BT31: 0.051 | BU31: 0.051 | BV31: 0.051 | BW31: 0.051 | BX31: 0.051 | BY31: 0.051 | BZ31: 0.051 | CA31: 0.051 | CB31: 0.051 | CC31: 0.051 | CD31: 0.051 | CE31: 0.051 | CF31: 0.051 | CG31: 0.051 | CH31: 0.051 | CI31: 0.051 | CJ31: 0.051 | CK31: 0.051 | CL31: =Inputs!AD31 -> 0.051 | CM31: =Inputs!AD31 -> 0.051 | CN31: =Inputs!AD31 -> 0.051 | CO31: =Inputs!AD31 -> 0.051 | CP31: =Inputs!AE31 -> 0.051 | CQ31: =Inputs!AE31 -> 0.051 | CR31: =Inputs!AE31 -> 0.051 | CS31: =Inputs!AE31 -> 0.051 | CT31: =Inputs!AF31 -> 0.051 | CU31: =Inputs!AF31 -> 0.051 | CV31: =Inputs!AF31 -> 0.051 | CW31: =Inputs!AF31 -> 0.051 | CX31: =Inputs!AG31 -> 0.051 | CY31: =Inputs!AG31 -> 0.051 | CZ31: =Inputs!AG31 -> 0.051 | DA31: =Inputs!AG31 -> 0.051 | DB31: =Inputs!AH31 -> 0.051 | DC31: =Inputs!AH31 -> 0.051 | DD31: =Inputs!AH31 -> 0.051 | DE31: =Inputs!AH31 -> 0.051 | DF31: =Inputs!AI31 -> 0.051 | DG31: =Inputs!AI31 -> 0.051 | DH31: =Inputs!AI31 -> 0.051 | DI31: =Inputs!AI31 -> 0.051 | DJ31: =Inputs!AJ31 -> 0.051 | DK31: =Inputs!AJ31 -> 0.051 | DL31: =Inputs!AJ31 -> 0.051 | DM31: =Inputs!AJ31 -> 0.051 | DN31: =Inputs!AK31 -> 0.051 | DO31: =Inputs!AK31 -> 0.051 | DP31: =Inputs!AK31 -> 0.051 | DQ31: =Inputs!AK31 -> 0.051 | DR31: =Inputs!AL31 -> 0.051 | DS31: =Inputs!AL31 -> 0.051 | DT31: =Inputs!AL31 -> 0.051 | DU31: =Inputs!AL31 -> 0.051 | DV31: =Inputs!AM31 -> 0.051 | DW31: =Inputs!AM31 -> 0.051 | DX31: =Inputs!AM31 -> 0.051 | DY31: =Inputs!AM31 -> 0.051 | DZ31: =Inputs!AN31 -> 0.051 | EA31: =Inputs!AN31 -> 0.051 | EB31: =Inputs!AN31 -> 0.051 | EC31: =Inputs!AN31 -> 0.051 | ED31: =Inputs!AO31 -> 0.051 | EE31: =Inputs!AO31 -> 0.051 | EF31: =Inputs!AO31 -> 0.051 | EG31: =Inputs!AO31 -> 0.051 | EH31: =Inputs!AP31 -> 0.051 | EI31: =Inputs!AP31 -> 0.051 | EJ31: =Inputs!AP31 -> 0.051 | EK31: =Inputs!AP31 -> 0.051 | EL31: =Inputs!AQ31 -> 0.051 | EM31: =Inputs!AP31 -> 0.051 | EN31: =Inputs!AQ31 -> 0.051 | EO31: =Inputs!AQ31 -> 0.051 | EP31: =Inputs!AR31 -> 0.051 | EQ31: =Inputs!AR31 -> 0.051 | ER31: =Inputs!AR31 -> 0.051 | ES31: =Inputs!AR31 -> 0.051 | ET31: =Inputs!AS31 -> 0.051 | EU31: =Inputs!AS31 -> 0.051 | EV31: =Inputs!AS31 -> 0.051 | EW31: =Inputs!AS31 -> 0.051 | EX31: =Inputs!AT31 -> 0.051 | EY31: =Inputs!AT31 -> 0.051 | EZ31: =Inputs!AT31 -> 0.051 | FA31: =Inputs!AT31 -> 0.051 | FB31: =Inputs!AU31 -> 0.051 | FC31: =Inputs!AU31 -> 0.051 | FD31: =Inputs!AU31 -> 0.051 | FE31: =Inputs!AU31 -> 0.051 | FF31: =Inputs!AV31 -> 0.051 | FG31: =Inputs!AV31 -> 0.051 | FH31: =Inputs!AV31 -> 0.051 | FI31: =Inputs!AV31 -> 0.051 | FJ31: =Inputs!AW31 -> 0.051 | FK31: =Inputs!AW31 -> 0.051 | FL31: =Inputs!AW31 -> 0.051 | FM31: =Inputs!AW31 -> 0.051 | FN31: =Inputs!AX31 -> 0.051 | FO31: =Inputs!AX31 -> 0.051 | FP31: =Inputs!AX31 -> 0.051 | FQ31: =Inputs!AX31 -> 0.051 | FR31: =Inputs!AY31 -> 0.051 | FS31: =Inputs!AY31 -> 0.051 | FT31: =Inputs!AY31 -> 0.051 | FU31: =Inputs!AY31 -> 0.051 | FV31: =Inputs!AZ31 -> 0.051 | FW31: =Inputs!AZ31 -> 0.051 | FX31: =Inputs!AZ31 -> 0.051 | FY31: =Inputs!AZ31 -> 0.051 | FZ31: =Inputs!BA31 -> 0.051 | GA31: =Inputs!BA31 -> 0.051 | GB31: =Inputs!BA31 -> 0.051 | GC31: =Inputs!BA31 -> 0.051 | GD31: =Inputs!BB31 -> 0.051 | GE31: =Inputs!BB31 -> 0.051 | GF31: =Inputs!BB31 -> 0.051 | GG31: =Inputs!BB31 -> 0.051 | GH31: =Inputs!BC31 -> 0.051 | GI31: =Inputs!BC31 -> 0.051 | GJ31: =Inputs!BC31 -> 0.051 | GK31: =Inputs!BC31 -> 0.051 | GL31: =Inputs!BD31 -> 0.051 | GM31: =Inputs!BD31 -> 0.051 | GN31: =Inputs!BD31 -> 0.051 | GO31: =Inputs!BD31 -> 0.051 | GP31: =Inputs!BE31 -> 0.051 | GQ31: =Inputs!BE31 -> 0.051 | GR31: =Inputs!BE31 -> 0.051 | GS31: =Inputs!BE31 -> 0.051 | GT31: =Inputs!BF31 -> 0.051 | GU31: =Inputs!BF31 -> 0.051 | GV31: =Inputs!BF31 -> 0.051 | GW31: =Inputs!BF31 -> 0.051 | GX31: =Inputs!BG31 -> 0.051 | GY31: =Inputs!BG31 -> 0.051 | GZ31: =Inputs!BG31 -> 0.051 | HA31: =Inputs!BG31 -> 0.051
A32: Общие | D32: Законодательство | F32: Ставка страхового взноса в ФСС | G32: % | I32: Не меняется | BJ32: 0.029 | BK32: 0.029 | BL32: 0.029 | BM32: 0.029 | BN32: 0.029 | BO32: 0.029 | BP32: 0.029 | BQ32: 0.029 | BR32: 0.029 | BS32: 0.029 | BT32: 0.029 | BU32: 0.029 | BV32: 0.029 | BW32: 0.029 | BX32: 0.029 | BY32: 0.029 | BZ32: 0.029 | CA32: 0.029 | CB32: 0.029 | CC32: 0.029 | CD32: 0.029 | CE32: 0.029 | CF32: 0.029 | CG32: 0.029 | CH32: 0.029 | CI32: 0.029 | CJ32: 0.029 | CK32: 0.029 | CL32: =Inputs!AD32 -> 0.029 | CM32: =Inputs!AD32 -> 0.029 | CN32: =Inputs!AD32 -> 0.029 | CO32: =Inputs!AD32 -> 0.029 | CP32: =Inputs!AE32 -> 0.029 | CQ32: =Inputs!AE32 -> 0.029 | CR32: =Inputs!AE32 -> 0.029 | CS32: =Inputs!AE32 -> 0.029 | CT32: =Inputs!AF32 -> 0.029 | CU32: =Inputs!AF32 -> 0.029 | CV32: =Inputs!AF32 -> 0.029 | CW32: =Inputs!AF32 -> 0.029 | CX32: =Inputs!AG32 -> 0.029 | CY32: =Inputs!AG32 -> 0.029 | CZ32: =Inputs!AG32 -> 0.029 | DA32: =Inputs!AG32 -> 0.029 | DB32: =Inputs!AH32 -> 0.029 | DC32: =Inputs!AH32 -> 0.029 | DD32: =Inputs!AH32 -> 0.029 | DE32: =Inputs!AH32 -> 0.029 | DF32: =Inputs!AI32 -> 0.029 | DG32: =Inputs!AI32 -> 0.029 | DH32: =Inputs!AI32 -> 0.029 | DI32: =Inputs!AI32 -> 0.029 | DJ32: =Inputs!AJ32 -> 0.029 | DK32: =Inputs!AJ32 -> 0.029 | DL32: =Inputs!AJ32 -> 0.029 | DM32: =Inputs!AJ32 -> 0.029 | DN32: =Inputs!AK32 -> 0.029 | DO32: =Inputs!AK32 -> 0.029 | DP32: =Inputs!AK32 -> 0.029 | DQ32: =Inputs!AK32 -> 0.029 | DR32: =Inputs!AL32 -> 0.029 | DS32: =Inputs!AL32 -> 0.029 | DT32: =Inputs!AL32 -> 0.029 | DU32: =Inputs!AL32 -> 0.029 | DV32: =Inputs!AM32 -> 0.029 | DW32: =Inputs!AM32 -> 0.029 | DX32: =Inputs!AM32 -> 0.029 | DY32: =Inputs!AM32 -> 0.029 | DZ32: =Inputs!AN32 -> 0.029 | EA32: =Inputs!AN32 -> 0.029 | EB32: =Inputs!AN32 -> 0.029 | EC32: =Inputs!AN32 -> 0.029 | ED32: =Inputs!AO32 -> 0.029 | EE32: =Inputs!AO32 -> 0.029 | EF32: =Inputs!AO32 -> 0.029 | EG32: =Inputs!AO32 -> 0.029 | EH32: =Inputs!AP32 -> 0.029 | EI32: =Inputs!AP32 -> 0.029 | EJ32: =Inputs!AP32 -> 0.029 | EK32: =Inputs!AP32 -> 0.029 | EL32: =Inputs!AQ32 -> 0.029 | EM32: =Inputs!AP32 -> 0.029 | EN32: =Inputs!AQ32 -> 0.029 | EO32: =Inputs!AQ32 -> 0.029 | EP32: =Inputs!AR32 -> 0.029 | EQ32: =Inputs!AR32 -> 0.029 | ER32: =Inputs!AR32 -> 0.029 | ES32: =Inputs!AR32 -> 0.029 | ET32: =Inputs!AS32 -> 0.029 | EU32: =Inputs!AS32 -> 0.029 | EV32: =Inputs!AS32 -> 0.029 | EW32: =Inputs!AS32 -> 0.029 | EX32: =Inputs!AT32 -> 0.029 | EY32: =Inputs!AT32 -> 0.029 | EZ32: =Inputs!AT32 -> 0.029 | FA32: =Inputs!AT32 -> 0.029 | FB32: =Inputs!AU32 -> 0.029 | FC32: =Inputs!AU32 -> 0.029 | FD32: =Inputs!AU32 -> 0.029 | FE32: =Inputs!AU32 -> 0.029 | FF32: =Inputs!AV32 -> 0.029 | FG32: =Inputs!AV32 -> 0.029 | FH32: =Inputs!AV32 -> 0.029 | FI32: =Inputs!AV32 -> 0.029 | FJ32: =Inputs!AW32 -> 0.029 | FK32: =Inputs!AW32 -> 0.029 | FL32: =Inputs!AW32 -> 0.029 | FM32: =Inputs!AW32 -> 0.029 | FN32: =Inputs!AX32 -> 0.029 | FO32: =Inputs!AX32 -> 0.029 | FP32: =Inputs!AX32 -> 0.029 | FQ32: =Inputs!AX32 -> 0.029 | FR32: =Inputs!AY32 -> 0.029 | FS32: =Inputs!AY32 -> 0.029 | FT32: =Inputs!AY32 -> 0.029 | FU32: =Inputs!AY32 -> 0.029 | FV32: =Inputs!AZ32 -> 0.029 | FW32: =Inputs!AZ32 -> 0.029 | FX32: =Inputs!AZ32 -> 0.029 | FY32: =Inputs!AZ32 -> 0.029 | FZ32: =Inputs!BA32 -> 0.029 | GA32: =Inputs!BA32 -> 0.029 | GB32: =Inputs!BA32 -> 0.029 | GC32: =Inputs!BA32 -> 0.029 | GD32: =Inputs!BB32 -> 0.029 | GE32: =Inputs!BB32 -> 0.029 | GF32: =Inputs!BB32 -> 0.029 | GG32: =Inputs!BB32 -> 0.029 | GH32: =Inputs!BC32 -> 0.029 | GI32: =Inputs!BC32 -> 0.029 | GJ32: =Inputs!BC32 -> 0.029 | GK32: =Inputs!BC32 -> 0.029 | GL32: =Inputs!BD32 -> 0.029 | GM32: =Inputs!BD32 -> 0.029 | GN32: =Inputs!BD32 -> 0.029 | GO32: =Inputs!BD32 -> 0.029 | GP32: =Inputs!BE32 -> 0.029 | GQ32: =Inputs!BE32 -> 0.029 | GR32: =Inputs!BE32 -> 0.029 | GS32: =Inputs!BE32 -> 0.029 | GT32: =Inputs!BF32 -> 0.029 | GU32: =Inputs!BF32 -> 0.029 | GV32: =Inputs!BF32 -> 0.029 | GW32: =Inputs!BF32 -> 0.029 | GX32: =Inputs!BG32 -> 0.029 | GY32: =Inputs!BG32 -> 0.029 | GZ32: =Inputs!BG32 -> 0.029 | HA32: =Inputs!BG32 -> 0.029
A33: Общие | D33: Законодательство | F33: Ставка страхового взноса в ПФР | G33: % | I33: Не меняется | BJ33: 0.22 | BK33: 0.22 | BL33: 0.22 | BM33: 0.22 | BN33: 0.22 | BO33: 0.22 | BP33: 0.22 | BQ33: 0.22 | BR33: 0.22 | BS33: 0.22 | BT33: 0.22 | BU33: 0.22 | BV33: 0.22 | BW33: 0.22 | BX33: 0.22 | BY33: 0.22 | BZ33: 0.22 | CA33: 0.22 | CB33: 0.22 | CC33: 0.22 | CD33: 0.22 | CE33: 0.22 | CF33: 0.22 | CG33: 0.22 | CH33: 0.22 | CI33: 0.22 | CJ33: 0.22 | CK33: 0.22 | CL33: =Inputs!AD33 -> 0.22 | CM33: =Inputs!AD33 -> 0.22 | CN33: =Inputs!AD33 -> 0.22 | CO33: =Inputs!AD33 -> 0.22 | CP33: =Inputs!AE33 -> 0.22 | CQ33: =Inputs!AE33 -> 0.22 | CR33: =Inputs!AE33 -> 0.22 | CS33: =Inputs!AE33 -> 0.22 | CT33: =Inputs!AF33 -> 0.22 | CU33: =Inputs!AF33 -> 0.22 | CV33: =Inputs!AF33 -> 0.22 | CW33: =Inputs!AF33 -> 0.22 | CX33: =Inputs!AG33 -> 0.22 | CY33: =Inputs!AG33 -> 0.22 | CZ33: =Inputs!AG33 -> 0.22 | DA33: =Inputs!AG33 -> 0.22 | DB33: =Inputs!AH33 -> 0.22 | DC33: =Inputs!AH33 -> 0.22 | DD33: =Inputs!AH33 -> 0.22 | DE33: =Inputs!AH33 -> 0.22 | DF33: =Inputs!AI33 -> 0.22 | DG33: =Inputs!AI33 -> 0.22 | DH33: =Inputs!AI33 -> 0.22 | DI33: =Inputs!AI33 -> 0.22 | DJ33: =Inputs!AJ33 -> 0.22 | DK33: =Inputs!AJ33 -> 0.22 | DL33: =Inputs!AJ33 -> 0.22 | DM33: =Inputs!AJ33 -> 0.22 | DN33: =Inputs!AK33 -> 0.22 | DO33: =Inputs!AK33 -> 0.22 | DP33: =Inputs!AK33 -> 0.22 | DQ33: =Inputs!AK33 -> 0.22 | DR33: =Inputs!AL33 -> 0.22 | DS33: =Inputs!AL33 -> 0.22 | DT33: =Inputs!AL33 -> 0.22 | DU33: =Inputs!AL33 -> 0.22 | DV33: =Inputs!AM33 -> 0.22 | DW33: =Inputs!AM33 -> 0.22 | DX33: =Inputs!AM33 -> 0.22 | DY33: =Inputs!AM33 -> 0.22 | DZ33: =Inputs!AN33 -> 0.22 | EA33: =Inputs!AN33 -> 0.22 | EB33: =Inputs!AN33 -> 0.22 | EC33: =Inputs!AN33 -> 0.22 | ED33: =Inputs!AO33 -> 0.22 | EE33: =Inputs!AO33 -> 0.22 | EF33: =Inputs!AO33 -> 0.22 | EG33: =Inputs!AO33 -> 0.22 | EH33: =Inputs!AP33 -> 0.22 | EI33: =Inputs!AP33 -> 0.22 | EJ33: =Inputs!AP33 -> 0.22 | EK33: =Inputs!AP33 -> 0.22 | EL33: =Inputs!AQ33 -> 0.22 | EM33: =Inputs!AP33 -> 0.22 | EN33: =Inputs!AQ33 -> 0.22 | EO33: =Inputs!AQ33 -> 0.22 | EP33: =Inputs!AR33 -> 0.22 | EQ33: =Inputs!AR33 -> 0.22 | ER33: =Inputs!AR33 -> 0.22 | ES33: =Inputs!AR33 -> 0.22 | ET33: =Inputs!AS33 -> 0.22 | EU33: =Inputs!AS33 -> 0.22 | EV33: =Inputs!AS33 -> 0.22 | EW33: =Inputs!AS33 -> 0.22 | EX33: =Inputs!AT33 -> 0.22 | EY33: =Inputs!AT33 -> 0.22 | EZ33: =Inputs!AT33 -> 0.22 | FA33: =Inputs!AT33 -> 0.22 | FB33: =Inputs!AU33 -> 0.22 | FC33: =Inputs!AU33 -> 0.22 | FD33: =Inputs!AU33 -> 0.22 | FE33: =Inputs!AU33 -> 0.22 | FF33: =Inputs!AV33 -> 0.22 | FG33: =Inputs!AV33 -> 0.22 | FH33: =Inputs!AV33 -> 0.22 | FI33: =Inputs!AV33 -> 0.22 | FJ33: =Inputs!AW33 -> 0.22 | FK33: =Inputs!AW33 -> 0.22 | FL33: =Inputs!AW33 -> 0.22 | FM33: =Inputs!AW33 -> 0.22 | FN33: =Inputs!AX33 -> 0.22 | FO33: =Inputs!AX33 -> 0.22 | FP33: =Inputs!AX33 -> 0.22 | FQ33: =Inputs!AX33 -> 0.22 | FR33: =Inputs!AY33 -> 0.22 | FS33: =Inputs!AY33 -> 0.22 | FT33: =Inputs!AY33 -> 0.22 | FU33: =Inputs!AY33 -> 0.22 | FV33: =Inputs!AZ33 -> 0.22 | FW33: =Inputs!AZ33 -> 0.22 | FX33: =Inputs!AZ33 -> 0.22 | FY33: =Inputs!AZ33 -> 0.22 | FZ33: =Inputs!BA33 -> 0.22 | GA33: =Inputs!BA33 -> 0.22 | GB33: =Inputs!BA33 -> 0.22 | GC33: =Inputs!BA33 -> 0.22 | GD33: =Inputs!BB33 -> 0.22 | GE33: =Inputs!BB33 -> 0.22 | GF33: =Inputs!BB33 -> 0.22 | GG33: =Inputs!BB33 -> 0.22 | GH33: =Inputs!BC33 -> 0.22 | GI33: =Inputs!BC33 -> 0.22 | GJ33: =Inputs!BC33 -> 0.22 | GK33: =Inputs!BC33 -> 0.22 | GL33: =Inputs!BD33 -> 0.22 | GM33: =Inputs!BD33 -> 0.22 | GN33: =Inputs!BD33 -> 0.22 | GO33: =Inputs!BD33 -> 0.22 | GP33: =Inputs!BE33 -> 0.22 | GQ33: =Inputs!BE33 -> 0.22 | GR33: =Inputs!BE33 -> 0.22 | GS33: =Inputs!BE33 -> 0.22 | GT33: =Inputs!BF33 -> 0.22 | GU33: =Inputs!BF33 -> 0.22 | GV33: =Inputs!BF33 -> 0.22 | GW33: =Inputs!BF33 -> 0.22 | GX33: =Inputs!BG33 -> 0.22 | GY33: =Inputs!BG33 -> 0.22 | GZ33: =Inputs!BG33 -> 0.22 | HA33: =Inputs!BG33 -> 0.22
A34: Общие | D34: Законодательство | F34: Ставка налога на прибыль организаций | G34: % | I34: Не меняется | BJ34: 0.2 | BK34: 0.2 | BL34: 0.2 | BM34: 0.2 | BN34: 0.2 | BO34: 0.2 | BP34: 0.2 | BQ34: 0.2 | BR34: 0.2 | BS34: 0.2 | BT34: 0.2 | BU34: 0.2 | BV34: 0.2 | BW34: 0.2 | BX34: 0.2 | BY34: 0.2 | BZ34: 0.2 | CA34: 0.2 | CB34: 0.2 | CC34: 0.2 | CD34: 0.2 | CE34: 0.2 | CF34: 0.2 | CG34: 0.2 | CH34: 0.2 | CI34: 0.2 | CJ34: 0.2 | CK34: 0.2 | CL34: =Inputs!AD34 -> 0.2 | CM34: =Inputs!AD34 -> 0.2 | CN34: =Inputs!AD34 -> 0.2 | CO34: =Inputs!AD34 -> 0.2 | CP34: =Inputs!AE34 -> 0.2 | CQ34: =Inputs!AE34 -> 0.2 | CR34: =Inputs!AE34 -> 0.2 | CS34: =Inputs!AE34 -> 0.2 | CT34: =Inputs!AF34 -> 0.2 | CU34: =Inputs!AF34 -> 0.2 | CV34: =Inputs!AF34 -> 0.2 | CW34: =Inputs!AF34 -> 0.2 | CX34: =Inputs!AG34 -> 0.2 | CY34: =Inputs!AG34 -> 0.2 | CZ34: =Inputs!AG34 -> 0.2 | DA34: =Inputs!AG34 -> 0.2 | DB34: =Inputs!AH34 -> 0.25 | DC34: =Inputs!AH34 -> 0.25 | DD34: =Inputs!AH34 -> 0.25 | DE34: =Inputs!AH34 -> 0.25 | DF34: =Inputs!AI34 -> 0.25 | DG34: =Inputs!AI34 -> 0.25 | DH34: =Inputs!AI34 -> 0.25 | DI34: =Inputs!AI34 -> 0.25 | DJ34: =Inputs!AJ34 -> 0.25 | DK34: =Inputs!AJ34 -> 0.25 | DL34: =Inputs!AJ34 -> 0.25 | DM34: =Inputs!AJ34 -> 0.25 | DN34: =Inputs!AK34 -> 0.25 | DO34: =Inputs!AK34 -> 0.25 | DP34: =Inputs!AK34 -> 0.25 | DQ34: =Inputs!AK34 -> 0.25 | DR34: =Inputs!AL34 -> 0.25 | DS34: =Inputs!AL34 -> 0.25 | DT34: =Inputs!AL34 -> 0.25 | DU34: =Inputs!AL34 -> 0.25 | DV34: =Inputs!AM34 -> 0.25 | DW34: =Inputs!AM34 -> 0.25 | DX34: =Inputs!AM34 -> 0.25 | DY34: =Inputs!AM34 -> 0.25 | DZ34: =Inputs!AN34 -> 0.25 | EA34: =Inputs!AN34 -> 0.25 | EB34: =Inputs!AN34 -> 0.25 | EC34: =Inputs!AN34 -> 0.25 | ED34: =Inputs!AO34 -> 0.25 | EE34: =Inputs!AO34 -> 0.25 | EF34: =Inputs!AO34 -> 0.25 | EG34: =Inputs!AO34 -> 0.25 | EH34: =Inputs!AP34 -> 0.25 | EI34: =Inputs!AP34 -> 0.25 | EJ34: =Inputs!AP34 -> 0.25 | EK34: =Inputs!AP34 -> 0.25 | EL34: =Inputs!AQ34 -> 0.25 | EM34: =Inputs!AP34 -> 0.25 | EN34: =Inputs!AQ34 -> 0.25 | EO34: =Inputs!AQ34 -> 0.25 | EP34: =Inputs!AR34 -> 0.25 | EQ34: =Inputs!AR34 -> 0.25 | ER34: =Inputs!AR34 -> 0.25 | ES34: =Inputs!AR34 -> 0.25 | ET34: =Inputs!AS34 -> 0.25 | EU34: =Inputs!AS34 -> 0.25 | EV34: =Inputs!AS34 -> 0.25 | EW34: =Inputs!AS34 -> 0.25 | EX34: =Inputs!AT34 -> 0.25 | EY34: =Inputs!AT34 -> 0.25 | EZ34: =Inputs!AT34 -> 0.25 | FA34: =Inputs!AT34 -> 0.25 | FB34: =Inputs!AU34 -> 0.25 | FC34: =Inputs!AU34 -> 0.25 | FD34: =Inputs!AU34 -> 0.25 | FE34: =Inputs!AU34 -> 0.25 | FF34: =Inputs!AV34 -> 0.25 | FG34: =Inputs!AV34 -> 0.25 | FH34: =Inputs!AV34 -> 0.25 | FI34: =Inputs!AV34 -> 0.25 | FJ34: =Inputs!AW34 -> 0.25 | FK34: =Inputs!AW34 -> 0.25 | FL34: =Inputs!AW34 -> 0.25 | FM34: =Inputs!AW34 -> 0.25 | FN34: =Inputs!AX34 -> 0.25 | FO34: =Inputs!AX34 -> 0.25 | FP34: =Inputs!AX34 -> 0.25 | FQ34: =Inputs!AX34 -> 0.25 | FR34: =Inputs!AY34 -> 0.25 | FS34: =Inputs!AY34 -> 0.25 | FT34: =Inputs!AY34 -> 0.25 | FU34: =Inputs!AY34 -> 0.25 | FV34: =Inputs!AZ34 -> 0.25 | FW34: =Inputs!AZ34 -> 0.25 | FX34: =Inputs!AZ34 -> 0.25 | FY34: =Inputs!AZ34 -> 0.25 | FZ34: =Inputs!BA34 -> 0.25 | GA34: =Inputs!BA34 -> 0.25 | GB34: =Inputs!BA34 -> 0.25 | GC34: =Inputs!BA34 -> 0.25 | GD34: =Inputs!BB34 -> 0.25 | GE34: =Inputs!BB34 -> 0.25 | GF34: =Inputs!BB34 -> 0.25 | GG34: =Inputs!BB34 -> 0.25 | GH34: =Inputs!BC34 -> 0.25 | GI34: =Inputs!BC34 -> 0.25 | GJ34: =Inputs!BC34 -> 0.25 | GK34: =Inputs!BC34 -> 0.25 | GL34: =Inputs!BD34 -> 0.25 | GM34: =Inputs!BD34 -> 0.25 | GN34: =Inputs!BD34 -> 0.25 | GO34: =Inputs!BD34 -> 0.25 | GP34: =Inputs!BE34 -> 0.25 | GQ34: =Inputs!BE34 -> 0.25 | GR34: =Inputs!BE34 -> 0.25 | GS34: =Inputs!BE34 -> 0.25 | GT34: =Inputs!BF34 -> 0.25 | GU34: =Inputs!BF34 -> 0.25 | GV34: =Inputs!BF34 -> 0.25 | GW34: =Inputs!BF34 -> 0.25 | GX34: =Inputs!BG34 -> 0.25 | GY34: =Inputs!BG34 -> 0.25 | GZ34: =Inputs!BG34 -> 0.25 | HA34: =Inputs!BG34 -> 0.25
A35: Общие | D35: ЦМИ | F35: Средний за период курс EUR к доллару США (av EUR/USD) | G35: EUR/$ | I35: 2017-21 ЦМИ | J35: 0.9231 | K35: 0.874 | L35: 0.8917 | M35: 0.8955 | N35: 0.8772 | O35: 0.9193 | P35: 0.9841 | Q35: 1.0014 | R35: 1.073 | S35: 1.1371 | T35: 1.1265 | U35: 1.1919 | V35: 1.2494 | W35: 1.2056 | X35: 1.2228 | Y35: 1.299 | Z35: 1.3107 | AA35: 1.259 | AB35: 1.2202 | AC35: 1.1893 | AD35: 1.2034 | AE35: 1.2584 | AF35: 1.2746 | AG35: 1.29 | AH35: 1.3111 | AI35: 1.3483 | AJ35: 1.3746 | AK35: 1.4484 | AL35: 1.4992 | AM35: 1.5632 | AN35: 1.504 | AO35: 1.3202 | AP35: 1.3063 | AQ35: 1.363 | AR35: 1.4302 | AS35: 1.4766 | AT35: 1.3837 | AU35: 1.2728 | AV35: 1.2931 | AW35: 1.3579 | AX35: 1.3696 | AY35: 1.4398 | AZ35: 1.4129 | BA35: 1.3473 | BB35: 1.3119 | BC35: 1.2832 | BD35: 1.2511 | BE35: 1.2976 | BF35: 1.32 | BG35: 1.3062 | BH35: 1.3254 | BI35: 1.3615 | BJ35: 1.3704 | BK35: 1.3716 | BL35: 1.3252 | BM35: 1.2488 | BN35: 1.1268 | BO35: 1.1069 | BP35: 1.1125 | BQ35: 1.0952 | BR35: 1.1041 | BS35: 1.1292 | BT35: 1.1163 | BU35: 1.0779 | BV35: 1.0654 | BW35: 1.1013 | BX35: 1.1754 | BY35: 1.1778 | BZ35: 1.2288 | CA35: 1.1916 | CB35: 1.1629 | CC35: 1.1408 | CD35: 1.1357 | CE35: 1.1234 | CF35: 1.1118 | CG35: 1.1073 | CH35: 1.1031634 | CI35: 1.1013628 | CJ35: 1.1683457 | CK35: 1.1917445 | CL35: 1.2067722 | CM35: 1.2044764 | CN35: 1.1794333 | CO35: 1.1443822 | CP35: 1.12283 | CQ35: 1.0601717 | CR35: 1.0063622 | CS35: 1.0179514 | CT35: 1.0739513 | CU35: 1.0897272 | CV35: 1.0888105 | CW35: 1.0755806 | CX35: 1.0867137 | CY35: 1.0769416 | CZ35: 1.0984104 | DA35: 1.070281 | DB35: 1.0529806 | DC35: 1.1356524 | DD35: 1.1695209 | DE35: 1.1645012 | DF35: 1.1708362 | DG35: 1.1631551 | DH35: 1.1554134 | DI35: 1.1623083 | DJ35: 1.1580635 | DK35: 1.1547454 | DL35: 1.1522465 | DM35: 1.1505784 | DN35: 1.1496825 | DO35: 1.1494167 | DP35: 1.1495509 | DQ35: 1.1498513 | DR35: 1.1500936 | DS35: 1.1501844 | DT35: 1.1501583 | DU35: 1.1500609 | DV35: 1.1499403 | DW35: 1.1498432 | DX35: 1.1498151 | DY35: 1.149905 | DZ35: =DY35 -> 1.149905 | EA35: =DZ35 -> 1.149905 | EB35: =EA35 -> 1.149905 | EC35: =EB35 -> 1.149905 | ED35: =EC35 -> 1.149905 | EE35: =ED35 -> 1.149905 | EF35: =EE35 -> 1.149905 | EG35: =EF35 -> 1.149905 | ... HA35: =GZ35 -> 1.149905
A36: Общие | D36: Расчет | F36: Курс EUR к доллару США в конце года (eop EUR/USD) | G36: EUR/$ | J36: 0.8767 | K36: 0.849 | L36: 0.9114 | M36: 0.8895 | N36: 0.8717 | O36: 0.9914 | P36: 0.9866 | Q36: 1.0492 | R36: 1.0915 | S36: 1.1511 | T36: 1.1656 | U36: 1.2595 | V36: 1.2316 | W36: 1.2199 | X36: 1.2436 | Y36: 1.3554 | Z36: 1.2964 | AA36: 1.2108 | AB36: 1.2026 | AC36: 1.1849 | AD36: 1.2118 | AE36: 1.279 | AF36: 1.2674 | AG36: 1.3199 | AH36: 1.3354 | AI36: 1.3542 | AJ36: 1.4267 | AK36: 1.459 | AL36: 1.5788 | AM36: 1.5755 | AN36: 1.4093 | AO36: 1.3973 | AP36: 1.3252 | AQ36: 1.4033 | AR36: 1.4638 | AS36: 1.4326 | AT36: 1.3509 | AU36: 1.2237 | AV36: 1.3633 | AW36: 1.3387 | AX36: 1.4158 | AY36: 1.4502 | AZ36: 1.3388 | BA36: 1.2959 | BB36: 1.3344 | BC36: 1.2666 | BD36: 1.2859 | BE36: 1.3192 | BF36: 1.2819 | BG36: 1.301 | BH36: 1.3527 | BI36: 1.3743 | BJ36: 1.377 | BK36: 1.3692 | BL36: 1.2631 | BM36: 1.2098 | BN36: 1.0731 | BO36: 1.1147 | BP36: 1.1177 | BQ36: 1.0856 | BR36: 1.138 | BS36: 1.1103 | BT36: 1.124 | BU36: 1.052 | BV36: 1.0653 | BW36: 1.1426 | BX36: 1.1814 | BY36: 1.2005 | BZ36: 1.2324 | CA36: 1.1683 | CB36: 1.1604 | CC36: 1.1469 | CD36: 1.1217 | CE36: 1.1368 | CF36: 1.09 | CG36: 1.1214 | CH36: 1.1031 | CI36: 1.1234 | CJ36: 1.1721 | CK36: 1.2217 | CL36: 1.173 | CM36: 1.1858 | CN36: 1.158 | CO36: =Inputs!AD36 -> 1.137 | CP36: 1.1141023 | CQ36: 1.0527777 | CR36: 0.96511243 | CS36: =Inputs!AE36 -> 1.0702 | CT36: 1.0865222 | CU36: 1.0928415 | CV36: 1.0590288 | CW36: =Inputs!AF36 -> 1.1036 | CX36: 1.0342102 | CY36: 1.0777843 | CZ36: 1.1160608 | DA36: =Inputs!AG36 -> 1.0434697 | DB36: 1.0713899 | DC36: 1.1759942 | DD36: 1.1722434 | DE36: 1.1772681 | DF36: 1.1518 | DG36: 1.1417 | DH36: 1.1647614 | DI36: 1.16 | DJ36: 1.1562603 | DK36: 1.1533573 | DL36: 1.1512739 | DM36: 1.15 | DN36: 1.1494593 | DO36: 1.1494328 | DP36: 1.149692 | DQ36: 1.15 | DR36: 1.1501632 | DS36: 1.1501883 | DT36: 1.1501182 | DU36: 1.15 | DV36: 1.149884 | DW36: 1.1498127 | DX36: 1.149835 | DY36: 1.15 | DZ36: =(EC36-DY36)/4+DY36 -> 1.149969 | EA36: =(EC36-DY36)/4*2+DY36 -> 1.149938 | EB36: =(EC36-DY36)/4*3+DY36 -> 1.149907 | EC36: =Inputs!AN36 -> 1.1498759 | ED36: =(EG36-EC36)/4+EC36 -> 1.1498759 | EE36: =(EG36-EC36)/4*2+EC36 -> 1.1498759 | EF36: =(EG36-EC36)/4*3+EC36 -> 1.1498759 | EG36: =Inputs!AO36 -> 1.1498759 | EH36: =(EK36-EG36)/4+EG36 -> 1.1498759 | EI36: =(EK36-EG36)/4*2+EG36 -> 1.1498759 | EJ36: =(EK36-EG36)/4*3+EG36 -> 1.1498759 | EK36: =Inputs!AP36 -> 1.1498759 | EL36: =(EO36-EK36)/4+EK36 -> 1.1498759 | EM36: =(EO36-EK36)/4*2+EK36 -> 1.1498759 | EN36: =(EO36-EK36)/4*3+EK36 -> 1.1498759 | EO36: =Inputs!AQ36 -> 1.1498759 | EP36: =(ES36-EO36)/4+EO36 -> 1.1498759 | EQ36: =(ES36-EO36)/4*2+EO36 -> 1.1498759 | ER36: =(ES36-EO36)/4*3+EO36 -> 1.1498759 | ES36: =Inputs!AR36 -> 1.1498759 | ET36: =(EW36-ES36)/4+ES36 -> 1.1498759 | EU36: =(EW36-ES36)/4*2+ES36 -> 1.1498759 | EV36: =(EW36-ES36)/4*3+ES36 -> 1.1498759 | EW36: =Inputs!AS36 -> 1.1498759 | EX36: =(FA36-EW36)/4+EW36 -> 1.1498759 | EY36: =(FA36-EW36)/4*2+EW36 -> 1.1498759 | EZ36: =(FA36-EW36)/4*3+EW36 -> 1.1498759 | FA36: =Inputs!AT36 -> 1.1498759 | FB36: =(FE36-FA36)/4+FA36 -> 1.1498759 | FC36: =(FE36-FA36)/4*2+FA36 -> 1.1498759 | FD36: =(FE36-FA36)/4*3+FA36 -> 1.1498759 | FE36: =Inputs!AU36 -> 1.1498759 | FF36: =(FI36-FE36)/4+FE36 -> 1.1498759 | FG36: =(FI36-FE36)/4*2+FE36 -> 1.1498759 | FH36: =(FI36-FE36)/4*3+FE36 -> 1.1498759 | FI36: =Inputs!AV36 -> 1.1498759 | FJ36: =(FM36-FI36)/4+FI36 -> 1.1498759 | FK36: =(FM36-FI36)/4*2+FI36 -> 1.1498759 | FL36: =(FM36-FI36)/4*3+FI36 -> 1.1498759 | FM36: =Inputs!AW36 -> 1.1498759 | FN36: =(FQ36-FM36)/4+FM36 -> 1.1498759 | FO36: =(FQ36-FM36)/4*2+FM36 -> 1.1498759 | FP36: =(FQ36-FM36)/4*3+FM36 -> 1.1498759 | FQ36: =Inputs!AX36 -> 1.1498759 | FR36: =(FU36-FQ36)/4+FQ36 -> 1.1498759 | FS36: =(FU36-FQ36)/4*2+FQ36 -> 1.1498759 | FT36: =(FU36-FQ36)/4*3+FQ36 -> 1.1498759 | FU36: =Inputs!AY36 -> 1.1498759 | FV36: =(FY36-FU36)/4+FU36 -> 1.1498759 | FW36: =(FY36-FU36)/4*2+FU36 -> 1.1498759 | FX36: =(FY36-FU36)/4*3+FU36 -> 1.1498759 | FY36: =Inputs!AZ36 -> 1.1498759 | FZ36: =(GC36-FY36)/4+FY36 -> 1.1498759 | GA36: =(GC36-FY36)/4*2+FY36 -> 1.1498759 | GB36: =(GC36-FY36)/4*3+FY36 -> 1.1498759 | GC36: =Inputs!BA36 -> 1.1498759 | GD36: =(GG36-GC36)/4+GC36 -> 1.1498759 | GE36: =(GG36-GC36)/4*2+GC36 -> 1.1498759 | GF36: =(GG36-GC36)/4*3+GC36 -> 1.1498759 | GG36: =Inputs!BB36 -> 1.1498759 | GH36: =(GK36-GG36)/4+GG36 -> 1.1498759 | GI36: =(GK36-GG36)/4*2+GG36 -> 1.1498759 | GJ36: =(GK36-GG36)/4*3+GG36 -> 1.1498759 | GK36: =Inputs!BC36 -> 1.1498759 | GL36: =(GO36-GK36)/4+GK36 -> 1.1498759 | GM36: =(GO36-GK36)/4*2+GK36 -> 1.1498759 | GN36: =(GO36-GK36)/4*3+GK36 -> 1.1498759 | GO36: =Inputs!BD36 -> 1.1498759 | GP36: =(GS36-GO36)/4+GO36 -> 1.1498759 | GQ36: =(GS36-GO36)/4*2+GO36 -> 1.1498759 | GR36: =(GS36-GO36)/4*3+GO36 -> 1.1498759 | GS36: =Inputs!BE36 -> 1.1498759 | GT36: =(GW36-GS36)/4+GS36 -> 1.1498759 | GU36: =(GW36-GS36)/4*2+GS36 -> 1.1498759 | GV36: =(GW36-GS36)/4*3+GS36 -> 1.1498759 | GW36: =Inputs!BF36 -> 1.1498759 | GX36: =(HA36-GW36)/4+GW36 -> 1.1498759 | GY36: =(HA36-GW36)/4*2+GW36 -> 1.1498759 | GZ36: =(HA36-GW36)/4*3+GW36 -> 1.1498759 | HA36: =Inputs!BG36 -> 1.1498759
